Workbook
Name 日期清單: 月報表!$A$118:$A$148

Sheet 月報表
A1: 115 年 4 月 份 報 表
A5: 營業額 | D5: - 變動成本 | G5: - 固定成本 | J5: = 本月淨利 | M5: - 本月攤提10% | O5: = 本月實拿
A7: =C18 -> 93582 | D7: =G26 -> 22111.236 | G7: =G47 -> 96280.81 | J7: =A7-D7-G7 -> -24810.046 | M7: =J7/10 -> -2481.0046 | O7: =J7-M7 -> -22329.041
A11: 財務月報表 | J11: 產品數據月報表
A15: 營收概況 | K15: 產品類別 | L15: 銷售量 | M15: 售價 | N15: 成本 | O15: 毛利 | P15: 毛利率 | Q15: 烘焙耗損率 | R15: 營業額
A16: 本月營業總額 | C16: 本月營業淨額 | G16: 金流 | J16: 綜合禮盒 | K16: 禮盒 | L16: =SUM('1:31'!T19) -> 231 | M16: 360 | N16: =SUM(D25:D28)+D30+D31+((D32+D33)*4) -> 58.905 | O16: =M16-N16 -> 301.095 | P16: =O16/M16 -> 0.836375 | R16: =L16*M16 -> 83160 | S16: 禮盒 | T16: =SUM(L16:L20) -> 264
A17: =SUM('1:31'!R10:S10) -> 98538 | J17: 原味禮盒 | K17: 禮盒 | L17: =SUM('1:31'!T20) -> 12 | M17: 360 | N17: =SUM(D25,D32,D33)*4+D30+D31 -> 54.831 | O17: =M17-N17 -> 305.169 | P17: =O17/M17 -> 0.84769167 | R17: =L17*M17 -> 4320 | S17: 單售 | T17: =SUM(L21:L24) -> 22
C18: =A17-B20-B21 -> 93582 | G18: 類別 | H18: 金額 | J18: 可可禮盒 | K18: 禮盒 | L18: =SUM('1:31'!T21) -> 7 | M18: 360 | N18: =SUM(D26,D32,D33)*4+D30+D31 -> 61.515 | O18: =M18-N18 -> 298.485 | P18: =O18/M18 -> 0.829125 | R18: =L18*M18 -> 2520
A19: 獲客成本 | G19: 匯款 | H19: =SUM('1:31'!U13) -> 41360 | J19: 伯爵禮盒 | K19: 禮盒 | L19: =SUM('1:31'!T22) -> 10 | M19: 360 | N19: =SUM(D27,D32,D33)*4+D30+D31 -> 59.187 | O19: =M19-N19 -> 300.813 | P19: =O19/M19 -> 0.83559167 | R19: =L19*M19 -> 3600
A20: 折讓 | B20: =SUM('1:31'!U10:V10) -> 4236 | G20: 現金 | H20: =SUM('1:31'!U14) -> 5278 | J20: 抹茶禮盒 | K20: 禮盒 | L20: =SUM('1:31'!T23) -> 4 | M20: 360 | N20: =SUM(D28,D32,D33)*4+D30+D31 -> 60.087 | O20: =M20-N20 -> 299.913 | P20: =O20/M20 -> 0.83309167 | R20: =L20*M20 -> 1440
A21: 公關品價值 | B21: =SUM('1:31'!U11:V11) -> 720 | G21: 應收帳款 | H21: =INDEX('31'!Y12:Z13,1,1) -> 31984 | J21: 原味單顆 | K21: 單售 | L21: =SUM('1:31'!T24) -> 2 | M21: 90 | N21: =D25+D32+D33 -> 11.352 | O21: =M21-N21 -> 78.648 | P21: =O21/M21 -> 0.87386667 | Q21: =M73 -> 0.11815562 | R21: =L21*M21 -> 180
J22: 可可單顆 | K22: 單售 | L22: =SUM('1:31'!T25) -> 5 | M22: 90 | N22: =D26+D32+D33 -> 13.023 | O22: =M22-N22 -> 76.977 | P22: =O22/M22 -> 0.8553 | Q22: =M74 -> 0.023489933 | R22: =L22*M22 -> 450
A23: 營業變動成本 | J23: 伯爵單顆 | K23: 單售 | L23: =SUM('1:31'!T26) -> 7 | M23: 90 | N23: =D27+D32+D33 -> 12.441 | O23: =M23-N23 -> 77.559 | P23: =O23/M23 -> 0.86176667 | Q23: =M75 -> 0.057324841 | R23: =L23*M23 -> 630
A24: 食材成本 | C24: 本月銷售量 | D24: 單顆成本 | E24: 本月成本 | F24: 小計 | G24: 本月成本總計 | J24: 抹茶單顆 | K24: 單售 | L24: =SUM('1:31'!T27) -> 8 | M24: 90 | N24: =D28+D32+D33 -> 12.666 | O24: =M24-N24 -> 77.334 | P24: =O24/M24 -> 0.85926667 | Q24: =M76 -> 0.083044983 | R24: =L24*M24 -> 720
B25: 原味 | C25: =SUM(SUM('1:31'!T20)*4,'1:31'!T24,'1:31'!T19) -> 281 | D25: =[1]可麗露!$L$8 -> 9.752 | E25: =ROUND(D25*C25,3) -> 2740.312 | F25: =SUM(E25:E28) -> 11591.612
B26: 可可 | C26: =SUM(SUM('1:31'!T21)*4,'1:31'!T25,'1:31'!T19) -> 264 | D26: =[1]可麗露!$M$8 -> 11.423 | E26: =ROUND(D26*C26,3) -> 3015.672 | G26: =SUM(F25,F30,E36,F38) -> 22111.236 | J26: 產品銷售分布圖
B27: 伯爵 | C27: =SUM(SUM('1:31'!T22)*4,'1:31'!T26,'1:31'!T19) -> 278 | D27: =[1]可麗露!$N$8 -> 10.841 | E27: =ROUND(D27*C27,3) -> 3013.798
B28: 抹茶 | C28: =SUM(SUM('1:31'!T23)*4,'1:31'!T27,'1:31'!T19) -> 255 | D28: =[1]可麗露!$M$10 -> 11.066 | E28: =ROUND(D28*C28,3) -> 2821.83
A29: 包材成本 | C29: 本月使用量 | D29: 單份成本 | E29: 本月成本 | F29: 小計
B30: 禮盒 | C30: =SUM('1:31'!V19) -> 266 | D30: 6.423 | E30: =D30*C30 -> 1708.518 | F30: =SUM(E30:E33) -> 4231.318
B31: 小卡 | C31: =SUM('1:31'!V19) -> 266 | D31: 3 | E31: =D31*C31 -> 798
B32: 單顆包裝袋 | C32: =SUM(C25:C28) -> 1078 | D32: 1.1 | E32: =D32*C32 -> 1185.8
B33: 貼紙 | C33: =SUM(C25:C28) -> 1078 | D33: 0.5 | E33: =D33*C33 -> 539
B34: 膠帶
A35: 貨運成本 | C35: 物流運費 | D35: 物流包材 | E35: 小計
B36: 金額 | C36: =-SUM('1:31'!Y21) -> 4848 | D36: =SUM('1:31'!Y20:Z20) -> 40 | E36: =SUM(C36:D36) -> 4888
A37: 耗損成本 | C37: 本月耗損 | D37: 本月成本 | E37: 總耗損率 | F37: 小計
B38: 原味 | C38: =O60 -> 32 | D38: =C38*D25 -> 312.064 | E38: =SUM(O58:O64)/SUM(K73:K76) -> 0.12980769 | F38: =SUM(D38:D41) -> 1400.306
B39: 可可 | C39: =O60 -> 32 | D39: =C39*D26 -> 365.536
B40: 伯爵 | C40: =O62 -> 34 | D40: =C40*D27 -> 368.594 | J40: 毛利分析圖
B41: 抹茶 | C41: =O64 -> 32 | D41: =C41*D28 -> 354.112
A42: 毛利 | C42: =C18-G26 -> 71470.764 | E42: 毛利率 | G42: =C42/C18 -> 0.76372341
A44: 品牌行銷及固定支出
A45: 固定支出 | B45: 項目 | C45: 金額 | D45: 項目 | E45: 金額 | F45: 小計 | G45: 本月總計
B46: 房租 | C46: 34133 | D46: 設備維修 | F46: =SUM(SUM(C46:C50),SUM(E46:E50),SUM(D51:E52)) -> 49123
B47: 水電 | C47: 10000 | D47: 設備折舊 | G47: =F46+F54 -> 96280.81
B48: 網路 | D48: 會計 | E48: 2000
B49: 勞健保 | D49: 雜項
B50: 人事 | D50: 營業稅 | E50: 2000
B51: 訂閱費 | C51: 表單系統 | D51: 990
C52: 官網
A53: 行銷支出 | B53: 項目 | C53: 金額 | D53: 項目 | E53: 金額 | F53: 小計
B54: 人人 | C54: 47040 | D54: 廣告投放 | F54: =SUM(SUM(C54:C56),SUM(E54:E58)) -> 47157.81
B55: 商攝 | D55: 合作 | J55: 耗損類別分析
B56: 贈品 | D56: 市集成本
B57: 公關品 | C57: 食材成本 | D57: =('31'!AC41*月報表!D25)+('31'!AC42*月報表!D26)+('31'!AC43*D27)+('31'!AC44*D28) -> 86.164 | E57: =SUM(D57:D59) -> 117.81 | K57: 人為 | L57: 技術 | M57: 過期 | N57: 吃掉 | O57: 總數
C58: 包材成本 | D58: ='31'!AC39*SUM(月報表!D30:D31)+(SUM('31'!AC41:AC44)*SUM(D32:D33)) -> 31.646 | J58: 原味 | K58: {=SUMPRODUCT(SUMIFS(INDIRECT("'"&日期清單&"'!s40:s55"),INDIRECT("'"&日期清單&"'!R40:r55"),"原味",INDIRECT("'"&日期清單&"'!t40:T55"),"人為"))} -> 17 | L58: {=SUMPRODUCT(SUMIFS(INDIRECT("'"&日期清單&"'!s40:s55"),INDIRECT("'"&日期清單&"'!R40:r55"),"原味",INDIRECT("'"&日期清單&"'!t40:T55"),"技術"))} -> 41 | M58: {=SUMPRODUCT(SUMIFS(INDIRECT("'"&日期清單&"'!s40:s55"),INDIRECT("'"&日期清單&"'!R40:r55"),"原味",INDIRECT("'"&日期清單&"'!t40:T55"),"過期"))} -> 0 | N58: {=SUMPRODUCT(SUMIFS(INDIRECT("'"&日期清單&"'!s40:s55"),INDIRECT("'"&日期清單&"'!R40:r55"),"原味",INDIRECT("'"&日期清單&"'!t40:T55"),"吃掉"))} -> 6 | O58: =SUM(K58:N58) -> 64
C59: 運費 | D59: =SUM('1:31'!Y19) -> 0
J60: 可可 | K60: {=SUMPRODUCT(SUMIFS(INDIRECT("'"&日期清單&"'!s40:s55"),INDIRECT("'"&日期清單&"'!R40:r55"),"可可",INDIRECT("'"&日期清單&"'!t40:T55"),"人為"))} -> 20 | L60: {=SUMPRODUCT(SUMIFS(INDIRECT("'"&日期清單&"'!s40:s55"),INDIRECT("'"&日期清單&"'!R40:r55"),"可可",INDIRECT("'"&日期清單&"'!t40:T55"),"技術"))} -> 7 | M60: {=SUMPRODUCT(SUMIFS(INDIRECT("'"&日期清單&"'!s40:s55"),INDIRECT("'"&日期清單&"'!R40:r55"),"可可",INDIRECT("'"&日期清單&"'!t40:T55"),"過期"))} -> 0 | N60: {=SUMPRODUCT(SUMIFS(INDIRECT("'"&日期清單&"'!s40:s55"),INDIRECT("'"&日期清單&"'!R40:r55"),"可可",INDIRECT("'"&日期清單&"'!t40:T55"),"吃掉"))} -> 5 | O60: =SUM(K60:N60) -> 32
J62: 伯爵 | K62: {=SUMPRODUCT(SUMIFS(INDIRECT("'"&日期清單&"'!s40:s55"),INDIRECT("'"&日期清單&"'!R40:r55"),"伯爵",INDIRECT("'"&日期清單&"'!t40:T55"),"人為"))} -> 7 | L62: {=SUMPRODUCT(SUMIFS(INDIRECT("'"&日期清單&"'!s40:s55"),INDIRECT("'"&日期清單&"'!R40:r55"),"伯爵",INDIRECT("'"&日期清單&"'!t40:T55"),"技術"))} -> 18 | M62: {=SUMPRODUCT(SUMIFS(INDIRECT("'"&日期清單&"'!s40:s55"),INDIRECT("'"&日期清單&"'!R40:r55"),"伯爵",INDIRECT("'"&日期清單&"'!t40:T55"),"過期"))} -> 2 | N62: {=SUMPRODUCT(SUMIFS(INDIRECT("'"&日期清單&"'!s40:s55"),INDIRECT("'"&日期清單&"'!R40:r55"),"伯爵",INDIRECT("'"&日期清單&"'!t40:T55"),"吃掉"))} -> 7 | O62: =SUM(K62:N62) -> 34
J64: 抹茶 | K64: {=SUMPRODUCT(SUMIFS(INDIRECT("'"&日期清單&"'!s40:s55"),INDIRECT("'"&日期清單&"'!R40:r55"),"抹茶",INDIRECT("'"&日期清單&"'!t40:T55"),"人為"))} -> 7 | L64: {=SUMPRODUCT(SUMIFS(INDIRECT("'"&日期清單&"'!s40:s55"),INDIRECT("'"&日期清單&"'!R40:r55"),"抹茶",INDIRECT("'"&日期清單&"'!t40:T55"),"技術"))} -> 24 | M64: {=SUMPRODUCT(SUMIFS(INDIRECT("'"&日期清單&"'!s40:s55"),INDIRECT("'"&日期清單&"'!R40:r55"),"抹茶",INDIRECT("'"&日期清單&"'!t40:T55"),"過期"))} -> 0 | N64: {=SUMPRODUCT(SUMIFS(INDIRECT("'"&日期清單&"'!s40:s55"),INDIRECT("'"&日期清單&"'!R40:r55"),"抹茶",INDIRECT("'"&日期清單&"'!t40:T55"),"吃掉"))} -> 1 | O64: =SUM(K64:N64) -> 32
J66: 合計 | K66: =SUM(K58:K64) -> 51 | L66: =SUM(L58:L64) -> 90 | M66: =SUM(M58:M64) -> 2 | N66: =SUM(N58:N64) -> 19 | O66: =SUM(O58:O64) -> 162
J70: 產品烘焙耗損率
K72: 實際產量 | L72: 技術耗損 | M72: 烘焙耗損
J73: 原味 | K73: =SUM('1:31'!U33) -> 347 | L73: =L58 -> 41 | M73: =L73/K73 -> 0.11815562
J74: 可可 | K74: =SUM('1:31'!U34) -> 298 | L74: =L60 -> 7 | M74: =L74/K74 -> 0.023489933
J75: 伯爵 | K75: =SUM('1:31'!U35) -> 314 | L75: =L62 -> 18 | M75: =L75/K75 -> 0.057324841
J76: 抹茶 | K76: =SUM('1:31'!U36) -> 289 | L76: =L64 -> 24 | M76: =L76/K76 -> 0.083044983
A118: 1
A119: 2
A120: 3
A121: 4
A122: 5
A123: 6
A124: 7
A125: 8
A126: 9
A127: 10
A128: 11
A129: 12
... A148: 31

Sheet 1
A1: 日報表
A5: 銷售明細 | R5: 總結
A6: 類別 | B6: 禮盒 | G6: 單顆 | K6: 金額
A7: 購買人 | B7: 綜合 | C7: 原味 | D7: 可可 | E7: 伯爵 | F7: 抹茶 | G7: 原味. | H7: 可可. | I7: 伯爵. | J7: 抹茶. | K7: 金額 | L7: 運費 | M7: 折讓金額 | N7: 實收金額 | O7: 欄1 | P7: 備註
A8: 林淑君 | B8: 4 | K8: =SUM(SUM(B8:F8)*360,SUM(G8:J8)*90) -> 1440 | M8: 40 | N8: =K8+L8-M8 -> 1400 | O8: 匯款 | R8: 金流 | X8: 應收帳款 | AB8: 今日未結帳款清單 | AC8: 今日銷帳清單
A9: 林淑瑛 | B9: 11 | K9: =SUM(SUM(B9:F9)*360,SUM(G9:J9)*90) -> 3960 | M9: 360 | N9: =K9+L9-M9 -> 3600 | O9: 匯款 | R9: 營業總額 | T9: 運費 | U9: =SUMIF(表格1_3[欄1],"<>公關品",表格1_3[運費]) -> 160 | X9: 累積未結 | Y9: 0 | AB9: {=_xlfn.LET(_xlpm.unpaid,_xlfn.UNIQUE(_xlfn._xlws.FILTER(A8:A100,O8:O100="未結帳款","今日無欠款")),IF(_xlpm.unpaid="今日無欠款","今日無欠款",_xlpm.unpaid&"："&SUMIFS(N8:N100,A8:A100,_xlpm.unpaid,O8:O100,"未結帳款")))} -> 李泓陞：880 | AC9: {=_xlfn.LET(_xlpm.paid,_xlfn.UNIQUE(_xlfn._xlws.FILTER(A8:A100,P8:P100="銷帳","今日無銷帳")),IF(_xlpm.paid="今日無銷帳","今日無銷帳",_xlpm.paid&"："&SUMIFS(N8:N100,A8:A100,_xlpm.paid,P8:P100,"銷帳")))} -> 今日無銷帳
A10: 許仁芳 | B10: 4 | K10: =SUM(SUM(B10:F10)*360,SUM(G10:J10)*90) -> 1440 | N10: =K10+L10-M10 -> 1440 | O10: 匯款 | R10: =SUM(K8:K101)-V15 -> 9900 | T10: 折讓 | U10: =SUM(M8:M101) -> 780 | X10: 今日未結 | Y10: =U15 -> 880
A11: 張秀麗 | C11: 1 | D11: 1 | E11: 1 | F11: 1 | K11: =SUM(SUM(B11:F11)*360,SUM(G11:J11)*90) -> 1440 | N11: =K11+L11-M11 -> 1440 | O11: 匯款 | R11: 營業額 | T11: 公關品 | U11: =SUMIF(P8:P100,"公關品",K8:K103) -> 0 | X11: 今日回款 | Y11: =V15 -> 0
A12: 李泓陞 | B12: 2 | K12: =SUM(SUM(B12:F12)*360,SUM(G12:J12)*90) -> 720 | L12: 160 | N12: =K12+L12-M12 -> 880 | O12: 未結帳款 | R12: =R10-U10-U11 -> 9120 | T12: 應收 | V12: 實收 | X12: 剩餘未結 | Y12: =Y9+Y10-Y11 -> 880
A13: 路人 | J13: 2 | K13: =SUM(SUM(B13:F13)*360,SUM(G13:J13)*90) -> 180 | M13: 20 | N13: =K13+L13-M13 -> 160 | O13: 現金 | T13: 匯款 | U13: =SUMIF(O8:O101,"匯款",N8:N101) -> 8240
A14: 雲億 | B14: 1 | K14: =SUM(SUM(B14:F14)*360,SUM(G14:J14)*90) -> 360 | M14: 360 | N14: =K14+L14-M14 -> 0 | O14: 匯款 | T14: 現金 | U14: =SUMIF(O8:O102,"現金",N8:N102) -> 160
A15: 晏禎 | E15: 1 | K15: =SUM(SUM(B15:F15)*360,SUM(G15:J15)*90) -> 360 | N15: =K15+L15-M15 -> 360 | O15: 匯款 | T15: 未結帳款 | U15: =SUMIF(O8:O102,"未結帳款",N8:N103) -> 880 | V15: =SUMIF(P8:P100,"銷帳",N8:N100) -> 0
K16: =SUM(SUM(B16:F16)*360,SUM(G16:J16)*90) -> 0 | N16: =K16+L16-M16 -> 0 | T16: 銷帳 | X16: 物流
K17: =SUM(SUM(B17:F17)*360,SUM(G17:J17)*90) -> 0 | N17: =K17+L17-M17 -> 0 | R17: 商品銷售量 | X17: 運費實收 | Y17: =U9 -> 160
K18: =SUM(SUM(B18:F18)*360,SUM(G18:J18)*90) -> 0 | N18: =K18+L18-M18 -> 0 | T18: 販售量 | U18: 公關品 | V18: 總盒數 | X18: 運費實支 | Y18: 865
K19: =SUM(SUM(B19:F19)*360,SUM(G19:J19)*90) -> 0 | N19: =K19+L19-M19 -> 0 | R19: 禮盒 | S19: 綜合 | T19: =SUMIF(P8:P102,"<>公關品",B8:B100) -> 22 | U19: =SUMIF(P8:P102,"公關品",B8:B100) -> 0 | V19: =SUM(T19:T23,U19) -> 27 | X19: 公關運費 | Y19: =SUMIF(P8:P100,"公關品",L8:L100) -> 0
K20: =SUM(SUM(B20:F20)*360,SUM(G20:J20)*90) -> 0 | N20: =K20+L20-M20 -> 0 | S20: 原味 | T20: =SUMIF(P8:P102,"<>公關品",C8:C100) -> 1 | U20: =SUMIF(P8:P102,"公關品",C8:C100) -> 0 | V20: 總顆數 | X20: 物流包材 | Y20: =SUM(Z24:Z27) -> 0
K21: =SUM(SUM(B21:F21)*360,SUM(G21:J21)*90) -> 0 | N21: =K21+L21-M21 -> 0 | S21: 可可 | T21: =SUMIF(P8:P104,"<>公關品",D8:D102) -> 1 | U21: =SUMIF(P8:P102,"公關品",D8:D100) -> 0 | X21: 成本差額 | Y21: =Y17-Y18-Y20+Y19 -> -705
K22: =SUM(SUM(B22:F22)*360,SUM(G22:J22)*90) -> 0 | N22: =K22+L22-M22 -> 0 | S22: 伯爵 | T22: =SUMIF(P8:P102,"<>公關品",E8:E100) -> 2 | U22: =SUMIF(P8:P102,"公關品",E8:E100) -> 0 | X22: 物流包材
K23: =SUM(SUM(B23:F23)*360,SUM(G23:J23)*90) -> 0 | N23: =K23+L23-M23 -> 0 | S23: 抹茶 | T23: =SUMIF(P8:P102,"<>公關品",F8:F100) -> 1 | U23: =SUMIF(P8:P102,"公關品",F8:F100) -> 0 | X23: 種類 | Y23: 數量 | Z23: 總額
K24: =SUM(SUM(B24:F24)*360,SUM(G24:J24)*90) -> 0 | N24: =K24+L24-M24 -> 0 | R24: 單顆 | S24: 原味 | T24: =SUMIF(P9:P103,"<>公關品",G8:G100) -> 0 | U24: =SUMIF(P8:P102,"公關品",G8:G100) -> 0 | V24: =T19+(T20*4)+T24 -> 26 | X24: 2入紙箱
K25: =SUM(SUM(B25:F25)*360,SUM(G25:J25)*90) -> 0 | N25: =K25+L25-M25 -> 0 | S25: 可可 | T25: =SUMIF(P8:P102,"<>公關品",H8:H100) -> 0 | U25: =SUMIF(P8:P102,"公關品",I8:I100) -> 0 | V25: =T19+(T21*4)+T25 -> 26 | X25: 4入紙箱 | Z25: =Y25*5 -> 0
K26: =SUM(SUM(B26:F26)*360,SUM(G26:J26)*90) -> 0 | N26: =K26+L26-M26 -> 0 | S26: 伯爵 | T26: =SUMIF(P9:P103,"<>公關品",I8:I100) -> 0 | U26: =SUMIF(P8:P102,"公關品",I8:I100) -> 0 | V26: =T19+(T22*4)+T26 -> 30 | X26: 10入紙箱
K27: =SUM(SUM(B27:F27)*360,SUM(G27:J27)*90) -> 0 | N27: =K27+L27-M27 -> 0 | S27: 抹茶 | T27: =SUMIF(P8:P102,"<>公關品",J8:J100) -> 2 | U27: =SUMIF(P9:P103,"公關品",J8:J100) -> 0 | V27: =T19+(T23*4)+T27 -> 28 | X27: 膠帶
K28: =SUM(SUM(B28:F28)*360,SUM(G28:J28)*90) -> 0 | N28: =K28+L28-M28 -> 0
K29: =SUM(SUM(B29:F29)*360,SUM(G29:J29)*90) -> 0 | N29: =K29+L29-M29 -> 0
K30: =SUM(SUM(B30:F30)*360,SUM(G30:J30)*90) -> 0 | N30: =K30+L30-M30 -> 0 | R30: 產能及庫存 | AB30: 今日公關品總結
K31: =SUM(SUM(B31:F31)*360,SUM(G31:J31)*90) -> 0 | N31: =K31+L31-M31 -> 0 | AB31: 總禮盒數 | AC31: =SUM(U19:U23) -> 0
K32: =SUM(SUM(B32:F32)*360,SUM(G32:J32)*90) -> 0 | N32: =K32+L32-M32 -> 0 | R32: 品項 | S32: 原庫存 | T32: 預計產量 | U32: 實際產量 | V32: 耗損 | W32: 實際銷售量 | Y32: 今日庫存 | Z32: 總損耗率 | AB32: 總顆數 | AC32: =SUM(AC33:AC36) -> 0
K33: =SUM(SUM(B33:F33)*360,SUM(G33:J33)*90) -> 0 | N33: =K33+L33-M33 -> 0 | R33: 原味 | S33: 0 | T33: 32 | U33: 32 | V33: =SUMIF(R40:R55,"原味",S40:S55) -> 6 | W33: =V24+U24+U19+U20*4 -> 26 | Y33: =S33+U33-V33-W33 -> 0 | Z33: =V33/(U33+S33) -> 0.1875 | AB33: 原味 | AC33: =U24+U19+U20*4 -> 0
K34: =SUM(SUM(B34:F34)*360,SUM(G34:J34)*90) -> 0 | N34: =K34+L34-M34 -> 0 | R34: 可可 | S34: 0 | T34: 32 | U34: 32 | V34: =SUMIF(R41:R55,"可可",S41:S55) -> 6 | W34: =V25+U25+U19+U21*4 -> 26 | Y34: =S34+U34-V34-W34 -> 0 | Z34: =V34/(U34+S34) -> 0.1875 | AB34: 可可 | AC34: =U25+U19+U21*4 -> 0
K35: =SUM(SUM(B35:F35)*360,SUM(G35:J35)*90) -> 0 | N35: =K35+L35-M35 -> 0 | R35: 伯爵 | S35: 0 | T35: 32 | U35: 34 | V35: =SUMIF(R41:R55,"伯爵",S41:S55) -> 1 | W35: =V26+U26+U19+U22*4 -> 30 | Y35: =S35+U35-V35-W35 -> 3 | Z35: =V35/(U35+S35) -> 0.029411765 | AB35: 伯爵 | AC35: =U26+U19+U22*4 -> 0
K36: =SUM(SUM(B36:F36)*360,SUM(G36:J36)*90) -> 0 | N36: =K36+L36-M36 -> 0 | R36: 抹茶 | S36: 0 | T36: 32 | U36: 32 | V36: =SUMIF(R41:R55,"抹茶",S41:S55) -> 0 | W36: =V27+U27+U19+U23*4 -> 28 | Y36: =S36+U36-V36-W36 -> 4 | Z36: =V36/(U36+S36) -> 0 | AB36: 抹茶 | AC36: =U27+U19+U23*4 -> 0
K37: =SUM(SUM(B37:F37)*360,SUM(G37:J37)*90) -> 0 | N37: =K37+L37-M37 -> 0
K38: =SUM(SUM(B38:F38)*360,SUM(G38:J38)*90) -> 0 | N38: =K38+L38-M38 -> 0 | R38: 損耗原因
K39: =SUM(SUM(B39:F39)*360,SUM(G39:J39)*90) -> 0 | N39: =K39+L39-M39 -> 0
K40: =SUM(SUM(B40:F40)*360,SUM(G40:J40)*90) -> 0 | N40: =K40+L40-M40 -> 0 | R40: 品項 | S40: 數量 | T40: 類別 | U40: 原因
K41: =SUM(SUM(B41:F41)*360,SUM(G41:J41)*90) -> 0 | N41: =K41+L41-M41 -> 0 | R41: 原味 | S41: 6 | T41: 技術 | U41: 白頭
K42: =SUM(SUM(B42:F42)*360,SUM(G42:J42)*90) -> 0 | N42: =K42+L42-M42 -> 0 | R42: 可可 | S42: 6 | T42: 人為 | U42: 掉地上
K43: =SUM(SUM(B43:F43)*360,SUM(G43:J43)*90) -> 0 | N43: =K43+L43-M43 -> 0 | R43: 伯爵 | S43: 1 | T43: 技術 | U43: 白頭
K44: =SUM(SUM(B44:F44)*360,SUM(G44:J44)*90) -> 0 | N44: =K44+L44-M44 -> 0
K45: =SUM(SUM(B45:F45)*360,SUM(G45:J45)*90) -> 0 | N45: =K45+L45-M45 -> 0
K46: =SUM(SUM(B46:F46)*360,SUM(G46:J46)*90) -> 0 | N46: =K46+L46-M46 -> 0
K47: =SUM(SUM(B47:F47)*360,SUM(G47:J47)*90) -> 0 | N47: =K47+L47-M47 -> 0
K48: =SUM(SUM(B48:F48)*360,SUM(G48:J48)*90) -> 0 | N48: =K48+L48-M48 -> 0
K49: =SUM(SUM(B49:F49)*360,SUM(G49:J49)*90) -> 0 | N49: =K49+L49-M49 -> 0
K50: =SUM(SUM(B50:F50)*360,SUM(G50:J50)*90) -> 0 | N50: =K50+L50-M50 -> 0
K51: =SUM(SUM(B51:F51)*360,SUM(G51:J51)*90) -> 0 | N51: =K51+L51-M51 -> 0
K52: =SUM(SUM(B52:F52)*360,SUM(G52:J52)*90) -> 0 | N52: =K52+L52-M52 -> 0
K53: =SUM(SUM(B53:F53)*360,SUM(G53:J53)*90) -> 0 | N53: =K53+L53-M53 -> 0
K54: =SUM(SUM(B54:F54)*360,SUM(G54:J54)*90) -> 0 | N54: =K54+L54-M54 -> 0
K55: =SUM(SUM(B55:F55)*360,SUM(G55:J55)*90) -> 0 | N55: =K55+L55-M55 -> 0
K56: =SUM(SUM(B56:F56)*360,SUM(G56:J56)*90) -> 0 | N56: =K56+L56-M56 -> 0
K57: =SUM(SUM(B57:F57)*360,SUM(G57:J57)*90) -> 0 | N57: =K57+L57-M57 -> 0 | R57: 備註
K58: =SUM(SUM(B58:F58)*360,SUM(G58:J58)*90) -> 0 | N58: =K58+L58-M58 -> 0
K59: =SUM(SUM(B59:F59)*360,SUM(G59:J59)*90) -> 0 | N59: =K59+L59-M59 -> 0
K60: =SUM(SUM(B60:F60)*360,SUM(G60:J60)*90) -> 0 | N60: =K60+L60-M60 -> 0
K61: =SUM(SUM(B61:F61)*360,SUM(G61:J61)*90) -> 0 | N61: =K61+L61-M61 -> 0
K62: =SUM(SUM(B62:F62)*360,SUM(G62:J62)*90) -> 0 | N62: =K62+L62-M62 -> 0
K63: =SUM(SUM(B63:F63)*360,SUM(G63:J63)*90) -> 0 | N63: =K63+L63-M63 -> 0
K64: =SUM(SUM(B64:F64)*360,SUM(G64:J64)*90) -> 0 | N64: =K64+L64-M64 -> 0
K65: =SUM(SUM(B65:F65)*360,SUM(G65:J65)*90) -> 0 | N65: =K65+L65-M65 -> 0
K66: =SUM(SUM(B66:F66)*360,SUM(G66:J66)*90) -> 0 | N66: =K66+L66-M66 -> 0
K67: =SUM(SUM(B67:F67)*360,SUM(G67:J67)*90) -> 0 | N67: =K67+L67-M67 -> 0
K68: =SUM(SUM(B68:F68)*360,SUM(G68:J68)*90) -> 0 | N68: =K68+L68-M68 -> 0
K69: =SUM(SUM(B69:F69)*360,SUM(G69:J69)*90) -> 0 | N69: =K69+L69-M69 -> 0
... K101: =SUM(SUM(B101:F101)*360,SUM(G101:J101)*90) -> 0 | N101: =K101+L101-M101 -> 0

Sheet 2
A1: 日報表
A5: 銷售明細 | R5: 總結
A6: 類別 | B6: 禮盒 | G6: 單顆 | K6: 金額
A7: 購買人 | B7: 綜合 | C7: 原味 | D7: 可可 | E7: 伯爵 | F7: 抹茶 | G7: 原味. | H7: 可可. | I7: 伯爵. | J7: 抹茶. | K7: 金額 | L7: 運費 | M7: 折讓金額 | N7: 實收金額 | O7: 欄1 | P7: 備註
A8: 吳明新 | B8: 3 | K8: =SUM(SUM(B8:F8)*360,SUM(G8:J8)*90) -> 1080 | L8: 0 | N8: =K8+L8-M8 -> 1080 | O8: 匯款 | R8: 金流 | X8: 應收帳款 | AB8: 今日未結帳款清單 | AC8: 今日銷帳清單
A9: 林士娟 | B9: 13 | C9: 1 | D9: 1 | E9: 1 | K9: =SUM(SUM(B9:F9)*360,SUM(G9:J9)*90) -> 5760 | M9: 576 | N9: =K9+L9-M9 -> 5184 | O9: 未結帳款 | P9: 9折 | R9: 營業總額 | T9: 運費 | U9: =SUMIF(表格1_33479[欄1],"<>公關品",表格1_33479[運費]) -> 0 | X9: 累積未結 | Y9: =INDEX('1'!Y12:Z13,1,1) -> 880 | AB9: {=_xlfn.LET(_xlpm.unpaid,_xlfn.UNIQUE(_xlfn._xlws.FILTER(A8:A100,O8:O100="未結帳款","今日無欠款")),IF(_xlpm.unpaid="今日無欠款","今日無欠款",_xlpm.unpaid&"："&SUMIFS(N8:N100,A8:A100,_xlpm.unpaid,O8:O100,"未結帳款")))} -> 林士娟：5184 | AC9: {=_xlfn.LET(_xlpm.paid,_xlfn.UNIQUE(_xlfn._xlws.FILTER(A8:A100,P8:P100="銷帳","今日無銷帳")),IF(_xlpm.paid="今日無銷帳","今日無銷帳",_xlpm.paid&"："&SUMIFS(N8:N100,A8:A100,_xlpm.paid,P8:P100,"銷帳")))} -> 今日無銷帳
A10: 黃薇芸 | B10: 4 | K10: =SUM(SUM(B10:F10)*360,SUM(G10:J10)*90) -> 1440 | N10: =K10+L10-M10 -> 1440 | O10: 現金 | R10: =SUM(K8:K101)-V15 -> 11880 | T10: 折讓 | U10: =SUM(M8:M101) -> 576 | X10: 今日未結 | Y10: =U15 -> 5184
A11: 威森家具 | B11: 2 | K11: =SUM(SUM(B11:F11)*360,SUM(G11:J11)*90) -> 720 | N11: =K11+L11-M11 -> 720 | O11: 現金 | R11: 營業額 | T11: 公關品 | U11: =SUMIF(P8:P100,"公關品",K8:K103) -> 0 | X11: 今日回款 | Y11: =V15 -> 0
A12: 吳張秀茶 | B12: 8 | K12: =SUM(SUM(B12:F12)*360,SUM(G12:J12)*90) -> 2880 | L12: 0 | N12: =K12+L12-M12 -> 2880 | O12: 匯款 | R12: =R10-U10-U11 -> 11304 | T12: 應收 | V12: 實收 | X12: 剩餘未結 | Y12: =Y9+Y10-Y11 -> 6064
K13: =SUM(SUM(B13:F13)*360,SUM(G13:J13)*90) -> 0 | N13: =K13+L13-M13 -> 0 | T13: 匯款 | U13: =SUMIF(O8:O101,"匯款",N8:N101) -> 3960
K14: =SUM(SUM(B14:F14)*360,SUM(G14:J14)*90) -> 0 | N14: =K14+L14-M14 -> 0 | T14: 現金 | U14: =SUMIF(O8:O102,"現金",N8:N102) -> 2160
K15: =SUM(SUM(B15:F15)*360,SUM(G15:J15)*90) -> 0 | N15: =K15+L15-M15 -> 0 | T15: 未結帳款 | U15: =SUMIF(O8:O102,"未結帳款",N8:N103) -> 5184 | V15: =SUMIF(P8:P100,"銷帳",N8:N100) -> 0
K16: =SUM(SUM(B16:F16)*360,SUM(G16:J16)*90) -> 0 | N16: =K16+L16-M16 -> 0 | T16: 銷帳 | X16: 物流
K17: =SUM(SUM(B17:F17)*360,SUM(G17:J17)*90) -> 0 | N17: =K17+L17-M17 -> 0 | R17: 商品銷售量 | X17: 運費實收 | Y17: =U9 -> 0
K18: =SUM(SUM(B18:F18)*360,SUM(G18:J18)*90) -> 0 | N18: =K18+L18-M18 -> 0 | T18: 販售量 | U18: 公關品 | V18: 總盒數 | X18: 運費實支
K19: =SUM(SUM(B19:F19)*360,SUM(G19:J19)*90) -> 0 | N19: =K19+L19-M19 -> 0 | R19: 禮盒 | S19: 綜合 | T19: =SUMIF(P8:P102,"<>公關品",B8:B100) -> 30 | U19: =SUMIF(P8:P102,"公關品",B8:B100) -> 0 | V19: =SUM(T19:T23,U19) -> 33 | X19: 公關運費 | Y19: =SUMIF(P8:P100,"公關品",L8:L100) -> 0
K20: =SUM(SUM(B20:F20)*360,SUM(G20:J20)*90) -> 0 | N20: =K20+L20-M20 -> 0 | S20: 原味 | T20: =SUMIF(P8:P102,"<>公關品",C8:C100) -> 1 | U20: =SUMIF(P8:P102,"公關品",C8:C100) -> 0 | V20: 總顆數 | X20: 物流包材 | Y20: =SUM(Z24:Z27) -> 0
K21: =SUM(SUM(B21:F21)*360,SUM(G21:J21)*90) -> 0 | N21: =K21+L21-M21 -> 0 | S21: 可可 | T21: =SUMIF(P8:P104,"<>公關品",D8:D102) -> 1 | U21: =SUMIF(P8:P102,"公關品",D8:D100) -> 0 | X21: 成本差額 | Y21: =Y17-Y18-Y20+Y19 -> 0
K22: =SUM(SUM(B22:F22)*360,SUM(G22:J22)*90) -> 0 | N22: =K22+L22-M22 -> 0 | S22: 伯爵 | T22: =SUMIF(P8:P102,"<>公關品",E8:E100) -> 1 | U22: =SUMIF(P8:P102,"公關品",E8:E100) -> 0 | X22: 物流包材
K23: =SUM(SUM(B23:F23)*360,SUM(G23:J23)*90) -> 0 | N23: =K23+L23-M23 -> 0 | S23: 抹茶 | T23: =SUMIF(P8:P102,"<>公關品",F8:F100) -> 0 | U23: =SUMIF(P8:P102,"公關品",F8:F100) -> 0 | X23: 種類 | Y23: 數量 | Z23: 總額
K24: =SUM(SUM(B24:F24)*360,SUM(G24:J24)*90) -> 0 | N24: =K24+L24-M24 -> 0 | R24: 單顆 | S24: 原味 | T24: =SUMIF(P9:P103,"<>公關品",G8:G100) -> 0 | U24: =SUMIF(P8:P102,"公關品",G8:G100) -> 0 | V24: =T19+(T20*4)+T24 -> 34 | X24: 2入紙箱
K25: =SUM(SUM(B25:F25)*360,SUM(G25:J25)*90) -> 0 | N25: =K25+L25-M25 -> 0 | S25: 可可 | T25: =SUMIF(P8:P102,"<>公關品",H8:H100) -> 0 | U25: =SUMIF(P8:P102,"公關品",I8:I100) -> 0 | V25: =T19+(T21*4)+T25 -> 34 | X25: 4入紙箱 | Z25: =Y25*5 -> 0
K26: =SUM(SUM(B26:F26)*360,SUM(G26:J26)*90) -> 0 | N26: =K26+L26-M26 -> 0 | S26: 伯爵 | T26: =SUMIF(P9:P103,"<>公關品",I8:I100) -> 0 | U26: =SUMIF(P8:P102,"公關品",I8:I100) -> 0 | V26: =T19+(T22*4)+T26 -> 34 | X26: 10入紙箱
K27: =SUM(SUM(B27:F27)*360,SUM(G27:J27)*90) -> 0 | N27: =K27+L27-M27 -> 0 | S27: 抹茶 | T27: =SUMIF(P8:P102,"<>公關品",J8:J100) -> 0 | U27: =SUMIF(P9:P103,"公關品",J8:J100) -> 0 | V27: =T19+(T23*4)+T27 -> 30 | X27: 膠帶
K28: =SUM(SUM(B28:F28)*360,SUM(G28:J28)*90) -> 0 | N28: =K28+L28-M28 -> 0
K29: =SUM(SUM(B29:F29)*360,SUM(G29:J29)*90) -> 0 | N29: =K29+L29-M29 -> 0
K30: =SUM(SUM(B30:F30)*360,SUM(G30:J30)*90) -> 0 | N30: =K30+L30-M30 -> 0 | R30: 產能及庫存 | AB30: 今日公關品總結
K31: =SUM(SUM(B31:F31)*360,SUM(G31:J31)*90) -> 0 | N31: =K31+L31-M31 -> 0 | AB31: 總禮盒數 | AC31: =SUM(U19:U23) -> 0
K32: =SUM(SUM(B32:F32)*360,SUM(G32:J32)*90) -> 0 | N32: =K32+L32-M32 -> 0 | R32: 品項 | S32: 原庫存 | T32: 預計產量 | U32: 實際產量 | V32: 耗損 | W32: 實際銷售量 | Y32: 今日庫存 | Z32: 總損耗率 | AB32: 總顆數 | AC32: =SUM(AC33:AC36) -> 0
K33: =SUM(SUM(B33:F33)*360,SUM(G33:J33)*90) -> 0 | N33: =K33+L33-M33 -> 0 | R33: 原味 | S33: ='1'!Y33 -> 0 | T33: 48 | U33: 47 | V33: =SUMIF(R40:R55,"原味",S40:S55) -> 6 | W33: =V24+U24+U19+U20*4 -> 34 | Y33: =S33+U33-V33-W33 -> 7 | Z33: =IFERROR((V33/(U33+S33))," ") -> 0.12765957 | AB33: 原味 | AC33: =U24+U19+U20*4 -> 0
K34: =SUM(SUM(B34:F34)*360,SUM(G34:J34)*90) -> 0 | N34: =K34+L34-M34 -> 0 | R34: 可可 | S34: ='1'!Y34 -> 0 | T34: 48 | U34: 46 | V34: =SUMIF(R41:R55,"可可",S41:S55) -> 5 | W34: =V25+U25+U19+U21*4 -> 34 | Y34: =S34+U34-V34-W34 -> 7 | Z34: =IFERROR((V34/(U34+S34))," ") -> 0.10869565 | AB34: 可可 | AC34: =U25+U19+U21*4 -> 0
K35: =SUM(SUM(B35:F35)*360,SUM(G35:J35)*90) -> 0 | N35: =K35+L35-M35 -> 0 | R35: 伯爵 | S35: ='1'!Y35 -> 3 | T35: 48 | U35: 48 | V35: =SUMIF(R41:R55,"伯爵",S41:S55) -> 3 | W35: =V26+U26+U19+U22*4 -> 34 | Y35: =S35+U35-V35-W35 -> 14 | Z35: =IFERROR((V35/(U35+S35))," ") -> 0.058823529 | AB35: 伯爵 | AC35: =U26+U19+U22*4 -> 0
K36: =SUM(SUM(B36:F36)*360,SUM(G36:J36)*90) -> 0 | N36: =K36+L36-M36 -> 0 | R36: 抹茶 | S36: ='1'!Y36 -> 4 | T36: 34 | U36: 34 | V36: =SUMIF(R41:R55,"抹茶",S41:S55) -> 5 | W36: =V27+U27+U19+U23*4 -> 30 | Y36: =S36+U36-V36-W36 -> 3 | Z36: =IFERROR((V36/(U36+S36))," ") -> 0.13157895 | AB36: 抹茶 | AC36: =U27+U19+U23*4 -> 0
K37: =SUM(SUM(B37:F37)*360,SUM(G37:J37)*90) -> 0 | N37: =K37+L37-M37 -> 0
K38: =SUM(SUM(B38:F38)*360,SUM(G38:J38)*90) -> 0 | N38: =K38+L38-M38 -> 0 | R38: 損耗原因
K39: =SUM(SUM(B39:F39)*360,SUM(G39:J39)*90) -> 0 | N39: =K39+L39-M39 -> 0
K40: =SUM(SUM(B40:F40)*360,SUM(G40:J40)*90) -> 0 | N40: =K40+L40-M40 -> 0 | R40: 品項 | S40: 數量 | T40: 類別 | U40: 原因
K41: =SUM(SUM(B41:F41)*360,SUM(G41:J41)*90) -> 0 | N41: =K41+L41-M41 -> 0 | R41: 原味 | S41: 6 | T41: 技術
K42: =SUM(SUM(B42:F42)*360,SUM(G42:J42)*90) -> 0 | N42: =K42+L42-M42 -> 0 | R42: 伯爵 | S42: 3 | T42: 技術
K43: =SUM(SUM(B43:F43)*360,SUM(G43:J43)*90) -> 0 | N43: =K43+L43-M43 -> 0 | R43: 可可 | S43: 3 | T43: 技術
K44: =SUM(SUM(B44:F44)*360,SUM(G44:J44)*90) -> 0 | N44: =K44+L44-M44 -> 0 | R44: 可可 | S44: 2 | T44: 吃掉
K45: =SUM(SUM(B45:F45)*360,SUM(G45:J45)*90) -> 0 | N45: =K45+L45-M45 -> 0 | R45: 抹茶 | S45: 5 | T45: 技術
K46: =SUM(SUM(B46:F46)*360,SUM(G46:J46)*90) -> 0 | N46: =K46+L46-M46 -> 0
K47: =SUM(SUM(B47:F47)*360,SUM(G47:J47)*90) -> 0 | N47: =K47+L47-M47 -> 0
K48: =SUM(SUM(B48:F48)*360,SUM(G48:J48)*90) -> 0 | N48: =K48+L48-M48 -> 0
K49: =SUM(SUM(B49:F49)*360,SUM(G49:J49)*90) -> 0 | N49: =K49+L49-M49 -> 0
K50: =SUM(SUM(B50:F50)*360,SUM(G50:J50)*90) -> 0 | N50: =K50+L50-M50 -> 0
K51: =SUM(SUM(B51:F51)*360,SUM(G51:J51)*90) -> 0 | N51: =K51+L51-M51 -> 0
K52: =SUM(SUM(B52:F52)*360,SUM(G52:J52)*90) -> 0 | N52: =K52+L52-M52 -> 0
K53: =SUM(SUM(B53:F53)*360,SUM(G53:J53)*90) -> 0 | N53: =K53+L53-M53 -> 0
K54: =SUM(SUM(B54:F54)*360,SUM(G54:J54)*90) -> 0 | N54: =K54+L54-M54 -> 0
K55: =SUM(SUM(B55:F55)*360,SUM(G55:J55)*90) -> 0 | N55: =K55+L55-M55 -> 0
K56: =SUM(SUM(B56:F56)*360,SUM(G56:J56)*90) -> 0 | N56: =K56+L56-M56 -> 0
K57: =SUM(SUM(B57:F57)*360,SUM(G57:J57)*90) -> 0 | N57: =K57+L57-M57 -> 0 | R57: 備註
K58: =SUM(SUM(B58:F58)*360,SUM(G58:J58)*90) -> 0 | N58: =K58+L58-M58 -> 0
K59: =SUM(SUM(B59:F59)*360,SUM(G59:J59)*90) -> 0 | N59: =K59+L59-M59 -> 0
K60: =SUM(SUM(B60:F60)*360,SUM(G60:J60)*90) -> 0 | N60: =K60+L60-M60 -> 0
K61: =SUM(SUM(B61:F61)*360,SUM(G61:J61)*90) -> 0 | N61: =K61+L61-M61 -> 0
K62: =SUM(SUM(B62:F62)*360,SUM(G62:J62)*90) -> 0 | N62: =K62+L62-M62 -> 0
K63: =SUM(SUM(B63:F63)*360,SUM(G63:J63)*90) -> 0 | N63: =K63+L63-M63 -> 0
K64: =SUM(SUM(B64:F64)*360,SUM(G64:J64)*90) -> 0 | N64: =K64+L64-M64 -> 0
K65: =SUM(SUM(B65:F65)*360,SUM(G65:J65)*90) -> 0 | N65: =K65+L65-M65 -> 0
K66: =SUM(SUM(B66:F66)*360,SUM(G66:J66)*90) -> 0 | N66: =K66+L66-M66 -> 0
K67: =SUM(SUM(B67:F67)*360,SUM(G67:J67)*90) -> 0 | N67: =K67+L67-M67 -> 0
K68: =SUM(SUM(B68:F68)*360,SUM(G68:J68)*90) -> 0 | N68: =K68+L68-M68 -> 0
K69: =SUM(SUM(B69:F69)*360,SUM(G69:J69)*90) -> 0 | N69: =K69+L69-M69 -> 0
... K101: =SUM(SUM(B101:F101)*360,SUM(G101:J101)*90) -> 0 | N101: =K101+L101-M101 -> 0

Sheet 3
A1: 日報表
A5: 銷售明細 | R5: 總結
A6: 類別 | B6: 禮盒 | G6: 單顆 | K6: 金額
A7: 購買人 | B7: 綜合 | C7: 原味 | D7: 可可 | E7: 伯爵 | F7: 抹茶 | G7: 原味. | H7: 可可. | I7: 伯爵. | J7: 抹茶. | K7: 金額 | L7: 運費 | M7: 折讓金額 | N7: 實收金額 | O7: 欄1 | P7: 備註
A8: 威森家具 | B8: 1 | K8: =SUM(SUM(B8:F8)*360,SUM(G8:J8)*90) -> 360 | N8: =K8+L8-M8 -> 360 | O8: 現金 | R8: 金流 | X8: 應收帳款 | AB8: 今日未結帳款清單 | AC8: 今日銷帳清單
K9: =SUM(SUM(B9:F9)*360,SUM(G9:J9)*90) -> 0 | N9: =K9+L9-M9 -> 0 | P9: 公關品 | R9: 營業總額 | T9: 運費 | U9: =SUMIF(表格1_334[欄1],"<>公關品",表格1_334[運費]) -> 0 | X9: 累積未結 | Y9: =INDEX('2'!Y12:Z13,1,1) -> 6064 | AB9: {=_xlfn.LET(_xlpm.unpaid,_xlfn.UNIQUE(_xlfn._xlws.FILTER(A8:A100,O8:O100="未結帳款","今日無欠款")),IF(_xlpm.unpaid="今日無欠款","今日無欠款",_xlpm.unpaid&"："&SUMIFS(N8:N100,A8:A100,_xlpm.unpaid,O8:O100,"未結帳款")))} -> 林祥睿：1080 | AC9: {=_xlfn.LET(_xlpm.paid,_xlfn.UNIQUE(_xlfn._xlws.FILTER(A8:A100,P8:P100="銷帳","今日無銷帳")),IF(_xlpm.paid="今日無銷帳","今日無銷帳",_xlpm.paid&"："&SUMIFS(N8:N100,A8:A100,_xlpm.paid,P8:P100,"銷帳")))} -> 今日無銷帳
A10: 林祥睿 | C10: 1 | D10: 1 | E10: 1 | K10: =SUM(SUM(B10:F10)*360,SUM(G10:J10)*90) -> 1080 | N10: =K10+L10-M10 -> 1080 | O10: 未結帳款 | R10: =SUM(K8:K101)-V15 -> 1440 | T10: 折讓 | U10: =SUM(M8:M101) -> 0 | X10: 今日未結 | Y10: =U15 -> 1080
K11: =SUM(SUM(B11:F11)*360,SUM(G11:J11)*90) -> 0 | N11: =K11+L11-M11 -> 0 | R11: 營業額 | T11: 公關品 | U11: =SUMIF(P8:P100,"公關品",K8:K103) -> 0 | X11: 今日回款 | Y11: =V15 -> 0
K12: =SUM(SUM(B12:F12)*360,SUM(G12:J12)*90) -> 0 | N12: =K12+L12-M12 -> 0 | R12: =R10-U10-U11 -> 1440 | T12: 應收 | V12: 實收 | X12: 剩餘未結 | Y12: =Y9+Y10-Y11 -> 7144
K13: =SUM(SUM(B13:F13)*360,SUM(G13:J13)*90) -> 0 | N13: =K13+L13-M13 -> 0 | T13: 匯款 | U13: =SUMIF(O8:O101,"匯款",N8:N101) -> 0
K14: =SUM(SUM(B14:F14)*360,SUM(G14:J14)*90) -> 0 | N14: =K14+L14-M14 -> 0 | T14: 現金 | U14: =SUMIF(O8:O102,"現金",N8:N102) -> 360
K15: =SUM(SUM(B15:F15)*360,SUM(G15:J15)*90) -> 0 | N15: =K15+L15-M15 -> 0 | T15: 未結帳款 | U15: =SUMIF(O8:O102,"未結帳款",N8:N103) -> 1080 | V15: =SUMIF(P8:P100,"銷帳",N8:N100) -> 0
K16: =SUM(SUM(B16:F16)*360,SUM(G16:J16)*90) -> 0 | N16: =K16+L16-M16 -> 0 | T16: 銷帳 | X16: 物流
K17: =SUM(SUM(B17:F17)*360,SUM(G17:J17)*90) -> 0 | N17: =K17+L17-M17 -> 0 | R17: 商品銷售量 | X17: 運費實收 | Y17: =U9 -> 0
K18: =SUM(SUM(B18:F18)*360,SUM(G18:J18)*90) -> 0 | N18: =K18+L18-M18 -> 0 | T18: 販售量 | U18: 公關品 | V18: 總盒數 | X18: 運費實支
K19: =SUM(SUM(B19:F19)*360,SUM(G19:J19)*90) -> 0 | N19: =K19+L19-M19 -> 0 | R19: 禮盒 | S19: 綜合 | T19: =SUMIF(P8:P102,"<>公關品",B8:B100) -> 1 | U19: =SUMIF(P8:P102,"公關品",B8:B100) -> 0 | V19: =SUM(T19:T23,U19) -> 4 | X19: 公關運費 | Y19: =SUMIF(P8:P100,"公關品",L8:L100) -> 0
K20: =SUM(SUM(B20:F20)*360,SUM(G20:J20)*90) -> 0 | N20: =K20+L20-M20 -> 0 | S20: 原味 | T20: =SUMIF(P8:P102,"<>公關品",C8:C100) -> 1 | U20: =SUMIF(P8:P102,"公關品",C8:C100) -> 0 | V20: 總顆數 | X20: 物流包材 | Y20: =SUM(Z24:Z27) -> 0
K21: =SUM(SUM(B21:F21)*360,SUM(G21:J21)*90) -> 0 | N21: =K21+L21-M21 -> 0 | S21: 可可 | T21: =SUMIF(P8:P104,"<>公關品",D8:D102) -> 1 | U21: =SUMIF(P8:P102,"公關品",D8:D100) -> 0 | X21: 成本差額 | Y21: =Y17-Y18-Y20+Y19 -> 0
K22: =SUM(SUM(B22:F22)*360,SUM(G22:J22)*90) -> 0 | N22: =K22+L22-M22 -> 0 | S22: 伯爵 | T22: =SUMIF(P8:P102,"<>公關品",E8:E100) -> 1 | U22: =SUMIF(P8:P102,"公關品",E8:E100) -> 0 | X22: 物流包材
K23: =SUM(SUM(B23:F23)*360,SUM(G23:J23)*90) -> 0 | N23: =K23+L23-M23 -> 0 | S23: 抹茶 | T23: =SUMIF(P8:P102,"<>公關品",F8:F100) -> 0 | U23: =SUMIF(P8:P102,"公關品",F8:F100) -> 0 | X23: 種類 | Y23: 數量 | Z23: 總額
K24: =SUM(SUM(B24:F24)*360,SUM(G24:J24)*90) -> 0 | N24: =K24+L24-M24 -> 0 | R24: 單顆 | S24: 原味 | T24: =SUMIF(P9:P103,"<>公關品",G8:G100) -> 0 | U24: =SUMIF(P8:P102,"公關品",G8:G100) -> 0 | V24: =T19+(T20*4)+T24 -> 5 | X24: 2入紙箱
K25: =SUM(SUM(B25:F25)*360,SUM(G25:J25)*90) -> 0 | N25: =K25+L25-M25 -> 0 | S25: 可可 | T25: =SUMIF(P8:P102,"<>公關品",H8:H100) -> 0 | U25: =SUMIF(P8:P102,"公關品",I8:I100) -> 0 | V25: =T19+(T21*4)+T25 -> 5 | X25: 4入紙箱 | Z25: =Y25*5 -> 0
K26: =SUM(SUM(B26:F26)*360,SUM(G26:J26)*90) -> 0 | N26: =K26+L26-M26 -> 0 | S26: 伯爵 | T26: =SUMIF(P9:P103,"<>公關品",I8:I100) -> 0 | U26: =SUMIF(P8:P102,"公關品",I8:I100) -> 0 | V26: =T19+(T22*4)+T26 -> 5 | X26: 10入紙箱
K27: =SUM(SUM(B27:F27)*360,SUM(G27:J27)*90) -> 0 | N27: =K27+L27-M27 -> 0 | S27: 抹茶 | T27: =SUMIF(P8:P102,"<>公關品",J8:J100) -> 0 | U27: =SUMIF(P9:P103,"公關品",J8:J100) -> 0 | V27: =T19+(T23*4)+T27 -> 1 | X27: 膠帶
K28: =SUM(SUM(B28:F28)*360,SUM(G28:J28)*90) -> 0 | N28: =K28+L28-M28 -> 0
K29: =SUM(SUM(B29:F29)*360,SUM(G29:J29)*90) -> 0 | N29: =K29+L29-M29 -> 0
K30: =SUM(SUM(B30:F30)*360,SUM(G30:J30)*90) -> 0 | N30: =K30+L30-M30 -> 0 | R30: 產能及庫存 | AB30: 今日公關品總結
K31: =SUM(SUM(B31:F31)*360,SUM(G31:J31)*90) -> 0 | N31: =K31+L31-M31 -> 0 | AB31: 總禮盒數 | AC31: =SUM(U19:U23) -> 0
K32: =SUM(SUM(B32:F32)*360,SUM(G32:J32)*90) -> 0 | N32: =K32+L32-M32 -> 0 | R32: 品項 | S32: 原庫存 | T32: 預計產量 | U32: 實際產量 | V32: 耗損 | W32: 實際銷售量 | Y32: 今日庫存 | Z32: 總損耗率 | AB32: 總顆數 | AC32: =SUM(AC33:AC36) -> 0
K33: =SUM(SUM(B33:F33)*360,SUM(G33:J33)*90) -> 0 | N33: =K33+L33-M33 -> 0 | R33: 原味 | S33: ='2'!Y33 -> 7 | U33: 0 | V33: =SUMIF(R40:R55,"原味",S40:S55) -> 0 | W33: =V24+U24+U19+U20*4 -> 5 | Y33: =S33+U33-V33-W33 -> 2 | Z33: =IFERROR((V33/(U33+S33))," ") -> 0 | AB33: 原味 | AC33: =U24+U19+U20*4 -> 0
K34: =SUM(SUM(B34:F34)*360,SUM(G34:J34)*90) -> 0 | N34: =K34+L34-M34 -> 0 | R34: 可可 | S34: ='2'!Y34 -> 7 | U34: 0 | V34: =SUMIF(R41:R55,"可可",S41:S55) -> 0 | W34: =V25+U25+U19+U21*4 -> 5 | Y34: =S34+U34-V34-W34 -> 2 | Z34: =IFERROR((V34/(U34+S34))," ") -> 0 | AB34: 可可 | AC34: =U25+U19+U21*4 -> 0
K35: =SUM(SUM(B35:F35)*360,SUM(G35:J35)*90) -> 0 | N35: =K35+L35-M35 -> 0 | R35: 伯爵 | S35: ='2'!Y35 -> 14 | T35: 0 | U35: 0 | V35: =SUMIF(R41:R55,"伯爵",S41:S55) -> 5 | W35: =V26+U26+U19+U22*4 -> 5 | Y35: =S35+U35-V35-W35 -> 4 | Z35: =IFERROR((V35/(U35+S35))," ") -> 0.35714286 | AB35: 伯爵 | AC35: =U26+U19+U22*4 -> 0
K36: =SUM(SUM(B36:F36)*360,SUM(G36:J36)*90) -> 0 | N36: =K36+L36-M36 -> 0 | R36: 抹茶 | S36: ='2'!Y36 -> 3 | T36: 0 | U36: 0 | V36: =SUMIF(R41:R55,"抹茶",S41:S55) -> 0 | W36: =V27+U27+U19+U23*4 -> 1 | Y36: =S36+U36-V36-W36 -> 2 | Z36: =IFERROR((V36/(U36+S36))," ") -> 0 | AB36: 抹茶 | AC36: =U27+U19+U23*4 -> 0
K37: =SUM(SUM(B37:F37)*360,SUM(G37:J37)*90) -> 0 | N37: =K37+L37-M37 -> 0
K38: =SUM(SUM(B38:F38)*360,SUM(G38:J38)*90) -> 0 | N38: =K38+L38-M38 -> 0 | R38: 損耗原因
K39: =SUM(SUM(B39:F39)*360,SUM(G39:J39)*90) -> 0 | N39: =K39+L39-M39 -> 0
K40: =SUM(SUM(B40:F40)*360,SUM(G40:J40)*90) -> 0 | N40: =K40+L40-M40 -> 0 | R40: 品項 | S40: 數量 | T40: 類別 | U40: 原因
K41: =SUM(SUM(B41:F41)*360,SUM(G41:J41)*90) -> 0 | N41: =K41+L41-M41 -> 0 | R41: 伯爵 | S41: 5 | T41: 吃掉
K42: =SUM(SUM(B42:F42)*360,SUM(G42:J42)*90) -> 0 | N42: =K42+L42-M42 -> 0
K43: =SUM(SUM(B43:F43)*360,SUM(G43:J43)*90) -> 0 | N43: =K43+L43-M43 -> 0
K44: =SUM(SUM(B44:F44)*360,SUM(G44:J44)*90) -> 0 | N44: =K44+L44-M44 -> 0
K45: =SUM(SUM(B45:F45)*360,SUM(G45:J45)*90) -> 0 | N45: =K45+L45-M45 -> 0
K46: =SUM(SUM(B46:F46)*360,SUM(G46:J46)*90) -> 0 | N46: =K46+L46-M46 -> 0
K47: =SUM(SUM(B47:F47)*360,SUM(G47:J47)*90) -> 0 | N47: =K47+L47-M47 -> 0
K48: =SUM(SUM(B48:F48)*360,SUM(G48:J48)*90) -> 0 | N48: =K48+L48-M48 -> 0
K49: =SUM(SUM(B49:F49)*360,SUM(G49:J49)*90) -> 0 | N49: =K49+L49-M49 -> 0
K50: =SUM(SUM(B50:F50)*360,SUM(G50:J50)*90) -> 0 | N50: =K50+L50-M50 -> 0
K51: =SUM(SUM(B51:F51)*360,SUM(G51:J51)*90) -> 0 | N51: =K51+L51-M51 -> 0
K52: =SUM(SUM(B52:F52)*360,SUM(G52:J52)*90) -> 0 | N52: =K52+L52-M52 -> 0
K53: =SUM(SUM(B53:F53)*360,SUM(G53:J53)*90) -> 0 | N53: =K53+L53-M53 -> 0
... K56: =SUM(SUM(B56:F56)*360,SUM(G56:J56)*90) -> 0 | N56: =K56+L56-M56 -> 0
K57: =SUM(SUM(B57:F57)*360,SUM(G57:J57)*90) -> 0 | N57: =K57+L57-M57 -> 0 | R57: 備註
K58: =SUM(SUM(B58:F58)*360,SUM(G58:J58)*90) -> 0 | N58: =K58+L58-M58 -> 0
K59: =SUM(SUM(B59:F59)*360,SUM(G59:J59)*90) -> 0 | N59: =K59+L59-M59 -> 0
K60: =SUM(SUM(B60:F60)*360,SUM(G60:J60)*90) -> 0 | N60: =K60+L60-M60 -> 0
K61: =SUM(SUM(B61:F61)*360,SUM(G61:J61)*90) -> 0 | N61: =K61+L61-M61 -> 0
K62: =SUM(SUM(B62:F62)*360,SUM(G62:J62)*90) -> 0 | N62: =K62+L62-M62 -> 0
K63: =SUM(SUM(B63:F63)*360,SUM(G63:J63)*90) -> 0 | N63: =K63+L63-M63 -> 0
K64: =SUM(SUM(B64:F64)*360,SUM(G64:J64)*90) -> 0 | N64: =K64+L64-M64 -> 0
K65: =SUM(SUM(B65:F65)*360,SUM(G65:J65)*90) -> 0 | N65: =K65+L65-M65 -> 0
K66: =SUM(SUM(B66:F66)*360,SUM(G66:J66)*90) -> 0 | N66: =K66+L66-M66 -> 0
K67: =SUM(SUM(B67:F67)*360,SUM(G67:J67)*90) -> 0 | N67: =K67+L67-M67 -> 0
K68: =SUM(SUM(B68:F68)*360,SUM(G68:J68)*90) -> 0 | N68: =K68+L68-M68 -> 0
K69: =SUM(SUM(B69:F69)*360,SUM(G69:J69)*90) -> 0 | N69: =K69+L69-M69 -> 0
... K101: =SUM(SUM(B101:F101)*360,SUM(G101:J101)*90) -> 0 | N101: =K101+L101-M101 -> 0

Sheet 4
A1: 日報表
A5: 銷售明細 | R5: 總結
A6: 類別 | B6: 禮盒 | G6: 單顆 | K6: 金額
A7: 購買人 | B7: 綜合 | C7: 原味 | D7: 可可 | E7: 伯爵 | F7: 抹茶 | G7: 原味. | H7: 可可. | I7: 伯爵. | J7: 抹茶. | K7: 金額 | L7: 運費 | M7: 折讓金額 | N7: 實收金額 | O7: 欄1 | P7: 備註
A8: 林祥睿 | B8: 8 | K8: =SUM(SUM(B8:F8)*360,SUM(G8:J8)*90) -> 2880 | N8: =K8+L8-M8 -> 2880 | O8: 未結帳款 | R8: 金流 | X8: 應收帳款 | AB8: 今日未結帳款清單 | AC8: 今日銷帳清單
K9: =SUM(SUM(B9:F9)*360,SUM(G9:J9)*90) -> 0 | N9: =K9+L9-M9 -> 0 | R9: 營業總額 | T9: 運費 | U9: =SUMIF(表格1_33451[欄1],"<>公關品",表格1_33451[運費]) -> 0 | X9: 累積未結 | Y9: =INDEX('3'!Y12:Z13,1,1) -> 7144 | AB9: {=_xlfn.LET(_xlpm.unpaid,_xlfn.UNIQUE(_xlfn._xlws.FILTER(A8:A100,O8:O100="未結帳款","今日無欠款")),IF(_xlpm.unpaid="今日無欠款","今日無欠款",_xlpm.unpaid&"："&SUMIFS(N8:N100,A8:A100,_xlpm.unpaid,O8:O100,"未結帳款")))} -> 林祥睿：2880 | AC9: {=_xlfn.LET(_xlpm.paid,_xlfn.UNIQUE(_xlfn._xlws.FILTER(A8:A100,P8:P100="銷帳","今日無銷帳")),IF(_xlpm.paid="今日無銷帳","今日無銷帳",_xlpm.paid&"："&SUMIFS(N8:N100,A8:A100,_xlpm.paid,P8:P100,"銷帳")))} -> 今日無銷帳
K10: =SUM(SUM(B10:F10)*360,SUM(G10:J10)*90) -> 0 | N10: =K10+L10-M10 -> 0 | R10: =SUM(K8:K101)-V15 -> 2880 | T10: 折讓 | U10: =SUM(M8:M101) -> 0 | X10: 今日未結 | Y10: =U15 -> 2880
K11: =SUM(SUM(B11:F11)*360,SUM(G11:J11)*90) -> 0 | N11: =K11+L11-M11 -> 0 | R11: 營業額 | T11: 公關品 | U11: =SUMIF(P8:P100,"公關品",K8:K103) -> 0 | X11: 今日回款 | Y11: =V15 -> 0
K12: =SUM(SUM(B12:F12)*360,SUM(G12:J12)*90) -> 0 | N12: =K12+L12-M12 -> 0 | R12: =R10-U10-U11 -> 2880 | T12: 應收 | V12: 實收 | X12: 剩餘未結 | Y12: =Y9+Y10-Y11 -> 10024
K13: =SUM(SUM(B13:F13)*360,SUM(G13:J13)*90) -> 0 | N13: =K13+L13-M13 -> 0 | T13: 匯款 | U13: =SUMIF(O8:O101,"匯款",N8:N101) -> 0
K14: =SUM(SUM(B14:F14)*360,SUM(G14:J14)*90) -> 0 | N14: =K14+L14-M14 -> 0 | T14: 現金 | U14: =SUMIF(O8:O102,"現金",N8:N102) -> 0
K15: =SUM(SUM(B15:F15)*360,SUM(G15:J15)*90) -> 0 | N15: =K15+L15-M15 -> 0 | T15: 未結帳款 | U15: =SUMIF(O8:O102,"未結帳款",N8:N103) -> 2880 | V15: =SUMIF(P8:P100,"銷帳",N8:N100) -> 0
K16: =SUM(SUM(B16:F16)*360,SUM(G16:J16)*90) -> 0 | N16: =K16+L16-M16 -> 0 | T16: 銷帳 | X16: 物流
K17: =SUM(SUM(B17:F17)*360,SUM(G17:J17)*90) -> 0 | N17: =K17+L17-M17 -> 0 | R17: 商品銷售量 | X17: 運費實收 | Y17: =U9 -> 0
K18: =SUM(SUM(B18:F18)*360,SUM(G18:J18)*90) -> 0 | N18: =K18+L18-M18 -> 0 | T18: 販售量 | U18: 公關品 | V18: 總盒數 | X18: 運費實支
K19: =SUM(SUM(B19:F19)*360,SUM(G19:J19)*90) -> 0 | N19: =K19+L19-M19 -> 0 | R19: 禮盒 | S19: 綜合 | T19: =SUMIF(P8:P102,"<>公關品",B8:B100) -> 8 | U19: =SUMIF(P8:P102,"公關品",B8:B100) -> 0 | V19: =SUM(T19:T23,U19) -> 8 | X19: 公關運費 | Y19: =SUMIF(P8:P100,"公關品",L8:L100) -> 0
K20: =SUM(SUM(B20:F20)*360,SUM(G20:J20)*90) -> 0 | N20: =K20+L20-M20 -> 0 | S20: 原味 | T20: =SUMIF(P8:P102,"<>公關品",C8:C100) -> 0 | U20: =SUMIF(P8:P102,"公關品",C8:C100) -> 0 | V20: 總顆數 | X20: 物流包材 | Y20: =SUM(Z24:Z27) -> 0
K21: =SUM(SUM(B21:F21)*360,SUM(G21:J21)*90) -> 0 | N21: =K21+L21-M21 -> 0 | S21: 可可 | T21: =SUMIF(P8:P104,"<>公關品",D8:D102) -> 0 | U21: =SUMIF(P8:P102,"公關品",D8:D100) -> 0 | X21: 成本差額 | Y21: =Y17-Y18-Y20+Y19 -> 0
K22: =SUM(SUM(B22:F22)*360,SUM(G22:J22)*90) -> 0 | N22: =K22+L22-M22 -> 0 | S22: 伯爵 | T22: =SUMIF(P8:P102,"<>公關品",E8:E100) -> 0 | U22: =SUMIF(P8:P102,"公關品",E8:E100) -> 0 | X22: 物流包材
K23: =SUM(SUM(B23:F23)*360,SUM(G23:J23)*90) -> 0 | N23: =K23+L23-M23 -> 0 | S23: 抹茶 | T23: =SUMIF(P8:P102,"<>公關品",F8:F100) -> 0 | U23: =SUMIF(P8:P102,"公關品",F8:F100) -> 0 | X23: 種類 | Y23: 數量 | Z23: 總額
K24: =SUM(SUM(B24:F24)*360,SUM(G24:J24)*90) -> 0 | N24: =K24+L24-M24 -> 0 | R24: 單顆 | S24: 原味 | T24: =SUMIF(P9:P103,"<>公關品",G8:G100) -> 0 | U24: =SUMIF(P8:P102,"公關品",G8:G100) -> 0 | V24: =T19+(T20*4)+T24 -> 8 | X24: 2入紙箱
K25: =SUM(SUM(B25:F25)*360,SUM(G25:J25)*90) -> 0 | N25: =K25+L25-M25 -> 0 | S25: 可可 | T25: =SUMIF(P8:P102,"<>公關品",H8:H100) -> 0 | U25: =SUMIF(P8:P102,"公關品",I8:I100) -> 0 | V25: =T19+(T21*4)+T25 -> 8 | X25: 4入紙箱 | Z25: =Y25*5 -> 0
K26: =SUM(SUM(B26:F26)*360,SUM(G26:J26)*90) -> 0 | N26: =K26+L26-M26 -> 0 | S26: 伯爵 | T26: =SUMIF(P9:P103,"<>公關品",I8:I100) -> 0 | U26: =SUMIF(P8:P102,"公關品",I8:I100) -> 0 | V26: =T19+(T22*4)+T26 -> 8 | X26: 10入紙箱
K27: =SUM(SUM(B27:F27)*360,SUM(G27:J27)*90) -> 0 | N27: =K27+L27-M27 -> 0 | S27: 抹茶 | T27: =SUMIF(P8:P102,"<>公關品",J8:J100) -> 0 | U27: =SUMIF(P9:P103,"公關品",J8:J100) -> 0 | V27: =T19+(T23*4)+T27 -> 8 | X27: 膠帶
K28: =SUM(SUM(B28:F28)*360,SUM(G28:J28)*90) -> 0 | N28: =K28+L28-M28 -> 0
K29: =SUM(SUM(B29:F29)*360,SUM(G29:J29)*90) -> 0 | N29: =K29+L29-M29 -> 0
K30: =SUM(SUM(B30:F30)*360,SUM(G30:J30)*90) -> 0 | N30: =K30+L30-M30 -> 0 | R30: 產能及庫存 | AB30: 今日公關品總結
K31: =SUM(SUM(B31:F31)*360,SUM(G31:J31)*90) -> 0 | N31: =K31+L31-M31 -> 0 | AB31: 總禮盒數 | AC31: =SUM(U19:U23) -> 0
K32: =SUM(SUM(B32:F32)*360,SUM(G32:J32)*90) -> 0 | N32: =K32+L32-M32 -> 0 | R32: 品項 | S32: 原庫存 | T32: 預計產量 | U32: 實際產量 | V32: 耗損 | W32: 實際銷售量 | Y32: 今日庫存 | Z32: 總損耗率 | AB32: 總顆數 | AC32: =SUM(AC33:AC36) -> 0
K33: =SUM(SUM(B33:F33)*360,SUM(G33:J33)*90) -> 0 | N33: =K33+L33-M33 -> 0 | R33: 原味 | S33: ='3'!Y33 -> 2 | T33: 16 | U33: 17 | V33: =SUMIF(R40:R55,"原味",S40:S55) -> 1 | W33: =V24+U24+U19+U20*4 -> 8 | Y33: =S33+U33-V33-W33 -> 10 | Z33: =IFERROR((V33/(U33+S33))," ") -> 0.052631579 | AB33: 原味 | AC33: =U24+U19+U20*4 -> 0
K34: =SUM(SUM(B34:F34)*360,SUM(G34:J34)*90) -> 0 | N34: =K34+L34-M34 -> 0 | R34: 可可 | S34: ='3'!Y34 -> 2 | T34: 16 | U34: 16 | V34: =SUMIF(R41:R55,"可可",S41:S55) -> 0 | W34: =V25+U25+U19+U21*4 -> 8 | Y34: =S34+U34-V34-W34 -> 10 | Z34: =IFERROR((V34/(U34+S34))," ") -> 0 | AB34: 可可 | AC34: =U25+U19+U21*4 -> 0
K35: =SUM(SUM(B35:F35)*360,SUM(G35:J35)*90) -> 0 | N35: =K35+L35-M35 -> 0 | R35: 伯爵 | S35: ='3'!Y35 -> 4 | T35: 16 | U35: 17 | V35: =SUMIF(R41:R55,"伯爵",S41:S55) -> 0 | W35: =V26+U26+U19+U22*4 -> 8 | Y35: =S35+U35-V35-W35 -> 13 | Z35: =IFERROR((V35/(U35+S35))," ") -> 0 | AB35: 伯爵 | AC35: =U26+U19+U22*4 -> 0
K36: =SUM(SUM(B36:F36)*360,SUM(G36:J36)*90) -> 0 | N36: =K36+L36-M36 -> 0 | R36: 抹茶 | S36: ='3'!Y36 -> 2 | T36: 16 | U36: 17 | V36: =SUMIF(R41:R55,"抹茶",S41:S55) -> 0 | W36: =V27+U27+U19+U23*4 -> 8 | Y36: =S36+U36-V36-W36 -> 11 | Z36: =IFERROR((V36/(U36+S36))," ") -> 0 | AB36: 抹茶 | AC36: =U27+U19+U23*4 -> 0
K37: =SUM(SUM(B37:F37)*360,SUM(G37:J37)*90) -> 0 | N37: =K37+L37-M37 -> 0
K38: =SUM(SUM(B38:F38)*360,SUM(G38:J38)*90) -> 0 | N38: =K38+L38-M38 -> 0 | R38: 損耗原因
K39: =SUM(SUM(B39:F39)*360,SUM(G39:J39)*90) -> 0 | N39: =K39+L39-M39 -> 0
K40: =SUM(SUM(B40:F40)*360,SUM(G40:J40)*90) -> 0 | N40: =K40+L40-M40 -> 0 | R40: 品項 | S40: 數量 | T40: 類別 | U40: 原因
K41: =SUM(SUM(B41:F41)*360,SUM(G41:J41)*90) -> 0 | N41: =K41+L41-M41 -> 0 | R41: 原味 | S41: 1 | T41: 技術 | U41: 白頭
K42: =SUM(SUM(B42:F42)*360,SUM(G42:J42)*90) -> 0 | N42: =K42+L42-M42 -> 0
K43: =SUM(SUM(B43:F43)*360,SUM(G43:J43)*90) -> 0 | N43: =K43+L43-M43 -> 0
K44: =SUM(SUM(B44:F44)*360,SUM(G44:J44)*90) -> 0 | N44: =K44+L44-M44 -> 0
K45: =SUM(SUM(B45:F45)*360,SUM(G45:J45)*90) -> 0 | N45: =K45+L45-M45 -> 0
K46: =SUM(SUM(B46:F46)*360,SUM(G46:J46)*90) -> 0 | N46: =K46+L46-M46 -> 0
K47: =SUM(SUM(B47:F47)*360,SUM(G47:J47)*90) -> 0 | N47: =K47+L47-M47 -> 0
K48: =SUM(SUM(B48:F48)*360,SUM(G48:J48)*90) -> 0 | N48: =K48+L48-M48 -> 0
K49: =SUM(SUM(B49:F49)*360,SUM(G49:J49)*90) -> 0 | N49: =K49+L49-M49 -> 0
K50: =SUM(SUM(B50:F50)*360,SUM(G50:J50)*90) -> 0 | N50: =K50+L50-M50 -> 0
K51: =SUM(SUM(B51:F51)*360,SUM(G51:J51)*90) -> 0 | N51: =K51+L51-M51 -> 0
K52: =SUM(SUM(B52:F52)*360,SUM(G52:J52)*90) -> 0 | N52: =K52+L52-M52 -> 0
K53: =SUM(SUM(B53:F53)*360,SUM(G53:J53)*90) -> 0 | N53: =K53+L53-M53 -> 0
... K56: =SUM(SUM(B56:F56)*360,SUM(G56:J56)*90) -> 0 | N56: =K56+L56-M56 -> 0
K57: =SUM(SUM(B57:F57)*360,SUM(G57:J57)*90) -> 0 | N57: =K57+L57-M57 -> 0 | R57: 備註
K58: =SUM(SUM(B58:F58)*360,SUM(G58:J58)*90) -> 0 | N58: =K58+L58-M58 -> 0
K59: =SUM(SUM(B59:F59)*360,SUM(G59:J59)*90) -> 0 | N59: =K59+L59-M59 -> 0
K60: =SUM(SUM(B60:F60)*360,SUM(G60:J60)*90) -> 0 | N60: =K60+L60-M60 -> 0
K61: =SUM(SUM(B61:F61)*360,SUM(G61:J61)*90) -> 0 | N61: =K61+L61-M61 -> 0
K62: =SUM(SUM(B62:F62)*360,SUM(G62:J62)*90) -> 0 | N62: =K62+L62-M62 -> 0
K63: =SUM(SUM(B63:F63)*360,SUM(G63:J63)*90) -> 0 | N63: =K63+L63-M63 -> 0
K64: =SUM(SUM(B64:F64)*360,SUM(G64:J64)*90) -> 0 | N64: =K64+L64-M64 -> 0
K65: =SUM(SUM(B65:F65)*360,SUM(G65:J65)*90) -> 0 | N65: =K65+L65-M65 -> 0
K66: =SUM(SUM(B66:F66)*360,SUM(G66:J66)*90) -> 0 | N66: =K66+L66-M66 -> 0
K67: =SUM(SUM(B67:F67)*360,SUM(G67:J67)*90) -> 0 | N67: =K67+L67-M67 -> 0
K68: =SUM(SUM(B68:F68)*360,SUM(G68:J68)*90) -> 0 | N68: =K68+L68-M68 -> 0
K69: =SUM(SUM(B69:F69)*360,SUM(G69:J69)*90) -> 0 | N69: =K69+L69-M69 -> 0
... K101: =SUM(SUM(B101:F101)*360,SUM(G101:J101)*90) -> 0 | N101: =K101+L101-M101 -> 0

Sheet 5
A1: 日報表
A5: 銷售明細 | R5: 總結
A6: 類別 | B6: 禮盒 | G6: 單顆 | K6: 金額
A7: 購買人 | B7: 綜合 | C7: 原味 | D7: 可可 | E7: 伯爵 | F7: 抹茶 | G7: 原味. | H7: 可可. | I7: 伯爵. | J7: 抹茶. | K7: 金額 | L7: 運費 | M7: 折讓金額 | N7: 實收金額 | O7: 欄1 | P7: 備註
K8: =SUM(SUM(B8:F8)*360,SUM(G8:J8)*90) -> 0 | N8: =K8+L8-M8 -> 0 | R8: 金流 | X8: 應收帳款 | AB8: 今日未結帳款清單 | AC8: 今日銷帳清單
K9: =SUM(SUM(B9:F9)*360,SUM(G9:J9)*90) -> 0 | N9: =K9+L9-M9 -> 0 | R9: 營業總額 | T9: 運費 | U9: =SUMIF(表格1_3345152[欄1],"<>公關品",表格1_3345152[運費]) -> 0 | X9: 累積未結 | Y9: =INDEX('4'!Y12:Z13,1,1) -> 10024 | AB9: {=_xlfn.LET(_xlpm.unpaid,_xlfn.UNIQUE(_xlfn._xlws.FILTER(A8:A100,O8:O100="未結帳款","今日無欠款")),IF(_xlpm.unpaid="今日無欠款","今日無欠款",_xlpm.unpaid&"："&SUMIFS(N8:N100,A8:A100,_xlpm.unpaid,O8:O100,"未結帳款")))} -> 今日無欠款 | AC9: {=_xlfn.LET(_xlpm.paid,_xlfn.UNIQUE(_xlfn._xlws.FILTER(A8:A100,P8:P100="銷帳","今日無銷帳")),IF(_xlpm.paid="今日無銷帳","今日無銷帳",_xlpm.paid&"："&SUMIFS(N8:N100,A8:A100,_xlpm.paid,P8:P100,"銷帳")))} -> 今日無銷帳
K10: =SUM(SUM(B10:F10)*360,SUM(G10:J10)*90) -> 0 | N10: =K10+L10-M10 -> 0 | R10: =SUM(K8:K101)-V15 -> 0 | T10: 折讓 | U10: =SUM(M8:M101) -> 0 | X10: 今日未結 | Y10: =U15 -> 0
K11: =SUM(SUM(B11:F11)*360,SUM(G11:J11)*90) -> 0 | N11: =K11+L11-M11 -> 0 | R11: 營業額 | T11: 公關品 | U11: =SUMIF(P8:P100,"公關品",K8:K103) -> 0 | X11: 今日回款 | Y11: =V15 -> 0
K12: =SUM(SUM(B12:F12)*360,SUM(G12:J12)*90) -> 0 | N12: =K12+L12-M12 -> 0 | R12: =R10-U10-U11 -> 0 | T12: 應收 | V12: 實收 | X12: 剩餘未結 | Y12: =Y9+Y10-Y11 -> 10024
K13: =SUM(SUM(B13:F13)*360,SUM(G13:J13)*90) -> 0 | N13: =K13+L13-M13 -> 0 | T13: 匯款 | U13: =SUMIF(O8:O101,"匯款",N8:N101) -> 0
K14: =SUM(SUM(B14:F14)*360,SUM(G14:J14)*90) -> 0 | N14: =K14+L14-M14 -> 0 | T14: 現金 | U14: =SUMIF(O8:O102,"現金",N8:N102) -> 0
K15: =SUM(SUM(B15:F15)*360,SUM(G15:J15)*90) -> 0 | N15: =K15+L15-M15 -> 0 | T15: 未結帳款 | U15: =SUMIF(O8:O102,"未結帳款",N8:N103) -> 0 | V15: =SUMIF(P8:P100,"銷帳",N8:N100) -> 0
K16: =SUM(SUM(B16:F16)*360,SUM(G16:J16)*90) -> 0 | N16: =K16+L16-M16 -> 0 | T16: 銷帳 | X16: 物流
K17: =SUM(SUM(B17:F17)*360,SUM(G17:J17)*90) -> 0 | N17: =K17+L17-M17 -> 0 | R17: 商品銷售量 | X17: 運費實收 | Y17: =U9 -> 0
K18: =SUM(SUM(B18:F18)*360,SUM(G18:J18)*90) -> 0 | N18: =K18+L18-M18 -> 0 | T18: 販售量 | U18: 公關品 | V18: 總盒數 | X18: 運費實支
K19: =SUM(SUM(B19:F19)*360,SUM(G19:J19)*90) -> 0 | N19: =K19+L19-M19 -> 0 | R19: 禮盒 | S19: 綜合 | T19: =SUMIF(P8:P102,"<>公關品",B8:B100) -> 0 | U19: =SUMIF(P8:P102,"公關品",B8:B100) -> 0 | V19: =SUM(T19:T23,U19) -> 0 | X19: 公關運費 | Y19: =SUMIF(P8:P100,"公關品",L8:L100) -> 0
K20: =SUM(SUM(B20:F20)*360,SUM(G20:J20)*90) -> 0 | N20: =K20+L20-M20 -> 0 | S20: 原味 | T20: =SUMIF(P8:P102,"<>公關品",C8:C100) -> 0 | U20: =SUMIF(P8:P102,"公關品",C8:C100) -> 0 | V20: 總顆數 | X20: 物流包材 | Y20: =SUM(Z24:Z27) -> 0
K21: =SUM(SUM(B21:F21)*360,SUM(G21:J21)*90) -> 0 | N21: =K21+L21-M21 -> 0 | S21: 可可 | T21: =SUMIF(P8:P104,"<>公關品",D8:D102) -> 0 | U21: =SUMIF(P8:P102,"公關品",D8:D100) -> 0 | X21: 成本差額 | Y21: =Y17-Y18-Y20+Y19 -> 0
K22: =SUM(SUM(B22:F22)*360,SUM(G22:J22)*90) -> 0 | N22: =K22+L22-M22 -> 0 | S22: 伯爵 | T22: =SUMIF(P8:P102,"<>公關品",E8:E100) -> 0 | U22: =SUMIF(P8:P102,"公關品",E8:E100) -> 0 | X22: 物流包材
K23: =SUM(SUM(B23:F23)*360,SUM(G23:J23)*90) -> 0 | N23: =K23+L23-M23 -> 0 | S23: 抹茶 | T23: =SUMIF(P8:P102,"<>公關品",F8:F100) -> 0 | U23: =SUMIF(P8:P102,"公關品",F8:F100) -> 0 | X23: 種類 | Y23: 數量 | Z23: 總額
K24: =SUM(SUM(B24:F24)*360,SUM(G24:J24)*90) -> 0 | N24: =K24+L24-M24 -> 0 | R24: 單顆 | S24: 原味 | T24: =SUMIF(P9:P103,"<>公關品",G8:G100) -> 0 | U24: =SUMIF(P8:P102,"公關品",G8:G100) -> 0 | V24: =T19+(T20*4)+T24 -> 0 | X24: 2入紙箱
K25: =SUM(SUM(B25:F25)*360,SUM(G25:J25)*90) -> 0 | N25: =K25+L25-M25 -> 0 | S25: 可可 | T25: =SUMIF(P8:P102,"<>公關品",H8:H100) -> 0 | U25: =SUMIF(P8:P102,"公關品",I8:I100) -> 0 | V25: =T19+(T21*4)+T25 -> 0 | X25: 4入紙箱 | Z25: =Y25*5 -> 0
K26: =SUM(SUM(B26:F26)*360,SUM(G26:J26)*90) -> 0 | N26: =K26+L26-M26 -> 0 | S26: 伯爵 | T26: =SUMIF(P9:P103,"<>公關品",I8:I100) -> 0 | U26: =SUMIF(P8:P102,"公關品",I8:I100) -> 0 | V26: =T19+(T22*4)+T26 -> 0 | X26: 10入紙箱
K27: =SUM(SUM(B27:F27)*360,SUM(G27:J27)*90) -> 0 | N27: =K27+L27-M27 -> 0 | S27: 抹茶 | T27: =SUMIF(P8:P102,"<>公關品",J8:J100) -> 0 | U27: =SUMIF(P9:P103,"公關品",J8:J100) -> 0 | V27: =T19+(T23*4)+T27 -> 0 | X27: 膠帶
K28: =SUM(SUM(B28:F28)*360,SUM(G28:J28)*90) -> 0 | N28: =K28+L28-M28 -> 0
K29: =SUM(SUM(B29:F29)*360,SUM(G29:J29)*90) -> 0 | N29: =K29+L29-M29 -> 0
K30: =SUM(SUM(B30:F30)*360,SUM(G30:J30)*90) -> 0 | N30: =K30+L30-M30 -> 0 | R30: 產能及庫存 | AB30: 今日公關品總結
K31: =SUM(SUM(B31:F31)*360,SUM(G31:J31)*90) -> 0 | N31: =K31+L31-M31 -> 0 | AB31: 總禮盒數 | AC31: =SUM(U19:U23) -> 0
K32: =SUM(SUM(B32:F32)*360,SUM(G32:J32)*90) -> 0 | N32: =K32+L32-M32 -> 0 | R32: 品項 | S32: 原庫存 | T32: 預計產量 | U32: 實際產量 | V32: 耗損 | W32: 實際銷售量 | Y32: 今日庫存 | Z32: 總損耗率 | AB32: 總顆數 | AC32: =SUM(AC33:AC36) -> 0
K33: =SUM(SUM(B33:F33)*360,SUM(G33:J33)*90) -> 0 | N33: =K33+L33-M33 -> 0 | R33: 原味 | S33: ='4'!Y33 -> 10 | T33: 30 | U33: 30 | V33: =SUMIF(R40:R55,"原味",S40:S55) -> 6 | W33: =V24+U24+U19+U20*4 -> 0 | Y33: =S33+U33-V33-W33 -> 34 | Z33: =IFERROR((V33/(U33+S33))," ") -> 0.15 | AB33: 原味 | AC33: =U24+U19+U20*4 -> 0
K34: =SUM(SUM(B34:F34)*360,SUM(G34:J34)*90) -> 0 | N34: =K34+L34-M34 -> 0 | R34: 可可 | S34: ='4'!Y34 -> 10 | T34: 30 | U34: 31 | V34: =SUMIF(R41:R55,"可可",S41:S55) -> 2 | W34: =V25+U25+U19+U21*4 -> 0 | Y34: =S34+U34-V34-W34 -> 39 | Z34: =IFERROR((V34/(U34+S34))," ") -> 0.048780488 | AB34: 可可 | AC34: =U25+U19+U21*4 -> 0
K35: =SUM(SUM(B35:F35)*360,SUM(G35:J35)*90) -> 0 | N35: =K35+L35-M35 -> 0 | R35: 伯爵 | S35: ='4'!Y35 -> 13 | T35: 30 | U35: 30 | V35: =SUMIF(R41:R55,"伯爵",S41:S55) -> 1 | W35: =V26+U26+U19+U22*4 -> 0 | Y35: =S35+U35-V35-W35 -> 42 | Z35: =IFERROR((V35/(U35+S35))," ") -> 0.023255814 | AB35: 伯爵 | AC35: =U26+U19+U22*4 -> 0
K36: =SUM(SUM(B36:F36)*360,SUM(G36:J36)*90) -> 0 | N36: =K36+L36-M36 -> 0 | R36: 抹茶 | S36: ='4'!Y36 -> 11 | T36: 30 | U36: 30 | V36: =SUMIF(R41:R55,"抹茶",S41:S55) -> 6 | W36: =V27+U27+U19+U23*4 -> 0 | Y36: =S36+U36-V36-W36 -> 35 | Z36: =IFERROR((V36/(U36+S36))," ") -> 0.14634146 | AB36: 抹茶 | AC36: =U27+U19+U23*4 -> 0
K37: =SUM(SUM(B37:F37)*360,SUM(G37:J37)*90) -> 0 | N37: =K37+L37-M37 -> 0
K38: =SUM(SUM(B38:F38)*360,SUM(G38:J38)*90) -> 0 | N38: =K38+L38-M38 -> 0 | R38: 損耗原因
K39: =SUM(SUM(B39:F39)*360,SUM(G39:J39)*90) -> 0 | N39: =K39+L39-M39 -> 0
K40: =SUM(SUM(B40:F40)*360,SUM(G40:J40)*90) -> 0 | N40: =K40+L40-M40 -> 0 | R40: 品項 | S40: 數量 | T40: 類別 | U40: 原因
K41: =SUM(SUM(B41:F41)*360,SUM(G41:J41)*90) -> 0 | N41: =K41+L41-M41 -> 0 | R41: 原味 | S41: 1 | T41: 吃掉
K42: =SUM(SUM(B42:F42)*360,SUM(G42:J42)*90) -> 0 | N42: =K42+L42-M42 -> 0 | R42: 可可 | S42: 2 | T42: 吃掉
K43: =SUM(SUM(B43:F43)*360,SUM(G43:J43)*90) -> 0 | N43: =K43+L43-M43 -> 0 | R43: 伯爵 | S43: 1 | T43: 吃掉
K44: =SUM(SUM(B44:F44)*360,SUM(G44:J44)*90) -> 0 | N44: =K44+L44-M44 -> 0
K45: =SUM(SUM(B45:F45)*360,SUM(G45:J45)*90) -> 0 | N45: =K45+L45-M45 -> 0 | R45: 原味 | S45: 5 | T45: 技術
K46: =SUM(SUM(B46:F46)*360,SUM(G46:J46)*90) -> 0 | N46: =K46+L46-M46 -> 0 | R46: 抹茶 | S46: 6 | T46: 技術
K47: =SUM(SUM(B47:F47)*360,SUM(G47:J47)*90) -> 0 | N47: =K47+L47-M47 -> 0
K48: =SUM(SUM(B48:F48)*360,SUM(G48:J48)*90) -> 0 | N48: =K48+L48-M48 -> 0
K49: =SUM(SUM(B49:F49)*360,SUM(G49:J49)*90) -> 0 | N49: =K49+L49-M49 -> 0
K50: =SUM(SUM(B50:F50)*360,SUM(G50:J50)*90) -> 0 | N50: =K50+L50-M50 -> 0
K51: =SUM(SUM(B51:F51)*360,SUM(G51:J51)*90) -> 0 | N51: =K51+L51-M51 -> 0
K52: =SUM(SUM(B52:F52)*360,SUM(G52:J52)*90) -> 0 | N52: =K52+L52-M52 -> 0
K53: =SUM(SUM(B53:F53)*360,SUM(G53:J53)*90) -> 0 | N53: =K53+L53-M53 -> 0
K54: =SUM(SUM(B54:F54)*360,SUM(G54:J54)*90) -> 0 | N54: =K54+L54-M54 -> 0
K55: =SUM(SUM(B55:F55)*360,SUM(G55:J55)*90) -> 0 | N55: =K55+L55-M55 -> 0
K56: =SUM(SUM(B56:F56)*360,SUM(G56:J56)*90) -> 0 | N56: =K56+L56-M56 -> 0
K57: =SUM(SUM(B57:F57)*360,SUM(G57:J57)*90) -> 0 | N57: =K57+L57-M57 -> 0 | R57: 備註
K58: =SUM(SUM(B58:F58)*360,SUM(G58:J58)*90) -> 0 | N58: =K58+L58-M58 -> 0
K59: =SUM(SUM(B59:F59)*360,SUM(G59:J59)*90) -> 0 | N59: =K59+L59-M59 -> 0
K60: =SUM(SUM(B60:F60)*360,SUM(G60:J60)*90) -> 0 | N60: =K60+L60-M60 -> 0
K61: =SUM(SUM(B61:F61)*360,SUM(G61:J61)*90) -> 0 | N61: =K61+L61-M61 -> 0
K62: =SUM(SUM(B62:F62)*360,SUM(G62:J62)*90) -> 0 | N62: =K62+L62-M62 -> 0
K63: =SUM(SUM(B63:F63)*360,SUM(G63:J63)*90) -> 0 | N63: =K63+L63-M63 -> 0
K64: =SUM(SUM(B64:F64)*360,SUM(G64:J64)*90) -> 0 | N64: =K64+L64-M64 -> 0
K65: =SUM(SUM(B65:F65)*360,SUM(G65:J65)*90) -> 0 | N65: =K65+L65-M65 -> 0
K66: =SUM(SUM(B66:F66)*360,SUM(G66:J66)*90) -> 0 | N66: =K66+L66-M66 -> 0
K67: =SUM(SUM(B67:F67)*360,SUM(G67:J67)*90) -> 0 | N67: =K67+L67-M67 -> 0
K68: =SUM(SUM(B68:F68)*360,SUM(G68:J68)*90) -> 0 | N68: =K68+L68-M68 -> 0
K69: =SUM(SUM(B69:F69)*360,SUM(G69:J69)*90) -> 0 | N69: =K69+L69-M69 -> 0
... K101: =SUM(SUM(B101:F101)*360,SUM(G101:J101)*90) -> 0 | N101: =K101+L101-M101 -> 0

Sheet 6
A1: 日報表
A5: 銷售明細 | R5: 總結
A6: 類別 | B6: 禮盒 | G6: 單顆 | K6: 金額
A7: 購買人 | B7: 綜合 | C7: 原味 | D7: 可可 | E7: 伯爵 | F7: 抹茶 | G7: 原味. | H7: 可可. | I7: 伯爵. | J7: 抹茶. | K7: 金額 | L7: 運費 | M7: 折讓金額 | N7: 實收金額 | O7: 收款類別 | P7: 備註
A8: Rebeca | B8: 2 | E8: 1 | K8: =SUM(SUM(B8:F8)*360,SUM(G8:J8)*90) -> 1080 | N8: =K8+L8-M8 -> 1080 | O8: 匯款 | R8: 金流 | X8: 應收帳款 | AB8: 今日未結帳款清單 | AC8: 今日銷帳清單
K9: =SUM(SUM(B9:F9)*360,SUM(G9:J9)*90) -> 0 | N9: =K9+L9-M9 -> 0 | R9: 營業總額 | T9: 運費 | U9: =SUMIF(表格1_334515253[收款類別],"<>公關品",表格1_334515253[運費]) -> 0 | X9: 累積未結 | Y9: =INDEX('5'!Y12:Z13,1,1) -> 10024 | AB9: {=_xlfn.LET(_xlpm.unpaid,_xlfn.UNIQUE(_xlfn._xlws.FILTER(A8:A100,O8:O100="未結帳款","今日無欠款")),IF(_xlpm.unpaid="今日無欠款","今日無欠款",_xlpm.unpaid&"："&SUMIFS(N8:N100,A8:A100,_xlpm.unpaid,O8:O100,"未結帳款")))} -> 李泓陞：720 | AC9: {=_xlfn.LET(_xlpm.paid,_xlfn.UNIQUE(_xlfn._xlws.FILTER(A8:A100,P8:P100="銷帳","今日無銷帳")),IF(_xlpm.paid="今日無銷帳","今日無銷帳",_xlpm.paid&"："&SUMIFS(N8:N100,A8:A100,_xlpm.paid,P8:P100,"銷帳")))} -> 林祥睿：9480
A10: 鄭凱丞 | B10: 3 | K10: =SUM(SUM(B10:F10)*360,SUM(G10:J10)*90) -> 1080 | N10: =K10+L10-M10 -> 1080 | O10: 匯款 | R10: =SUM(K8:K101) -> 15840 | T10: 折讓 | U10: =SUM(M8:M101) -> 720 | X10: 今日未結 | Y10: =U15 -> 720 | AC10: 李泓陞：9520
A11: 王嘉鈴 | C11: 1 | E11: 1 | F11: 1 | K11: =SUM(SUM(B11:F11)*360,SUM(G11:J11)*90) -> 1080 | N11: =K11+L11-M11 -> 1080 | O11: 匯款 | R11: 營業額 | T11: 公關品 | U11: =SUMIF(P8:P100,"公關品",K8:K103) -> 0 | X11: 今日回款 | Y11: =V15 -> 19000
A12: 李貴燕 | B12: 11 | K12: =SUM(SUM(B12:F12)*360,SUM(G12:J12)*90) -> 3960 | M12: 360 | N12: =K12+L12-M12 -> 3600 | O12: 匯款 | P12: 買十送一 | R12: =R10-U10-U11 -> 15120 | T12: 應收 | V12: 實收 | X12: 剩餘未結 | Y12: =Y9+Y10-Y11 -> -8256
A13: 陳德鴻 | B13: 3 | K13: =SUM(SUM(B13:F13)*360,SUM(G13:J13)*90) -> 1080 | N13: =K13+L13-M13 -> 1080 | O13: 匯款 | T13: 匯款 | U13: =SUMIF(O8:O101,"匯款",N8:N101) -> 13320
A14: 郭思妤 | B14: 3 | K14: =SUM(SUM(B14:F14)*360,SUM(G14:J14)*90) -> 1080 | N14: =K14+L14-M14 -> 1080 | O14: 匯款 | T14: 現金 | U14: =SUMIF(O8:O102,"現金",N8:N102) -> 0
A15: 洪惠珍 | B15: 2 | C15: 2 | E15: 2 | K15: =SUM(SUM(B15:F15)*360,SUM(G15:J15)*90) -> 2160 | N15: =K15+L15-M15 -> 2160 | O15: 匯款 | T15: 未結帳款 | U15: =SUMIF(O8:O102,"未結帳款",N8:N103) -> 720 | V15: =SUMIF(P8:P100,"銷帳",N8:N100) -> 19000
A16: 王柏竣 | B16: 2 | K16: =SUM(SUM(B16:F16)*360,SUM(G16:J16)*90) -> 720 | N16: =K16+L16-M16 -> 720 | O16: 匯款 | T16: 銷帳 | X16: 物流
A17: 吳明順 | B17: 5 | K17: =SUM(SUM(B17:F17)*360,SUM(G17:J17)*90) -> 1800 | M17: 360 | N17: =K17+L17-M17 -> 1440 | O17: 匯款 | P17: 買十送一 | R17: 商品銷售量 | X17: 運費實收 | Y17: =U9 -> 0
A18: 李泓陞 | B18: 2 | K18: =SUM(SUM(B18:F18)*360,SUM(G18:J18)*90) -> 720 | N18: =K18+L18-M18 -> 720 | O18: 未結帳款 | P18: 鄭凱丞 | T18: 販售量 | U18: 公關品 | V18: 總盒數 | X18: 運費實支 | Y18: 1315
A19: 張雲逸 | C19: 2 | K19: =SUM(SUM(B19:F19)*360,SUM(G19:J19)*90) -> 720 | N19: =K19+L19-M19 -> 720 | R19: 禮盒 | S19: 綜合 | T19: =SUMIF(P8:P102,"<>公關品",B8:B100) -> 34 | U19: =SUMIF(P8:P102,"公關品",B8:B100) -> 0 | V19: =SUM(T19:T23,U19) -> 44 | X19: 公關運費 | Y19: =SUMIF(P8:P100,"公關品",L8:L100) -> 0
A20: 張采妮 | B20: 1 | K20: =SUM(SUM(B20:F20)*360,SUM(G20:J20)*90) -> 360 | N20: =K20+L20-M20 -> 360 | S20: 原味 | T20: =SUMIF(P8:P102,"<>公關品",C8:C100) -> 5 | U20: =SUMIF(P8:P102,"公關品",C8:C100) -> 0 | V20: 總顆數 | X20: 物流包材 | Y20: =SUM(Z24:Z27) -> 20
A21: 林祥睿 | K21: =SUM(SUM(B21:F21)*360,SUM(G21:J21)*90) -> 0 | N21: 9480 | P21: 銷帳 | S21: 可可 | T21: =SUMIF(P8:P104,"<>公關品",D8:D102) -> 0 | U21: =SUMIF(P8:P102,"公關品",D8:D100) -> 0 | X21: 成本差額 | Y21: =Y17-Y18-Y20+Y19 -> -1335
A22: 李泓陞 | K22: =SUM(SUM(B22:F22)*360,SUM(G22:J22)*90) -> 0 | N22: 9520 | P22: 銷帳 | S22: 伯爵 | T22: =SUMIF(P8:P102,"<>公關品",E8:E100) -> 4 | U22: =SUMIF(P8:P102,"公關品",E8:E100) -> 0 | X22: 物流包材
K23: =SUM(SUM(B23:F23)*360,SUM(G23:J23)*90) -> 0 | N23: =K23+L23-M23 -> 0 | S23: 抹茶 | T23: =SUMIF(P8:P102,"<>公關品",F8:F100) -> 1 | U23: =SUMIF(P8:P102,"公關品",F8:F100) -> 0 | X23: 種類 | Y23: 數量 | Z23: 總額
K24: =SUM(SUM(B24:F24)*360,SUM(G24:J24)*90) -> 0 | N24: =K24+L24-M24 -> 0 | R24: 單顆 | S24: 原味 | T24: =SUMIF(P9:P103,"<>公關品",G8:G100) -> 0 | U24: =SUMIF(P8:P102,"公關品",G8:G100) -> 0 | V24: =T19+(T20*4)+T24 -> 54 | X24: 2入紙箱
K25: =SUM(SUM(B25:F25)*360,SUM(G25:J25)*90) -> 0 | N25: =K25+L25-M25 -> 0 | S25: 可可 | T25: =SUMIF(P8:P102,"<>公關品",H8:H100) -> 0 | U25: =SUMIF(P8:P102,"公關品",I8:I100) -> 0 | V25: =T19+(T21*4)+T25 -> 34 | X25: 4入紙箱 | Y25: 4 | Z25: =Y25*5 -> 20
K26: =SUM(SUM(B26:F26)*360,SUM(G26:J26)*90) -> 0 | N26: =K26+L26-M26 -> 0 | S26: 伯爵 | T26: =SUMIF(P9:P103,"<>公關品",I8:I100) -> 0 | U26: =SUMIF(P8:P102,"公關品",I8:I100) -> 0 | V26: =T19+(T22*4)+T26 -> 50 | X26: 10入紙箱 | Y26: 3
K27: =SUM(SUM(B27:F27)*360,SUM(G27:J27)*90) -> 0 | N27: =K27+L27-M27 -> 0 | S27: 抹茶 | T27: =SUMIF(P8:P102,"<>公關品",J8:J100) -> 0 | U27: =SUMIF(P9:P103,"公關品",J8:J100) -> 0 | V27: =T19+(T23*4)+T27 -> 38 | X27: 膠帶
K28: =SUM(SUM(B28:F28)*360,SUM(G28:J28)*90) -> 0 | N28: =K28+L28-M28 -> 0
K29: =SUM(SUM(B29:F29)*360,SUM(G29:J29)*90) -> 0 | N29: =K29+L29-M29 -> 0
K30: =SUM(SUM(B30:F30)*360,SUM(G30:J30)*90) -> 0 | N30: =K30+L30-M30 -> 0 | R30: 產能及庫存 | AB30: 今日公關品總結
K31: =SUM(SUM(B31:F31)*360,SUM(G31:J31)*90) -> 0 | N31: =K31+L31-M31 -> 0 | AB31: 總禮盒數 | AC31: =SUM(U19:U23) -> 0
K32: =SUM(SUM(B32:F32)*360,SUM(G32:J32)*90) -> 0 | N32: =K32+L32-M32 -> 0 | R32: 品項 | S32: 原庫存 | T32: 預計產量 | U32: 實際產量 | V32: 耗損 | W32: 實際銷售量 | Y32: 今日庫存 | Z32: 總損耗率 | AB32: 總顆數 | AC32: =SUM(AC33:AC36) -> 0
K33: =SUM(SUM(B33:F33)*360,SUM(G33:J33)*90) -> 0 | N33: =K33+L33-M33 -> 0 | R33: 原味 | S33: ='5'!Y33 -> 34 | T33: 30 | U33: 31 | V33: =SUMIF(R40:R55,"原味",S40:S55) -> 4 | W33: =V24+U24+U19+U20*4 -> 54 | Y33: =S33+U33-V33-W33 -> 7 | Z33: =IFERROR((V33/(U33+S33))," ") -> 0.061538462 | AB33: 原味 | AC33: =U24+U19+U20*4 -> 0
K34: =SUM(SUM(B34:F34)*360,SUM(G34:J34)*90) -> 0 | N34: =K34+L34-M34 -> 0 | R34: 可可 | S34: ='5'!Y34 -> 39 | V34: =SUMIF(R41:R55,"可可",S41:S55) -> 4 | W34: =V25+U25+U19+U21*4 -> 34 | Y34: =S34+U34-V34-W34 -> 1 | Z34: =IFERROR((V34/(U34+S34))," ") -> 0.1025641 | AB34: 可可 | AC34: =U25+U19+U21*4 -> 0
K35: =SUM(SUM(B35:F35)*360,SUM(G35:J35)*90) -> 0 | N35: =K35+L35-M35 -> 0 | R35: 伯爵 | S35: ='5'!Y35 -> 42 | T35: 15 | U35: 15 | V35: =SUMIF(R41:R55,"伯爵",S41:S55) -> 3 | W35: =V26+U26+U19+U22*4 -> 50 | Y35: =S35+U35-V35-W35 -> 4 | Z35: =IFERROR((V35/(U35+S35))," ") -> 0.052631579 | AB35: 伯爵 | AC35: =U26+U19+U22*4 -> 0
K36: =SUM(SUM(B36:F36)*360,SUM(G36:J36)*90) -> 0 | N36: =K36+L36-M36 -> 0 | R36: 抹茶 | S36: ='5'!Y36 -> 35 | T36: 15 | U36: 15 | V36: =SUMIF(R41:R55,"抹茶",S41:S55) -> 2 | W36: =V27+U27+U19+U23*4 -> 38 | Y36: =S36+U36-V36-W36 -> 10 | Z36: =IFERROR((V36/(U36+S36))," ") -> 0.04 | AB36: 抹茶 | AC36: =U27+U19+U23*4 -> 0
K37: =SUM(SUM(B37:F37)*360,SUM(G37:J37)*90) -> 0 | N37: =K37+L37-M37 -> 0
K38: =SUM(SUM(B38:F38)*360,SUM(G38:J38)*90) -> 0 | N38: =K38+L38-M38 -> 0 | R38: 損耗原因
K39: =SUM(SUM(B39:F39)*360,SUM(G39:J39)*90) -> 0 | N39: =K39+L39-M39 -> 0
K40: =SUM(SUM(B40:F40)*360,SUM(G40:J40)*90) -> 0 | N40: =K40+L40-M40 -> 0 | R40: 品項 | S40: 數量 | T40: 類別 | U40: 原因
K41: =SUM(SUM(B41:F41)*360,SUM(G41:J41)*90) -> 0 | N41: =K41+L41-M41 -> 0 | R41: 原味 | S41: 4 | T41: 技術
K42: =SUM(SUM(B42:F42)*360,SUM(G42:J42)*90) -> 0 | N42: =K42+L42-M42 -> 0 | R42: 抹茶 | S42: 2 | T42: 技術
K43: =SUM(SUM(B43:F43)*360,SUM(G43:J43)*90) -> 0 | N43: =K43+L43-M43 -> 0 | R43: 伯爵 | S43: 1 | T43: 過期
K44: =SUM(SUM(B44:F44)*360,SUM(G44:J44)*90) -> 0 | N44: =K44+L44-M44 -> 0 | R44: 可可 | S44: 4 | T44: 人為
K45: =SUM(SUM(B45:F45)*360,SUM(G45:J45)*90) -> 0 | N45: =K45+L45-M45 -> 0 | R45: 伯爵 | S45: 2 | T45: 人為
K46: =SUM(SUM(B46:F46)*360,SUM(G46:J46)*90) -> 0 | N46: =K46+L46-M46 -> 0
K47: =SUM(SUM(B47:F47)*360,SUM(G47:J47)*90) -> 0 | N47: =K47+L47-M47 -> 0
K48: =SUM(SUM(B48:F48)*360,SUM(G48:J48)*90) -> 0 | N48: =K48+L48-M48 -> 0
K49: =SUM(SUM(B49:F49)*360,SUM(G49:J49)*90) -> 0 | N49: =K49+L49-M49 -> 0
K50: =SUM(SUM(B50:F50)*360,SUM(G50:J50)*90) -> 0 | N50: =K50+L50-M50 -> 0
K51: =SUM(SUM(B51:F51)*360,SUM(G51:J51)*90) -> 0 | N51: =K51+L51-M51 -> 0
K52: =SUM(SUM(B52:F52)*360,SUM(G52:J52)*90) -> 0 | N52: =K52+L52-M52 -> 0
K53: =SUM(SUM(B53:F53)*360,SUM(G53:J53)*90) -> 0 | N53: =K53+L53-M53 -> 0
K54: =SUM(SUM(B54:F54)*360,SUM(G54:J54)*90) -> 0 | N54: =K54+L54-M54 -> 0
K55: =SUM(SUM(B55:F55)*360,SUM(G55:J55)*90) -> 0 | N55: =K55+L55-M55 -> 0
K56: =SUM(SUM(B56:F56)*360,SUM(G56:J56)*90) -> 0 | N56: =K56+L56-M56 -> 0
K57: =SUM(SUM(B57:F57)*360,SUM(G57:J57)*90) -> 0 | N57: =K57+L57-M57 -> 0 | R57: 備註
K58: =SUM(SUM(B58:F58)*360,SUM(G58:J58)*90) -> 0 | N58: =K58+L58-M58 -> 0
K59: =SUM(SUM(B59:F59)*360,SUM(G59:J59)*90) -> 0 | N59: =K59+L59-M59 -> 0
K60: =SUM(SUM(B60:F60)*360,SUM(G60:J60)*90) -> 0 | N60: =K60+L60-M60 -> 0
K61: =SUM(SUM(B61:F61)*360,SUM(G61:J61)*90) -> 0 | N61: =K61+L61-M61 -> 0
K62: =SUM(SUM(B62:F62)*360,SUM(G62:J62)*90) -> 0 | N62: =K62+L62-M62 -> 0
K63: =SUM(SUM(B63:F63)*360,SUM(G63:J63)*90) -> 0 | N63: =K63+L63-M63 -> 0
K64: =SUM(SUM(B64:F64)*360,SUM(G64:J64)*90) -> 0 | N64: =K64+L64-M64 -> 0
K65: =SUM(SUM(B65:F65)*360,SUM(G65:J65)*90) -> 0 | N65: =K65+L65-M65 -> 0
K66: =SUM(SUM(B66:F66)*360,SUM(G66:J66)*90) -> 0 | N66: =K66+L66-M66 -> 0
K67: =SUM(SUM(B67:F67)*360,SUM(G67:J67)*90) -> 0 | N67: =K67+L67-M67 -> 0
K68: =SUM(SUM(B68:F68)*360,SUM(G68:J68)*90) -> 0 | N68: =K68+L68-M68 -> 0
K69: =SUM(SUM(B69:F69)*360,SUM(G69:J69)*90) -> 0 | N69: =K69+L69-M69 -> 0
... K101: =SUM(SUM(B101:F101)*360,SUM(G101:J101)*90) -> 0 | N101: =K101+L101-M101 -> 0

Sheet 7
A1: 日報表
A5: 銷售明細 | R5: 總結
A6: 類別 | B6: 禮盒 | G6: 單顆 | K6: 金額
A7: 購買人 | B7: 綜合 | C7: 原味 | D7: 可可 | E7: 伯爵 | F7: 抹茶 | G7: 原味. | H7: 可可. | I7: 伯爵. | J7: 抹茶. | K7: 金額 | L7: 運費 | M7: 折讓金額 | N7: 實收金額 | O7: 欄1 | P7: 備註
A8: 李益昌 | B8: 5 | K8: =SUM(SUM(B8:F8)*360,SUM(G8:J8)*90) -> 1800 | N8: =K8+L8-M8 -> 1800 | O8: 匯款 | R8: 金流 | X8: 應收帳款 | AB8: 今日未結帳款清單 | AC8: 今日銷帳清單
A9: 李泓陞 | B9: 2 | K9: =SUM(SUM(B9:F9)*360,SUM(G9:J9)*90) -> 720 | L9: 160 | N9: =K9+L9-M9 -> 880 | O9: 未結帳款 | P9: 魏辰安 | R9: 營業總額 | T9: 運費 | U9: =SUMIF(表格1_33451525354[欄1],"<>公關品",表格1_33451525354[運費]) -> 1440 | X9: 累積未結 | Y9: =INDEX('6'!Y12:Z13,1,1) -> -8256 | AB9: {=_xlfn.LET(_xlpm.unpaid,_xlfn.UNIQUE(_xlfn._xlws.FILTER(A8:A100,O8:O100="未結帳款","今日無欠款")),IF(_xlpm.unpaid="今日無欠款","今日無欠款",_xlpm.unpaid&"："&SUMIFS(N8:N100,A8:A100,_xlpm.unpaid,O8:O100,"未結帳款")))} -> 李泓陞：6160 | AC9: {=_xlfn.LET(_xlpm.paid,_xlfn.UNIQUE(_xlfn._xlws.FILTER(A8:A100,P8:P100="銷帳","今日無銷帳")),IF(_xlpm.paid="今日無銷帳","今日無銷帳",_xlpm.paid&"："&SUMIFS(N8:N100,A8:A100,_xlpm.paid,P8:P100,"銷帳")))} -> 今日無銷帳
K10: =SUM(SUM(B10:F10)*360,SUM(G10:J10)*90) -> 0 | N10: =K10+L10-M10 -> 0 | R10: =SUM(K8:K101)-V15 -> 11238 | T10: 折讓 | U10: =SUM(M8:M101) -> 0 | X10: 今日未結 | Y10: =U15 -> 7560 | AB10: 吳宜亭：880
A11: 李泓陞 | B11: 2 | K11: =SUM(SUM(B11:F11)*360,SUM(G11:J11)*90) -> 720 | L11: 160 | N11: =K11+L11-M11 -> 880 | O11: 未結帳款 | P11: 李有霖 | R11: 營業額 | T11: 公關品 | U11: =SUMIF(P8:P100,"公關品",K8:K103) -> 720 | X11: 今日回款 | Y11: =V15 -> 0 | AB11: 林祥睿：520
A12: 李泓陞 | B12: 2 | K12: =SUM(SUM(B12:F12)*360,SUM(G12:J12)*90) -> 720 | L12: 160 | N12: =K12+L12-M12 -> 880 | O12: 未結帳款 | P12: 李杰紘 | R12: =R10-U10-U11 -> 10518 | T12: 應收 | V12: 實收 | X12: 剩餘未結 | Y12: =Y9+Y10-Y11 -> -696
A13: 李泓陞 | B13: 2 | K13: =SUM(SUM(B13:F13)*360,SUM(G13:J13)*90) -> 720 | L13: 160 | N13: =K13+L13-M13 -> 880 | O13: 未結帳款 | P13: 林以婕 | T13: 匯款 | U13: =SUMIF(O8:O101,"匯款",N8:N101) -> 3600
A14: 李泓陞 | B14: 2 | K14: =SUM(SUM(B14:F14)*360,SUM(G14:J14)*90) -> 720 | L14: 160 | N14: =K14+L14-M14 -> 880 | O14: 未結帳款 | P14: 楊欣蕙 | T14: 現金 | U14: =SUMIF(O8:O102,"現金",N8:N102) -> 798
T15: 未結帳款 | U15: =SUMIF(O8:O102,"未結帳款",N8:N103) -> 7560 | V15: =SUMIF(P8:P100,"銷帳",N8:N100) -> 0
A16: 李泓陞 | B16: 2 | K16: =SUM(SUM(B16:F16)*360,SUM(G16:J16)*90) -> 720 | L16: 160 | N16: =K16+L16-M16 -> 880 | O16: 未結帳款 | P16: 蔡品睿 | T16: 銷帳 | X16: 物流
A17: 李泓陞 | B17: 2 | K17: =SUM(SUM(B17:F17)*360,SUM(G17:J17)*90) -> 720 | L17: 160 | N17: =K17+L17-M17 -> 880 | O17: 未結帳款 | P17: 徐韋傑 | R17: 商品銷售量 | X17: 運費實收 | Y17: =U9 -> 1440
A18: 吳宜亭 | B18: 2 | K18: =SUM(SUM(B18:F18)*360,SUM(G18:J18)*90) -> 720 | L18: 160 | N18: =K18+L18-M18 -> 880 | O18: 未結帳款 | P18: 倪茂翔 | T18: 販售量 | U18: 公關品 | V18: 總盒數 | X18: 運費實支 | Y18: 609
A19: 陳宥嫺 | C19: 3 | D19: 2 | K19: =SUM(SUM(B19:F19)*360,SUM(G19:J19)*90) -> 1800 | N19: =K19+L19-M19 -> 1800 | O19: 匯款 | R19: 禮盒 | S19: 綜合 | T19: =SUMIF(P8:P102,"<>公關品",B8:B100) -> 22 | U19: =SUMIF(P8:P102,"公關品",B8:B100) -> 2 | V19: =SUM(T19:T23,U19) -> 29 | X19: 公關運費 | Y19: =SUMIF(P8:P100,"公關品",L8:L100) -> 0
A20: 檸檬 | K20: 798 | N20: 798 | O20: 現金 | P20: 小可＊2 | S20: 原味 | T20: =SUMIF(P8:P102,"<>公關品",C8:C100) -> 3 | U20: =SUMIF(P8:P102,"公關品",C8:C100) -> 0 | V20: 總顆數 | X20: 物流包材 | Y20: =SUM(Z24:Z27) -> 10
A21: 抽獎 | B21: 1 | K21: =SUM(SUM(B21:F21)*360,SUM(G21:J21)*90) -> 360 | N21: =K21+L21-M21 -> 360 | P21: 公關品 | S21: 可可 | T21: =SUMIF(P8:P104,"<>公關品",D8:D102) -> 2 | U21: =SUMIF(P8:P102,"公關品",D8:D100) -> 0 | X21: 成本差額 | Y21: =Y17-Y18-Y20+Y19 -> 821
A22: 林祥睿 | B22: 1 | K22: =SUM(SUM(B22:F22)*360,SUM(G22:J22)*90) -> 360 | L22: 160 | N22: =K22+L22-M22 -> 520 | O22: 未結帳款 | P22: 陳裕莛 | S22: 伯爵 | T22: =SUMIF(P8:P102,"<>公關品",E8:E100) -> 0 | U22: =SUMIF(P8:P102,"公關品",E8:E100) -> 0 | X22: 物流包材
A23: 雅山 | B23: 1 | K23: =SUM(SUM(B23:F23)*360,SUM(G23:J23)*90) -> 360 | N23: =K23+L23-M23 -> 360 | P23: 公關品 | S23: 抹茶 | T23: =SUMIF(P8:P102,"<>公關品",F8:F100) -> 0 | U23: =SUMIF(P8:P102,"公關品",F8:F100) -> 0 | X23: 種類 | Y23: 數量 | Z23: 總額
K24: =SUM(SUM(B24:F24)*360,SUM(G24:J24)*90) -> 0 | N24: =K24+L24-M24 -> 0 | R24: 單顆 | S24: 原味 | T24: =SUMIF(P9:P103,"<>公關品",G8:G100) -> 0 | U24: =SUMIF(P8:P102,"公關品",G8:G100) -> 0 | V24: =T19+(T20*4)+T24 -> 34 | X24: 2入紙箱 | Y24: 10
K25: =SUM(SUM(B25:F25)*360,SUM(G25:J25)*90) -> 0 | N25: =K25+L25-M25 -> 0 | S25: 可可 | T25: =SUMIF(P8:P102,"<>公關品",H8:H100) -> 0 | U25: =SUMIF(P8:P102,"公關品",I8:I100) -> 0 | V25: =T19+(T21*4)+T25 -> 30 | X25: 4入紙箱 | Y25: 2 | Z25: =Y25*5 -> 10
K26: =SUM(SUM(B26:F26)*360,SUM(G26:J26)*90) -> 0 | N26: =K26+L26-M26 -> 0 | S26: 伯爵 | T26: =SUMIF(P9:P103,"<>公關品",I8:I100) -> 0 | U26: =SUMIF(P8:P102,"公關品",I8:I100) -> 0 | V26: =T19+(T22*4)+T26 -> 22 | X26: 10入紙箱
K27: =SUM(SUM(B27:F27)*360,SUM(G27:J27)*90) -> 0 | N27: =K27+L27-M27 -> 0 | S27: 抹茶 | T27: =SUMIF(P8:P102,"<>公關品",J8:J100) -> 0 | U27: =SUMIF(P9:P103,"公關品",J8:J100) -> 0 | V27: =T19+(T23*4)+T27 -> 22 | X27: 膠帶
K28: =SUM(SUM(B28:F28)*360,SUM(G28:J28)*90) -> 0 | N28: =K28+L28-M28 -> 0
K29: =SUM(SUM(B29:F29)*360,SUM(G29:J29)*90) -> 0 | N29: =K29+L29-M29 -> 0
K30: =SUM(SUM(B30:F30)*360,SUM(G30:J30)*90) -> 0 | N30: =K30+L30-M30 -> 0 | R30: 產能及庫存 | AB30: 今日公關品總結
K31: =SUM(SUM(B31:F31)*360,SUM(G31:J31)*90) -> 0 | N31: =K31+L31-M31 -> 0 | AB31: 總禮盒數 | AC31: =SUM(U19:U23) -> 2
K32: =SUM(SUM(B32:F32)*360,SUM(G32:J32)*90) -> 0 | N32: =K32+L32-M32 -> 0 | R32: 品項 | S32: 原庫存 | T32: 預計產量 | U32: 實際產量 | V32: 耗損 | W32: 實際銷售量 | Y32: 今日庫存 | Z32: 總損耗率 | AB32: 總顆數 | AC32: =SUM(AC33:AC36) -> 8
K33: =SUM(SUM(B33:F33)*360,SUM(G33:J33)*90) -> 0 | N33: =K33+L33-M33 -> 0 | R33: 原味 | S33: ='6'!Y33 -> 7 | T33: 45 | U33: 40 | V33: =SUMIF(R40:R55,"原味",S40:S55) -> 7 | W33: =V24+U24+U19+U20*4 -> 36 | Y33: =S33+U33-V33-W33 -> 4 | Z33: =IFERROR((V33/(U33+S33))," ") -> 0.14893617 | AB33: 原味 | AC33: =U24+U19+U20*4 -> 2
K34: =SUM(SUM(B34:F34)*360,SUM(G34:J34)*90) -> 0 | N34: =K34+L34-M34 -> 0 | R34: 可可 | S34: ='6'!Y34 -> 1 | T34: 45 | U34: 37 | V34: =SUMIF(R41:R55,"可可",S41:S55) -> 1 | W34: =V25+U25+U19+U21*4 -> 32 | Y34: =S34+U34-V34-W34 -> 5 | Z34: =IFERROR((V34/(U34+S34))," ") -> 0.026315789 | AB34: 可可 | AC34: =U25+U19+U21*4 -> 2
K35: =SUM(SUM(B35:F35)*360,SUM(G35:J35)*90) -> 0 | N35: =K35+L35-M35 -> 0 | R35: 伯爵 | S35: ='6'!Y35 -> 4 | T35: 30 | U35: 31 | V35: =SUMIF(R41:R55,"伯爵",S41:S55) -> 1 | W35: =V26+U26+U19+U22*4 -> 24 | Y35: =S35+U35-V35-W35 -> 10 | Z35: =IFERROR((V35/(U35+S35))," ") -> 0.028571429 | AB35: 伯爵 | AC35: =U26+U19+U22*4 -> 2
K36: =SUM(SUM(B36:F36)*360,SUM(G36:J36)*90) -> 0 | N36: =K36+L36-M36 -> 0 | R36: 抹茶 | S36: ='6'!Y36 -> 10 | T36: 45 | U36: 20 | V36: =SUMIF(R41:R55,"抹茶",S41:S55) -> 2 | W36: =V27+U27+U19+U23*4 -> 24 | Y36: =S36+U36-V36-W36 -> 4 | Z36: =IFERROR((V36/(U36+S36))," ") -> 0.066666667 | AB36: 抹茶 | AC36: =U27+U19+U23*4 -> 2
K37: =SUM(SUM(B37:F37)*360,SUM(G37:J37)*90) -> 0 | N37: =K37+L37-M37 -> 0
K38: =SUM(SUM(B38:F38)*360,SUM(G38:J38)*90) -> 0 | N38: =K38+L38-M38 -> 0 | R38: 損耗原因
K39: =SUM(SUM(B39:F39)*360,SUM(G39:J39)*90) -> 0 | N39: =K39+L39-M39 -> 0
K40: =SUM(SUM(B40:F40)*360,SUM(G40:J40)*90) -> 0 | N40: =K40+L40-M40 -> 0 | R40: 品項 | S40: 數量 | T40: 類別 | U40: 原因
K41: =SUM(SUM(B41:F41)*360,SUM(G41:J41)*90) -> 0 | N41: =K41+L41-M41 -> 0 | R41: 原味 | S41: 4 | T41: 技術
K42: =SUM(SUM(B42:F42)*360,SUM(G42:J42)*90) -> 0 | N42: =K42+L42-M42 -> 0 | R42: 可可 | S42: 1 | T42: 吃掉
K43: =SUM(SUM(B43:F43)*360,SUM(G43:J43)*90) -> 0 | N43: =K43+L43-M43 -> 0 | R43: 抹茶 | S43: 2 | T43: 技術
K44: =SUM(SUM(B44:F44)*360,SUM(G44:J44)*90) -> 0 | N44: =K44+L44-M44 -> 0 | R44: 原味 | S44: 3 | T44: 吃掉
K45: =SUM(SUM(B45:F45)*360,SUM(G45:J45)*90) -> 0 | N45: =K45+L45-M45 -> 0
K46: =SUM(SUM(B46:F46)*360,SUM(G46:J46)*90) -> 0 | N46: =K46+L46-M46 -> 0 | R46: 伯爵 | S46: 1 | T46: 過期
K47: =SUM(SUM(B47:F47)*360,SUM(G47:J47)*90) -> 0 | N47: =K47+L47-M47 -> 0
K48: =SUM(SUM(B48:F48)*360,SUM(G48:J48)*90) -> 0 | N48: =K48+L48-M48 -> 0
K49: =SUM(SUM(B49:F49)*360,SUM(G49:J49)*90) -> 0 | N49: =K49+L49-M49 -> 0
K50: =SUM(SUM(B50:F50)*360,SUM(G50:J50)*90) -> 0 | N50: =K50+L50-M50 -> 0
K51: =SUM(SUM(B51:F51)*360,SUM(G51:J51)*90) -> 0 | N51: =K51+L51-M51 -> 0
K52: =SUM(SUM(B52:F52)*360,SUM(G52:J52)*90) -> 0 | N52: =K52+L52-M52 -> 0
K53: =SUM(SUM(B53:F53)*360,SUM(G53:J53)*90) -> 0 | N53: =K53+L53-M53 -> 0
K54: =SUM(SUM(B54:F54)*360,SUM(G54:J54)*90) -> 0 | N54: =K54+L54-M54 -> 0
K55: =SUM(SUM(B55:F55)*360,SUM(G55:J55)*90) -> 0 | N55: =K55+L55-M55 -> 0
K56: =SUM(SUM(B56:F56)*360,SUM(G56:J56)*90) -> 0 | N56: =K56+L56-M56 -> 0
K57: =SUM(SUM(B57:F57)*360,SUM(G57:J57)*90) -> 0 | N57: =K57+L57-M57 -> 0 | R57: 備註
K58: =SUM(SUM(B58:F58)*360,SUM(G58:J58)*90) -> 0 | N58: =K58+L58-M58 -> 0
K59: =SUM(SUM(B59:F59)*360,SUM(G59:J59)*90) -> 0 | N59: =K59+L59-M59 -> 0
K60: =SUM(SUM(B60:F60)*360,SUM(G60:J60)*90) -> 0 | N60: =K60+L60-M60 -> 0 | R60: 1.小李8個明天寄
K61: =SUM(SUM(B61:F61)*360,SUM(G61:J61)*90) -> 0 | N61: =K61+L61-M61 -> 0 | R61: 2明天運費記得要轉過來
K62: =SUM(SUM(B62:F62)*360,SUM(G62:J62)*90) -> 0 | N62: =K62+L62-M62 -> 0
K63: =SUM(SUM(B63:F63)*360,SUM(G63:J63)*90) -> 0 | N63: =K63+L63-M63 -> 0
K64: =SUM(SUM(B64:F64)*360,SUM(G64:J64)*90) -> 0 | N64: =K64+L64-M64 -> 0
K65: =SUM(SUM(B65:F65)*360,SUM(G65:J65)*90) -> 0 | N65: =K65+L65-M65 -> 0
K66: =SUM(SUM(B66:F66)*360,SUM(G66:J66)*90) -> 0 | N66: =K66+L66-M66 -> 0
K67: =SUM(SUM(B67:F67)*360,SUM(G67:J67)*90) -> 0 | N67: =K67+L67-M67 -> 0
K68: =SUM(SUM(B68:F68)*360,SUM(G68:J68)*90) -> 0 | N68: =K68+L68-M68 -> 0
K69: =SUM(SUM(B69:F69)*360,SUM(G69:J69)*90) -> 0 | N69: =K69+L69-M69 -> 0
K70: =SUM(SUM(B70:F70)*360,SUM(G70:J70)*90) -> 0 | N70: =K70+L70-M70 -> 0
K71: =SUM(SUM(B71:F71)*360,SUM(G71:J71)*90) -> 0 | N71: =K71+L71-M71 -> 0
K72: =SUM(SUM(B72:F72)*360,SUM(G72:J72)*90) -> 0 | N72: =K72+L72-M72 -> 0
K73: =SUM(SUM(B73:F73)*360,SUM(G73:J73)*90) -> 0 | N73: =K73+L73-M73 -> 0
... K101: =SUM(SUM(B101:F101)*360,SUM(G101:J101)*90) -> 0 | N101: =K101+L101-M101 -> 0

Sheet 8
A1: 日報表
A5: 銷售明細 | R5: 總結
A6: 類別 | B6: 禮盒 | G6: 單顆 | K6: 金額
A7: 購買人 | B7: 綜合 | C7: 原味 | D7: 可可 | E7: 伯爵 | F7: 抹茶 | G7: 原味. | H7: 可可. | I7: 伯爵. | J7: 抹茶. | K7: 金額 | L7: 運費 | M7: 折讓金額 | N7: 實收金額 | O7: 欄1 | P7: 備註
K8: =SUM(SUM(B8:F8)*360,SUM(G8:J8)*90) -> 0 | N8: =K8+L8-M8 -> 0 | O8: 匯款 | R8: 金流 | X8: 應收帳款 | AB8: 今日未結帳款清單 | AC8: 今日銷帳清單
A9: 林祥睿 | C9: 1 | D9: 1 | E9: 1 | F9: 1 | K9: =SUM(SUM(B9:F9)*360,SUM(G9:J9)*90) -> 1440 | N9: =K9+L9-M9 -> 1440 | O9: 未結帳款 | P9: 謝凌汎 | R9: 營業總額 | T9: 運費 | U9: =SUMIF(表格1_3345152535455[欄1],"<>公關品",表格1_3345152535455[運費]) -> 480 | X9: 累積未結 | Y9: =INDEX('7'!Y12:Z13,1,1) -> -696 | AB9: {=_xlfn.LET(_xlpm.unpaid,_xlfn.UNIQUE(_xlfn._xlws.FILTER(A8:A100,O8:O100="未結帳款","今日無欠款")),IF(_xlpm.unpaid="今日無欠款","今日無欠款",_xlpm.unpaid&"："&SUMIFS(N8:N100,A8:A100,_xlpm.unpaid,O8:O100,"未結帳款")))} -> 林祥睿：5880 | AC9: {=_xlfn.LET(_xlpm.paid,_xlfn.UNIQUE(_xlfn._xlws.FILTER(A8:A100,P8:P100="銷帳","今日無銷帳")),IF(_xlpm.paid="今日無銷帳","今日無銷帳",_xlpm.paid&"："&SUMIFS(N8:N100,A8:A100,_xlpm.paid,P8:P100,"銷帳")))} -> 今日無銷帳
A10: 林祥睿 | B10: 5 | K10: =SUM(SUM(B10:F10)*360,SUM(G10:J10)*90) -> 1800 | N10: =K10+L10-M10 -> 1800 | O10: 未結帳款 | P10: 李凱裕 | R10: =SUM(K8:K101)-V15 -> 6480 | T10: 折讓 | U10: =SUM(M8:M101) -> 0 | X10: 今日未結 | Y10: =U15 -> 6600 | AB10: 李泓陞：720
A11: 林祥睿 | B11: 2 | K11: =SUM(SUM(B11:F11)*360,SUM(G11:J11)*90) -> 720 | L11: 160 | N11: =K11+L11-M11 -> 880 | O11: 未結帳款 | P11: 王威鈞 | R11: 營業額 | T11: 公關品 | U11: =SUMIF(P8:P100,"公關品",K8:K103) -> 0 | X11: 今日回款 | Y11: =V15 -> 0
A12: 林祥睿 | B12: 2 | K12: =SUM(SUM(B12:F12)*360,SUM(G12:J12)*90) -> 720 | L12: 160 | N12: =K12+L12-M12 -> 880 | O12: 未結帳款 | P12: 郭小姐 | R12: =R10-U10-U11 -> 6480 | T12: 應收 | V12: 實收 | X12: 剩餘未結 | Y12: =Y9+Y10-Y11 -> 5904
A13: 李泓陞 | B13: 2 | K13: =SUM(SUM(B13:F13)*360,SUM(G13:J13)*90) -> 720 | N13: =K13+L13-M13 -> 720 | O13: 未結帳款 | P13: 自取 | T13: 匯款 | U13: =SUMIF(O8:O101,"匯款",N8:N101) -> 360
A14: 林祥睿 | B14: 2 | K14: =SUM(SUM(B14:F14)*360,SUM(G14:J14)*90) -> 720 | L14: 160 | N14: =K14+L14-M14 -> 880 | O14: 未結帳款 | P14: 柳攸孟 | T14: 現金 | U14: =SUMIF(O8:O102,"現金",N8:N102) -> 0
A15: 王儷穎 | B15: 1 | K15: =SUM(SUM(B15:F15)*360,SUM(G15:J15)*90) -> 360 | N15: =K15+L15-M15 -> 360 | O15: 匯款 | T15: 未結帳款 | U15: =SUMIF(O8:O102,"未結帳款",N8:N103) -> 6600 | V15: =SUMIF(P8:P100,"銷帳",N8:N100) -> 0
K16: =SUM(SUM(B16:F16)*360,SUM(G16:J16)*90) -> 0 | N16: =K16+L16-M16 -> 0 | T16: 銷帳 | X16: 物流
K17: =SUM(SUM(B17:F17)*360,SUM(G17:J17)*90) -> 0 | N17: =K17+L17-M17 -> 0 | R17: 商品銷售量 | X17: 運費實收 | Y17: =U9 -> 480
K18: =SUM(SUM(B18:F18)*360,SUM(G18:J18)*90) -> 0 | N18: =K18+L18-M18 -> 0 | T18: 販售量 | U18: 公關品 | V18: 總盒數 | X18: 運費實支 | Y18: 2080
K19: =SUM(SUM(B19:F19)*360,SUM(G19:J19)*90) -> 0 | N19: =K19+L19-M19 -> 0 | R19: 禮盒 | S19: 綜合 | T19: =SUMIF(P8:P102,"<>公關品",B8:B100) -> 14 | U19: =SUMIF(P8:P102,"公關品",B8:B100) -> 0 | V19: =SUM(T19:T23,U19) -> 18 | X19: 公關運費 | Y19: =SUMIF(P8:P100,"公關品",L8:L100) -> 0
K20: =SUM(SUM(B20:F20)*360,SUM(G20:J20)*90) -> 0 | N20: =K20+L20-M20 -> 0 | S20: 原味 | T20: =SUMIF(P8:P102,"<>公關品",C8:C100) -> 1 | U20: =SUMIF(P8:P102,"公關品",C8:C100) -> 0 | V20: 總顆數 | X20: 物流包材 | Y20: =SUM(Z24:Z27) -> 10
K21: =SUM(SUM(B21:F21)*360,SUM(G21:J21)*90) -> 0 | N21: =K21+L21-M21 -> 0 | S21: 可可 | T21: =SUMIF(P8:P104,"<>公關品",D8:D102) -> 1 | U21: =SUMIF(P8:P102,"公關品",D8:D100) -> 0 | X21: 成本差額 | Y21: =Y17-Y18-Y20+Y19 -> -1610
K22: =SUM(SUM(B22:F22)*360,SUM(G22:J22)*90) -> 0 | N22: =K22+L22-M22 -> 0 | S22: 伯爵 | T22: =SUMIF(P8:P102,"<>公關品",E8:E100) -> 1 | U22: =SUMIF(P8:P102,"公關品",E8:E100) -> 0 | X22: 物流包材
K23: =SUM(SUM(B23:F23)*360,SUM(G23:J23)*90) -> 0 | N23: =K23+L23-M23 -> 0 | S23: 抹茶 | T23: =SUMIF(P8:P102,"<>公關品",F8:F100) -> 1 | U23: =SUMIF(P8:P102,"公關品",F8:F100) -> 0 | X23: 種類 | Y23: 數量 | Z23: 總額
K24: =SUM(SUM(B24:F24)*360,SUM(G24:J24)*90) -> 0 | N24: =K24+L24-M24 -> 0 | R24: 單顆 | S24: 原味 | T24: =SUMIF(P9:P103,"<>公關品",G8:G100) -> 0 | U24: =SUMIF(P8:P102,"公關品",G8:G100) -> 0 | V24: =T19+(T20*4)+T24 -> 18 | X24: 2入紙箱 | Y24: 3
K25: =SUM(SUM(B25:F25)*360,SUM(G25:J25)*90) -> 0 | N25: =K25+L25-M25 -> 0 | S25: 可可 | T25: =SUMIF(P8:P102,"<>公關品",H8:H100) -> 0 | U25: =SUMIF(P8:P102,"公關品",I8:I100) -> 0 | V25: =T19+(T21*4)+T25 -> 18 | X25: 4入紙箱 | Y25: 2 | Z25: =Y25*5 -> 10
K26: =SUM(SUM(B26:F26)*360,SUM(G26:J26)*90) -> 0 | N26: =K26+L26-M26 -> 0 | S26: 伯爵 | T26: =SUMIF(P9:P103,"<>公關品",I8:I100) -> 0 | U26: =SUMIF(P8:P102,"公關品",I8:I100) -> 0 | V26: =T19+(T22*4)+T26 -> 18 | X26: 10入紙箱 | Y26: 2
K27: =SUM(SUM(B27:F27)*360,SUM(G27:J27)*90) -> 0 | N27: =K27+L27-M27 -> 0 | S27: 抹茶 | T27: =SUMIF(P8:P102,"<>公關品",J8:J100) -> 0 | U27: =SUMIF(P9:P103,"公關品",J8:J100) -> 0 | V27: =T19+(T23*4)+T27 -> 18 | X27: 膠帶
K28: =SUM(SUM(B28:F28)*360,SUM(G28:J28)*90) -> 0 | N28: =K28+L28-M28 -> 0
K29: =SUM(SUM(B29:F29)*360,SUM(G29:J29)*90) -> 0 | N29: =K29+L29-M29 -> 0
K30: =SUM(SUM(B30:F30)*360,SUM(G30:J30)*90) -> 0 | N30: =K30+L30-M30 -> 0 | R30: 產能及庫存 | AB30: 今日公關品總結
K31: =SUM(SUM(B31:F31)*360,SUM(G31:J31)*90) -> 0 | N31: =K31+L31-M31 -> 0 | AB31: 總禮盒數 | AC31: =SUM(U19:U23) -> 0
K32: =SUM(SUM(B32:F32)*360,SUM(G32:J32)*90) -> 0 | N32: =K32+L32-M32 -> 0 | R32: 品項 | S32: 原庫存 | T32: 預計產量 | U32: 實際產量 | V32: 耗損 | W32: 實際銷售量 | Y32: 今日庫存 | Z32: 總損耗率 | AB32: 總顆數 | AC32: =SUM(AC33:AC36) -> 0
K33: =SUM(SUM(B33:F33)*360,SUM(G33:J33)*90) -> 0 | N33: =K33+L33-M33 -> 0 | R33: 原味 | S33: ='7'!Y33 -> 4 | T33: 43 | U33: 44 | V33: =SUMIF(R40:R55,"原味",S40:S55) -> 10 | W33: =V24+U24+U19+U20*4 -> 18 | Y33: =S33+U33-V33-W33 -> 20 | Z33: =IFERROR((V33/(U33+S33))," ") -> 0.20833333 | AB33: 原味 | AC33: =U24+U19+U20*4 -> 0
K34: =SUM(SUM(B34:F34)*360,SUM(G34:J34)*90) -> 0 | N34: =K34+L34-M34 -> 0 | R34: 可可 | S34: ='7'!Y34 -> 5 | T34: 45 | U34: 45 | V34: =SUMIF(R41:R55,"可可",S41:S55) -> 3 | W34: =V25+U25+U19+U21*4 -> 18 | Y34: =S34+U34-V34-W34 -> 29 | Z34: =IFERROR((V34/(U34+S34))," ") -> 0.06 | AB34: 可可 | AC34: =U25+U19+U21*4 -> 0
K35: =SUM(SUM(B35:F35)*360,SUM(G35:J35)*90) -> 0 | N35: =K35+L35-M35 -> 0 | R35: 伯爵 | S35: ='7'!Y35 -> 10 | T35: 38 | U35: 31 | V35: =SUMIF(R41:R55,"伯爵",S41:S55) -> 12 | W35: =V26+U26+U19+U22*4 -> 18 | Y35: =S35+U35-V35-W35 -> 11 | Z35: =IFERROR((V35/(U35+S35))," ") -> 0.29268293 | AB35: 伯爵 | AC35: =U26+U19+U22*4 -> 0
K36: =SUM(SUM(B36:F36)*360,SUM(G36:J36)*90) -> 0 | N36: =K36+L36-M36 -> 0 | R36: 抹茶 | S36: ='7'!Y36 -> 4 | T36: 44 | U36: 49 | V36: =SUMIF(R41:R55,"抹茶",S41:S55) -> 7 | W36: =V27+U27+U19+U23*4 -> 18 | Y36: =S36+U36-V36-W36 -> 28 | Z36: =IFERROR((V36/(U36+S36))," ") -> 0.13207547 | AB36: 抹茶 | AC36: =U27+U19+U23*4 -> 0
K37: =SUM(SUM(B37:F37)*360,SUM(G37:J37)*90) -> 0 | N37: =K37+L37-M37 -> 0
K38: =SUM(SUM(B38:F38)*360,SUM(G38:J38)*90) -> 0 | N38: =K38+L38-M38 -> 0 | R38: 損耗原因
K39: =SUM(SUM(B39:F39)*360,SUM(G39:J39)*90) -> 0 | N39: =K39+L39-M39 -> 0
K40: =SUM(SUM(B40:F40)*360,SUM(G40:J40)*90) -> 0 | N40: =K40+L40-M40 -> 0 | R40: 品項 | S40: 數量 | T40: 類別 | U40: 原因
K41: =SUM(SUM(B41:F41)*360,SUM(G41:J41)*90) -> 0 | N41: =K41+L41-M41 -> 0 | R41: 原味 | S41: 5 | T41: 技術
K42: =SUM(SUM(B42:F42)*360,SUM(G42:J42)*90) -> 0 | N42: =K42+L42-M42 -> 0 | R42: 可可 | S42: 3 | T42: 技術
K43: =SUM(SUM(B43:F43)*360,SUM(G43:J43)*90) -> 0 | N43: =K43+L43-M43 -> 0 | R43: 伯爵 | S43: 1 | T43: 技術
K44: =SUM(SUM(B44:F44)*360,SUM(G44:J44)*90) -> 0 | N44: =K44+L44-M44 -> 0 | R44: 抹茶 | S44: 7 | T44: 技術
K45: =SUM(SUM(B45:F45)*360,SUM(G45:J45)*90) -> 0 | N45: =K45+L45-M45 -> 0 | R45: 原味 | S45: 4 | T45: 技術 | U45: 燒焦
K46: =SUM(SUM(B46:F46)*360,SUM(G46:J46)*90) -> 0 | N46: =K46+L46-M46 -> 0 | R46: 伯爵 | S46: 11 | T46: 技術 | U46: 燒焦
K47: =SUM(SUM(B47:F47)*360,SUM(G47:J47)*90) -> 0 | N47: =K47+L47-M47 -> 0 | R47: 原味 | S47: 1 | T47: 人為 | U47: 掉地上
K48: =SUM(SUM(B48:F48)*360,SUM(G48:J48)*90) -> 0 | N48: =K48+L48-M48 -> 0
K49: =SUM(SUM(B49:F49)*360,SUM(G49:J49)*90) -> 0 | N49: =K49+L49-M49 -> 0
K50: =SUM(SUM(B50:F50)*360,SUM(G50:J50)*90) -> 0 | N50: =K50+L50-M50 -> 0
K51: =SUM(SUM(B51:F51)*360,SUM(G51:J51)*90) -> 0 | N51: =K51+L51-M51 -> 0
K52: =SUM(SUM(B52:F52)*360,SUM(G52:J52)*90) -> 0 | N52: =K52+L52-M52 -> 0
K53: =SUM(SUM(B53:F53)*360,SUM(G53:J53)*90) -> 0 | N53: =K53+L53-M53 -> 0
K54: =SUM(SUM(B54:F54)*360,SUM(G54:J54)*90) -> 0 | N54: =K54+L54-M54 -> 0
K55: =SUM(SUM(B55:F55)*360,SUM(G55:J55)*90) -> 0 | N55: =K55+L55-M55 -> 0
K56: =SUM(SUM(B56:F56)*360,SUM(G56:J56)*90) -> 0 | N56: =K56+L56-M56 -> 0
K57: =SUM(SUM(B57:F57)*360,SUM(G57:J57)*90) -> 0 | N57: =K57+L57-M57 -> 0 | R57: 備註
K58: =SUM(SUM(B58:F58)*360,SUM(G58:J58)*90) -> 0 | N58: =K58+L58-M58 -> 0
K59: =SUM(SUM(B59:F59)*360,SUM(G59:J59)*90) -> 0 | N59: =K59+L59-M59 -> 0
K60: =SUM(SUM(B60:F60)*360,SUM(G60:J60)*90) -> 0 | N60: =K60+L60-M60 -> 0
K61: =SUM(SUM(B61:F61)*360,SUM(G61:J61)*90) -> 0 | N61: =K61+L61-M61 -> 0
K62: =SUM(SUM(B62:F62)*360,SUM(G62:J62)*90) -> 0 | N62: =K62+L62-M62 -> 0
K63: =SUM(SUM(B63:F63)*360,SUM(G63:J63)*90) -> 0 | N63: =K63+L63-M63 -> 0
K64: =SUM(SUM(B64:F64)*360,SUM(G64:J64)*90) -> 0 | N64: =K64+L64-M64 -> 0
K65: =SUM(SUM(B65:F65)*360,SUM(G65:J65)*90) -> 0 | N65: =K65+L65-M65 -> 0
K66: =SUM(SUM(B66:F66)*360,SUM(G66:J66)*90) -> 0 | N66: =K66+L66-M66 -> 0
K67: =SUM(SUM(B67:F67)*360,SUM(G67:J67)*90) -> 0 | N67: =K67+L67-M67 -> 0
K68: =SUM(SUM(B68:F68)*360,SUM(G68:J68)*90) -> 0 | N68: =K68+L68-M68 -> 0
K69: =SUM(SUM(B69:F69)*360,SUM(G69:J69)*90) -> 0 | N69: =K69+L69-M69 -> 0
... K101: =SUM(SUM(B101:F101)*360,SUM(G101:J101)*90) -> 0 | N101: =K101+L101-M101 -> 0

Sheet 9
A1: 日報表
A5: 銷售明細 | R5: 總結
A6: 類別 | B6: 禮盒 | G6: 單顆 | K6: 金額
A7: 購買人 | B7: 綜合 | C7: 原味 | D7: 可可 | E7: 伯爵 | F7: 抹茶 | G7: 原味. | H7: 可可. | I7: 伯爵. | J7: 抹茶. | K7: 金額 | L7: 運費 | M7: 折讓金額 | N7: 實收金額 | O7: 欄1 | P7: 備註
A8: 張文信 | B8: 3 | K8: =SUM(SUM(B8:F8)*360,SUM(G8:J8)*90) -> 1080 | N8: =K8+L8-M8 -> 1080 | O8: 匯款 | R8: 金流 | X8: 應收帳款 | AB8: 今日未結帳款清單 | AC8: 今日銷帳清單
A9: 派大星 | G9: 1 | H9: 2 | I9: 1 | K9: =SUM(SUM(B9:F9)*360,SUM(G9:J9)*90) -> 360 | N9: =K9+L9-M9 -> 360 | O9: 匯款 | P9: 自取 | R9: 營業總額 | T9: 運費 | U9: =SUMIF(表格1_334515253545556[欄1],"<>公關品",表格1_334515253545556[運費]) -> 800 | X9: 累積未結 | Y9: =INDEX('8'!Y12:Z13,1,1) -> 5904 | AB9: {=_xlfn.LET(_xlpm.unpaid,_xlfn.UNIQUE(_xlfn._xlws.FILTER(A8:A100,O8:O100="未結帳款","今日無欠款")),IF(_xlpm.unpaid="今日無欠款","今日無欠款",_xlpm.unpaid&"："&SUMIFS(N8:N100,A8:A100,_xlpm.unpaid,O8:O100,"未結帳款")))} -> 林祥睿：8360 | AC9: {=_xlfn.LET(_xlpm.paid,_xlfn.UNIQUE(_xlfn._xlws.FILTER(A8:A100,P8:P100="銷帳","今日無銷帳")),IF(_xlpm.paid="今日無銷帳","今日無銷帳",_xlpm.paid&"："&SUMIFS(N8:N100,A8:A100,_xlpm.paid,P8:P100,"銷帳")))} -> 今日無銷帳
A10: 李張秀菊 | B10: 12 | K10: =SUM(SUM(B10:F10)*360,SUM(G10:J10)*90) -> 4320 | M10: 360 | N10: =K10+L10-M10 -> 3960 | O10: 匯款 | R10: =SUM(K8:K101)-V15 -> 21960 | T10: 折讓 | U10: =SUM(M8:M101) -> 2160 | X10: 今日未結 | Y10: =U15 -> 8360
A11: 林祥睿 | B11: 5 | K11: =SUM(SUM(B11:F11)*360,SUM(G11:J11)*90) -> 1800 | N11: =K11+L11-M11 -> 1800 | O11: 未結帳款 | P11: 蘇伯偉 | R11: 營業額 | T11: 公關品 | U11: =SUMIF(P8:P100,"公關品",K8:K103) -> 0 | X11: 今日回款 | Y11: =V15 -> 0
A12: 林祥睿 | B12: 2 | K12: =SUM(SUM(B12:F12)*360,SUM(G12:J12)*90) -> 720 | L12: 160 | N12: =K12+L12-M12 -> 880 | O12: 未結帳款 | P12: 鄭昱翔 | R12: =R10-U10-U11 -> 19800 | T12: 應收 | V12: 實收 | X12: 剩餘未結 | Y12: =Y9+Y10-Y11 -> 14264
A13: 林祥睿 | B13: 4 | K13: =SUM(SUM(B13:F13)*360,SUM(G13:J13)*90) -> 1440 | N13: =K13+L13-M13 -> 1440 | O13: 未結帳款 | P13: 余軍威 | T13: 匯款 | U13: =SUMIF(O8:O101,"匯款",N8:N101) -> 11880
A14: 林祥睿 | B14: 2 | K14: =SUM(SUM(B14:F14)*360,SUM(G14:J14)*90) -> 720 | L14: 160 | M14: 360 | N14: =K14+L14-M14 -> 520 | O14: 未結帳款 | P14: 楊智鈞 | T14: 現金 | U14: =SUMIF(O8:O102,"現金",N8:N102) -> 360
A15: 林祥睿 | B15: 2 | K15: =SUM(SUM(B15:F15)*360,SUM(G15:J15)*90) -> 720 | L15: 160 | N15: =K15+L15-M15 -> 880 | O15: 未結帳款 | P15: 張吉愷 | T15: 未結帳款 | U15: =SUMIF(O8:O102,"未結帳款",N8:N103) -> 8360 | V15: =SUMIF(P8:P100,"銷帳",N8:N100) -> 0
A16: 林祥睿 | B16: 2 | K16: =SUM(SUM(B16:F16)*360,SUM(G16:J16)*90) -> 720 | L16: 160 | N16: =K16+L16-M16 -> 880 | O16: 未結帳款 | P16: 陳小陳 | T16: 銷帳 | X16: 物流
A17: 林祥睿 | B17: 2 | K17: =SUM(SUM(B17:F17)*360,SUM(G17:J17)*90) -> 720 | L17: 160 | N17: =K17+L17-M17 -> 880 | O17: 未結帳款 | P17: 曾小曾 | R17: 商品銷售量 | X17: 運費實收 | Y17: =U9 -> 800
A18: 林祥睿 | B18: 3 | K18: =SUM(SUM(B18:F18)*360,SUM(G18:J18)*90) -> 1080 | N18: =K18+L18-M18 -> 1080 | O18: 未結帳款 | P18: 黃詩祐 | T18: 販售量 | U18: 公關品 | V18: 總盒數 | X18: 運費實支 | Y18: 2050
A19: 展昭 | B19: 22 | K19: =SUM(SUM(B19:F19)*360,SUM(G19:J19)*90) -> 7920 | M19: 1440 | N19: =K19+L19-M19 -> 6480 | O19: 匯款 | R19: 禮盒 | S19: 綜合 | T19: =SUMIF(P8:P102,"<>公關品",B8:B100) -> 59 | U19: =SUMIF(P8:P102,"公關品",B8:B100) -> 0 | V19: =SUM(T19:T23,U19) -> 59 | X19: 公關運費 | Y19: =SUMIF(P8:P100,"公關品",L8:L100) -> 0
A20: 威森家具 | H20: 1 | I20: 2 | J20: 1 | K20: =SUM(SUM(B20:F20)*360,SUM(G20:J20)*90) -> 360 | N20: =K20+L20-M20 -> 360 | O20: 現金 | P20: 對面老闆 | S20: 原味 | T20: =SUMIF(P8:P102,"<>公關品",C8:C100) -> 0 | U20: =SUMIF(P8:P102,"公關品",C8:C100) -> 0 | V20: 總顆數 | X20: 物流包材 | Y20: =SUM(Z24:Z27) -> 0
K21: =SUM(SUM(B21:F21)*360,SUM(G21:J21)*90) -> 0 | N21: =K21+L21-M21 -> 0 | S21: 可可 | T21: =SUMIF(P8:P104,"<>公關品",D8:D102) -> 0 | U21: =SUMIF(P8:P102,"公關品",D8:D100) -> 0 | X21: 成本差額 | Y21: =Y17-Y18-Y20+Y19 -> -1250
K22: =SUM(SUM(B22:F22)*360,SUM(G22:J22)*90) -> 0 | N22: =K22+L22-M22 -> 0 | S22: 伯爵 | T22: =SUMIF(P8:P102,"<>公關品",E8:E100) -> 0 | U22: =SUMIF(P8:P102,"公關品",E8:E100) -> 0 | X22: 物流包材
K23: =SUM(SUM(B23:F23)*360,SUM(G23:J23)*90) -> 0 | N23: =K23+L23-M23 -> 0 | S23: 抹茶 | T23: =SUMIF(P8:P102,"<>公關品",F8:F100) -> 0 | U23: =SUMIF(P8:P102,"公關品",F8:F100) -> 0 | X23: 種類 | Y23: 數量 | Z23: 總額
K24: =SUM(SUM(B24:F24)*360,SUM(G24:J24)*90) -> 0 | N24: =K24+L24-M24 -> 0 | R24: 單顆 | S24: 原味 | T24: =SUMIF(P9:P103,"<>公關品",G8:G100) -> 1 | U24: =SUMIF(P8:P102,"公關品",G8:G100) -> 0 | V24: =T19+(T20*4)+T24 -> 60 | X24: 2入紙箱
K25: =SUM(SUM(B25:F25)*360,SUM(G25:J25)*90) -> 0 | N25: =K25+L25-M25 -> 0 | S25: 可可 | T25: =SUMIF(P8:P102,"<>公關品",H8:H100) -> 3 | U25: =SUMIF(P8:P102,"公關品",I8:I100) -> 0 | V25: =T19+(T21*4)+T25 -> 62 | X25: 4入紙箱 | Z25: =Y25*5 -> 0
K26: =SUM(SUM(B26:F26)*360,SUM(G26:J26)*90) -> 0 | N26: =K26+L26-M26 -> 0 | S26: 伯爵 | T26: =SUMIF(P9:P103,"<>公關品",I8:I100) -> 3 | U26: =SUMIF(P8:P102,"公關品",I8:I100) -> 0 | V26: =T19+(T22*4)+T26 -> 62 | X26: 10入紙箱
K27: =SUM(SUM(B27:F27)*360,SUM(G27:J27)*90) -> 0 | N27: =K27+L27-M27 -> 0 | S27: 抹茶 | T27: =SUMIF(P8:P102,"<>公關品",J8:J100) -> 1 | U27: =SUMIF(P9:P103,"公關品",J8:J100) -> 0 | V27: =T19+(T23*4)+T27 -> 60 | X27: 膠帶
K28: =SUM(SUM(B28:F28)*360,SUM(G28:J28)*90) -> 0 | N28: =K28+L28-M28 -> 0
K29: =SUM(SUM(B29:F29)*360,SUM(G29:J29)*90) -> 0 | N29: =K29+L29-M29 -> 0
K30: =SUM(SUM(B30:F30)*360,SUM(G30:J30)*90) -> 0 | N30: =K30+L30-M30 -> 0 | R30: 產能及庫存 | AB30: 今日公關品總結
K31: =SUM(SUM(B31:F31)*360,SUM(G31:J31)*90) -> 0 | N31: =K31+L31-M31 -> 0 | AB31: 總禮盒數 | AC31: =SUM(U19:U23) -> 0
K32: =SUM(SUM(B32:F32)*360,SUM(G32:J32)*90) -> 0 | N32: =K32+L32-M32 -> 0 | R32: 品項 | S32: 原庫存 | T32: 預計產量 | U32: 實際產量 | V32: 耗損 | W32: 實際銷售量 | Y32: 今日庫存 | Z32: 總損耗率 | AB32: 總顆數 | AC32: =SUM(AC33:AC36) -> 0
K33: =SUM(SUM(B33:F33)*360,SUM(G33:J33)*90) -> 0 | N33: =K33+L33-M33 -> 0 | R33: 原味 | S33: ='8'!Y33 -> 20 | U33: 46 | V33: =SUMIF(R40:R55,"原味",S40:S55) -> 6 | W33: =V24+U24+U19+U20*4 -> 60 | Y33: =S33+U33-V33-W33 -> 0 | Z33: =IFERROR((V33/(U33+S33))," ") -> 0.090909091 | AB33: 原味 | AC33: =U24+U19+U20*4 -> 0
K34: =SUM(SUM(B34:F34)*360,SUM(G34:J34)*90) -> 0 | N34: =K34+L34-M34 -> 0 | R34: 可可 | S34: ='8'!Y34 -> 29 | U34: 45 | V34: =SUMIF(R41:R55,"可可",S41:S55) -> 1 | W34: =V25+U25+U19+U21*4 -> 62 | Y34: =S34+U34-V34-W34 -> 11 | Z34: =IFERROR((V34/(U34+S34))," ") -> 0.013513514 | AB34: 可可 | AC34: =U25+U19+U21*4 -> 0
K35: =SUM(SUM(B35:F35)*360,SUM(G35:J35)*90) -> 0 | N35: =K35+L35-M35 -> 0 | R35: 伯爵 | S35: ='8'!Y35 -> 11 | U35: 62 | V35: =SUMIF(R41:R55,"伯爵",S41:S55) -> 1 | W35: =V26+U26+U19+U22*4 -> 62 | Y35: =S35+U35-V35-W35 -> 10 | Z35: =IFERROR((V35/(U35+S35))," ") -> 0.01369863 | AB35: 伯爵 | AC35: =U26+U19+U22*4 -> 0
K36: =SUM(SUM(B36:F36)*360,SUM(G36:J36)*90) -> 0 | N36: =K36+L36-M36 -> 0 | R36: 抹茶 | S36: ='8'!Y36 -> 28 | U36: 46 | V36: =SUMIF(R41:R55,"抹茶",S41:S55) -> 1 | W36: =V27+U27+U19+U23*4 -> 60 | Y36: =S36+U36-V36-W36 -> 13 | Z36: =IFERROR((V36/(U36+S36))," ") -> 0.013513514 | AB36: 抹茶 | AC36: =U27+U19+U23*4 -> 0
K37: =SUM(SUM(B37:F37)*360,SUM(G37:J37)*90) -> 0 | N37: =K37+L37-M37 -> 0
K38: =SUM(SUM(B38:F38)*360,SUM(G38:J38)*90) -> 0 | N38: =K38+L38-M38 -> 0 | R38: 損耗原因
K39: =SUM(SUM(B39:F39)*360,SUM(G39:J39)*90) -> 0 | N39: =K39+L39-M39 -> 0
K40: =SUM(SUM(B40:F40)*360,SUM(G40:J40)*90) -> 0 | N40: =K40+L40-M40 -> 0 | R40: 品項 | S40: 數量 | T40: 類別 | U40: 原因
K41: =SUM(SUM(B41:F41)*360,SUM(G41:J41)*90) -> 0 | N41: =K41+L41-M41 -> 0 | R41: 原味 | S41: 6 | T41: 技術
K42: =SUM(SUM(B42:F42)*360,SUM(G42:J42)*90) -> 0 | N42: =K42+L42-M42 -> 0 | R42: 伯爵 | S42: 1 | T42: 吃掉
K43: =SUM(SUM(B43:F43)*360,SUM(G43:J43)*90) -> 0 | N43: =K43+L43-M43 -> 0 | R43: 可可 | S43: 1 | T43: 技術
K44: =SUM(SUM(B44:F44)*360,SUM(G44:J44)*90) -> 0 | N44: =K44+L44-M44 -> 0
K45: =SUM(SUM(B45:F45)*360,SUM(G45:J45)*90) -> 0 | N45: =K45+L45-M45 -> 0
K46: =SUM(SUM(B46:F46)*360,SUM(G46:J46)*90) -> 0 | N46: =K46+L46-M46 -> 0 | R46: 抹茶 | S46: 1 | T46: 人為 | U46: 掉地上
K47: =SUM(SUM(B47:F47)*360,SUM(G47:J47)*90) -> 0 | N47: =K47+L47-M47 -> 0
K48: =SUM(SUM(B48:F48)*360,SUM(G48:J48)*90) -> 0 | N48: =K48+L48-M48 -> 0
K49: =SUM(SUM(B49:F49)*360,SUM(G49:J49)*90) -> 0 | N49: =K49+L49-M49 -> 0
K50: =SUM(SUM(B50:F50)*360,SUM(G50:J50)*90) -> 0 | N50: =K50+L50-M50 -> 0
K51: =SUM(SUM(B51:F51)*360,SUM(G51:J51)*90) -> 0 | N51: =K51+L51-M51 -> 0
K52: =SUM(SUM(B52:F52)*360,SUM(G52:J52)*90) -> 0 | N52: =K52+L52-M52 -> 0
K53: =SUM(SUM(B53:F53)*360,SUM(G53:J53)*90) -> 0 | N53: =K53+L53-M53 -> 0
K54: =SUM(SUM(B54:F54)*360,SUM(G54:J54)*90) -> 0 | N54: =K54+L54-M54 -> 0
K55: =SUM(SUM(B55:F55)*360,SUM(G55:J55)*90) -> 0 | N55: =K55+L55-M55 -> 0
K56: =SUM(SUM(B56:F56)*360,SUM(G56:J56)*90) -> 0 | N56: =K56+L56-M56 -> 0
K57: =SUM(SUM(B57:F57)*360,SUM(G57:J57)*90) -> 0 | N57: =K57+L57-M57 -> 0 | R57: 備註
K58: =SUM(SUM(B58:F58)*360,SUM(G58:J58)*90) -> 0 | N58: =K58+L58-M58 -> 0
K59: =SUM(SUM(B59:F59)*360,SUM(G59:J59)*90) -> 0 | N59: =K59+L59-M59 -> 0
K60: =SUM(SUM(B60:F60)*360,SUM(G60:J60)*90) -> 0 | N60: =K60+L60-M60 -> 0
K61: =SUM(SUM(B61:F61)*360,SUM(G61:J61)*90) -> 0 | N61: =K61+L61-M61 -> 0
K62: =SUM(SUM(B62:F62)*360,SUM(G62:J62)*90) -> 0 | N62: =K62+L62-M62 -> 0
K63: =SUM(SUM(B63:F63)*360,SUM(G63:J63)*90) -> 0 | N63: =K63+L63-M63 -> 0
K64: =SUM(SUM(B64:F64)*360,SUM(G64:J64)*90) -> 0 | N64: =K64+L64-M64 -> 0
K65: =SUM(SUM(B65:F65)*360,SUM(G65:J65)*90) -> 0 | N65: =K65+L65-M65 -> 0
K66: =SUM(SUM(B66:F66)*360,SUM(G66:J66)*90) -> 0 | N66: =K66+L66-M66 -> 0
K67: =SUM(SUM(B67:F67)*360,SUM(G67:J67)*90) -> 0 | N67: =K67+L67-M67 -> 0
K68: =SUM(SUM(B68:F68)*360,SUM(G68:J68)*90) -> 0 | N68: =K68+L68-M68 -> 0
K69: =SUM(SUM(B69:F69)*360,SUM(G69:J69)*90) -> 0 | N69: =K69+L69-M69 -> 0
... K101: =SUM(SUM(B101:F101)*360,SUM(G101:J101)*90) -> 0 | N101: =K101+L101-M101 -> 0

Sheet 10
A1: 日報表
A5: 銷售明細 | R5: 總結
A6: 類別 | B6: 禮盒 | G6: 單顆 | K6: 金額
A7: 購買人 | B7: 綜合 | C7: 原味 | D7: 可可 | E7: 伯爵 | F7: 抹茶 | G7: 原味. | H7: 可可. | I7: 伯爵. | J7: 抹茶. | K7: 金額 | L7: 運費 | M7: 折讓金額 | N7: 實收金額 | O7: 欄1 | P7: 備註
A8: 周先生 | G8: 1 | I8: 1 | J8: 2 | K8: =SUM(SUM(B8:F8)*360,SUM(G8:J8)*90) -> 360 | N8: =K8+L8-M8 -> 360 | O8: 現金 | P8: 店取 | R8: 金流 | X8: 應收帳款 | AB8: 今日未結帳款清單 | AC8: 今日銷帳清單
A9: 林祥睿 | B9: 2 | K9: =SUM(SUM(B9:F9)*360,SUM(G9:J9)*90) -> 720 | L9: 160 | N9: =K9+L9-M9 -> 880 | O9: 未結帳款 | P9: 李小丁 | R9: 營業總額 | T9: 運費 | U9: =SUMIF(表格1_33451525354555657[欄1],"<>公關品",表格1_33451525354555657[運費]) -> 2240 | X9: 累積未結 | Y9: =INDEX('9'!Y12:Z13,1,1) -> 14264 | AB9: {=_xlfn.LET(_xlpm.unpaid,_xlfn.UNIQUE(_xlfn._xlws.FILTER(A8:A100,O8:O100="未結帳款","今日無欠款")),IF(_xlpm.unpaid="今日無欠款","今日無欠款",_xlpm.unpaid&"："&SUMIFS(N8:N100,A8:A100,_xlpm.unpaid,O8:O100,"未結帳款")))} -> 林祥睿：16120 | AC9: {=_xlfn.LET(_xlpm.paid,_xlfn.UNIQUE(_xlfn._xlws.FILTER(A8:A100,P8:P100="銷帳","今日無銷帳")),IF(_xlpm.paid="今日無銷帳","今日無銷帳",_xlpm.paid&"："&SUMIFS(N8:N100,A8:A100,_xlpm.paid,P8:P100,"銷帳")))} -> 今日無銷帳
A10: 林祥睿 | B10: 1 | K10: =SUM(SUM(B10:F10)*360,SUM(G10:J10)*90) -> 360 | L10: 160 | N10: =K10+L10-M10 -> 520 | O10: 未結帳款 | P10: 夏詩萌 | R10: =SUM(K8:K101)-V15 -> 16920 | T10: 折讓 | U10: =SUM(M8:M101) -> 0 | X10: 今日未結 | Y10: =U15 -> 17720 | AB10: 吳宜亭：880
A11: 林祥睿 | B11: 1 | K11: =SUM(SUM(B11:F11)*360,SUM(G11:J11)*90) -> 360 | L11: 160 | N11: =K11+L11-M11 -> 520 | O11: 未結帳款 | P11: 劉美美 | R11: 營業額 | T11: 公關品 | U11: =SUMIF(P8:P100,"公關品",K8:K103) -> 0 | X11: 今日回款 | Y11: =V15 -> 0 | AB11: 李泓陞：720
A12: 林祥睿 | B12: 1 | K12: =SUM(SUM(B12:F12)*360,SUM(G12:J12)*90) -> 360 | L12: 160 | N12: =K12+L12-M12 -> 520 | O12: 未結帳款 | P12: 徐妍熙 | R12: =R10-U10-U11 -> 16920 | T12: 應收 | V12: 實收 | X12: 剩餘未結 | Y12: =Y9+Y10-Y11 -> 31984
A13: 林祥睿 | B13: 1 | K13: =SUM(SUM(B13:F13)*360,SUM(G13:J13)*90) -> 360 | L13: 160 | N13: =K13+L13-M13 -> 520 | O13: 未結帳款 | P13: 林芯璿 | T13: 匯款 | U13: =SUMIF(O8:O101,"匯款",N8:N101) -> 0
A14: 林祥睿 | B14: 3 | K14: =SUM(SUM(B14:F14)*360,SUM(G14:J14)*90) -> 1080 | N14: =K14+L14-M14 -> 1080 | O14: 未結帳款 | P14: 郭芷涵 | T14: 現金 | U14: =SUMIF(O8:O102,"現金",N8:N102) -> 1440
A15: 林祥睿 | B15: 3 | K15: =SUM(SUM(B15:F15)*360,SUM(G15:J15)*90) -> 1080 | N15: =K15+L15-M15 -> 1080 | O15: 未結帳款 | P15: 潘威綸 | T15: 未結帳款 | U15: =SUMIF(O8:O102,"未結帳款",N8:N103) -> 17720 | V15: =SUMIF(P8:P100,"銷帳",N8:N100) -> 0
A16: 林祥睿 | B16: 2 | K16: =SUM(SUM(B16:F16)*360,SUM(G16:J16)*90) -> 720 | L16: 160 | N16: =K16+L16-M16 -> 880 | O16: 未結帳款 | P16: 小小七 | T16: 銷帳 | X16: 物流
A17: 林祥睿 | B17: 2 | K17: =SUM(SUM(B17:F17)*360,SUM(G17:J17)*90) -> 720 | L17: 160 | N17: =K17+L17-M17 -> 880 | O17: 未結帳款 | P17: 黃品涵 | R17: 商品銷售量 | X17: 運費實收 | Y17: =U9 -> 2240
A18: 林祥睿 | B18: 2 | K18: =SUM(SUM(B18:F18)*360,SUM(G18:J18)*90) -> 720 | L18: 160 | N18: =K18+L18-M18 -> 880 | O18: 未結帳款 | P18: 劉玉凡 | T18: 販售量 | U18: 公關品 | V18: 總盒數 | X18: 運費實支 | Y18: 3009
A19: 林祥睿 | B19: 2 | K19: =SUM(SUM(B19:F19)*360,SUM(G19:J19)*90) -> 720 | L19: 160 | N19: =K19+L19-M19 -> 880 | O19: 未結帳款 | P19: 張景涵 | R19: 禮盒 | S19: 綜合 | T19: =SUMIF(P8:P102,"<>公關品",B8:B100) -> 41 | U19: =SUMIF(P8:P102,"公關品",B8:B100) -> 0 | V19: =SUM(T19:T23,U19) -> 44 | X19: 公關運費 | Y19: =SUMIF(P8:P100,"公關品",L8:L100) -> 0
A20: 林祥睿 | B20: 2 | K20: =SUM(SUM(B20:F20)*360,SUM(G20:J20)*90) -> 720 | L20: 160 | N20: =K20+L20-M20 -> 880 | O20: 未結帳款 | P20: 崔江朔 | S20: 原味 | T20: =SUMIF(P8:P102,"<>公關品",C8:C100) -> 0 | U20: =SUMIF(P8:P102,"公關品",C8:C100) -> 0 | V20: 總顆數 | X20: 物流包材 | Y20: =SUM(Z24:Z27) -> 0
A21: 林祥睿 | B21: 3 | K21: =SUM(SUM(B21:F21)*360,SUM(G21:J21)*90) -> 1080 | N21: =K21+L21-M21 -> 1080 | O21: 未結帳款 | P21: 詹仁勳 | S21: 可可 | T21: =SUMIF(P8:P104,"<>公關品",D8:D102) -> 1 | U21: =SUMIF(P8:P102,"公關品",D8:D100) -> 0 | X21: 成本差額 | Y21: =Y17-Y18-Y20+Y19 -> -769
A22: 林士娟 | B22: 3 | K22: =SUM(SUM(B22:F22)*360,SUM(G22:J22)*90) -> 1080 | N22: =K22+L22-M22 -> 1080 | O22: 現金 | P22: 王薇慈 | S22: 伯爵 | T22: =SUMIF(P8:P102,"<>公關品",E8:E100) -> 1 | U22: =SUMIF(P8:P102,"公關品",E8:E100) -> 0 | X22: 物流包材
A23: 林祥睿 | B23: 1 | K23: =SUM(SUM(B23:F23)*360,SUM(G23:J23)*90) -> 360 | L23: 160 | N23: =K23+L23-M23 -> 520 | O23: 未結帳款 | P23: 黃建豪 | S23: 抹茶 | T23: =SUMIF(P8:P102,"<>公關品",F8:F100) -> 1 | U23: =SUMIF(P8:P102,"公關品",F8:F100) -> 0 | X23: 種類 | Y23: 數量 | Z23: 總額
A24: 林祥睿 | B24: 3 | K24: =SUM(SUM(B24:F24)*360,SUM(G24:J24)*90) -> 1080 | N24: =K24+L24-M24 -> 1080 | O24: 未結帳款 | P24: 李承宇 | R24: 單顆 | S24: 原味 | T24: =SUMIF(P9:P103,"<>公關品",G8:G100) -> 1 | U24: =SUMIF(P8:P102,"公關品",G8:G100) -> 0 | V24: =T19+(T20*4)+T24 -> 42 | X24: 2入紙箱
A25: 林祥睿 | B25: 1 | K25: =SUM(SUM(B25:F25)*360,SUM(G25:J25)*90) -> 360 | L25: 160 | N25: =K25+L25-M25 -> 520 | O25: 未結帳款 | P25: 王威峻 | S25: 可可 | T25: =SUMIF(P8:P102,"<>公關品",H8:H100) -> 2 | U25: =SUMIF(P8:P102,"公關品",I8:I100) -> 0 | V25: =T19+(T21*4)+T25 -> 47 | X25: 4入紙箱 | Z25: =Y25*5 -> 0
A26: 林祥睿 | B26: 1 | K26: =SUM(SUM(B26:F26)*360,SUM(G26:J26)*90) -> 360 | L26: 160 | N26: =K26+L26-M26 -> 520 | O26: 未結帳款 | P26: 吳思錡 | S26: 伯爵 | T26: =SUMIF(P9:P103,"<>公關品",I8:I100) -> 4 | U26: =SUMIF(P8:P102,"公關品",I8:I100) -> 0 | V26: =T19+(T22*4)+T26 -> 49 | X26: 10入紙箱
A27: 林祥睿 | B27: 5 | K27: =SUM(SUM(B27:F27)*360,SUM(G27:J27)*90) -> 1800 | N27: =K27+L27-M27 -> 1800 | O27: 未結帳款 | P27: 周梓筠 | S27: 抹茶 | T27: =SUMIF(P8:P102,"<>公關品",J8:J100) -> 5 | U27: =SUMIF(P9:P103,"公關品",J8:J100) -> 0 | V27: =T19+(T23*4)+T27 -> 50 | X27: 膠帶
A28: 吳宜亭 | B28: 2 | K28: =SUM(SUM(B28:F28)*360,SUM(G28:J28)*90) -> 720 | L28: 160 | N28: =K28+L28-M28 -> 880 | O28: 未結帳款 | P28: 陳佳慧
A29: 林祥睿 | D29: 1 | E29: 1 | F29: 1 | K29: =SUM(SUM(B29:F29)*360,SUM(G29:J29)*90) -> 1080 | N29: =K29+L29-M29 -> 1080 | O29: 未結帳款
A30: 李泓陞 | H30: 2 | I30: 3 | J30: 3 | K30: =SUM(SUM(B30:F30)*360,SUM(G30:J30)*90) -> 720 | N30: =K30+L30-M30 -> 720 | O30: 未結帳款 | R30: 產能及庫存 | AB30: 今日公關品總結
K31: =SUM(SUM(B31:F31)*360,SUM(G31:J31)*90) -> 0 | N31: =K31+L31-M31 -> 0 | AB31: 總禮盒數 | AC31: =SUM(U19:U23) -> 0
K32: =SUM(SUM(B32:F32)*360,SUM(G32:J32)*90) -> 0 | N32: =K32+L32-M32 -> 0 | R32: 品項 | S32: 原庫存 | T32: 預計產量 | U32: 實際產量 | V32: 耗損 | W32: 實際銷售量 | Y32: 今日庫存 | Z32: 總損耗率 | AB32: 總顆數 | AC32: =SUM(AC33:AC36) -> 0
K33: =SUM(SUM(B33:F33)*360,SUM(G33:J33)*90) -> 0 | N33: =K33+L33-M33 -> 0 | R33: 原味 | S33: ='9'!Y33 -> 0 | U33: 60 | V33: =SUMIF(R40:R55,"原味",S40:S55) -> 18 | W33: =V24+U24+U19+U20*4 -> 42 | Y33: =S33+U33-V33-W33 -> 0 | Z33: =IFERROR((V33/(U33+S33))," ") -> 0.3 | AB33: 原味 | AC33: =U24+U19+U20*4 -> 0
K34: =SUM(SUM(B34:F34)*360,SUM(G34:J34)*90) -> 0 | N34: =K34+L34-M34 -> 0 | R34: 可可 | S34: ='9'!Y34 -> 11 | U34: 46 | V34: =SUMIF(R41:R55,"可可",S41:S55) -> 10 | W34: =V25+U25+U19+U21*4 -> 47 | Y34: =S34+U34-V34-W34 -> 0 | Z34: =IFERROR((V34/(U34+S34))," ") -> 0.1754386 | AB34: 可可 | AC34: =U25+U19+U21*4 -> 0
K35: =SUM(SUM(B35:F35)*360,SUM(G35:J35)*90) -> 0 | N35: =K35+L35-M35 -> 0 | R35: 伯爵 | S35: ='9'!Y35 -> 10 | U35: 46 | V35: =SUMIF(R41:R55,"伯爵",S41:S55) -> 7 | W35: =V26+U26+U19+U22*4 -> 49 | Y35: =S35+U35-V35-W35 -> 0 | Z35: =IFERROR((V35/(U35+S35))," ") -> 0.125 | AB35: 伯爵 | AC35: =U26+U19+U22*4 -> 0
K36: =SUM(SUM(B36:F36)*360,SUM(G36:J36)*90) -> 0 | N36: =K36+L36-M36 -> 0 | R36: 抹茶 | S36: ='9'!Y36 -> 13 | U36: 46 | V36: =SUMIF(R41:R55,"抹茶",S41:S55) -> 9 | W36: =V27+U27+U19+U23*4 -> 50 | Y36: =S36+U36-V36-W36 -> 0 | Z36: =IFERROR((V36/(U36+S36))," ") -> 0.15254237 | AB36: 抹茶 | AC36: =U27+U19+U23*4 -> 0
K37: =SUM(SUM(B37:F37)*360,SUM(G37:J37)*90) -> 0 | N37: =K37+L37-M37 -> 0
K38: =SUM(SUM(B38:F38)*360,SUM(G38:J38)*90) -> 0 | N38: =K38+L38-M38 -> 0 | R38: 損耗原因
K39: =SUM(SUM(B39:F39)*360,SUM(G39:J39)*90) -> 0 | N39: =K39+L39-M39 -> 0
K40: =SUM(SUM(B40:F40)*360,SUM(G40:J40)*90) -> 0 | N40: =K40+L40-M40 -> 0 | R40: 品項 | S40: 數量 | T40: 類別 | U40: 原因
K41: =SUM(SUM(B41:F41)*360,SUM(G41:J41)*90) -> 0 | N41: =K41+L41-M41 -> 0 | R41: 伯爵 | S41: 2 | T41: 技術
K42: =SUM(SUM(B42:F42)*360,SUM(G42:J42)*90) -> 0 | N42: =K42+L42-M42 -> 0 | R42: 抹茶 | S42: 2 | T42: 技術
K43: =SUM(SUM(B43:F43)*360,SUM(G43:J43)*90) -> 0 | N43: =K43+L43-M43 -> 0 | R43: 原味 | S43: 2 | T43: 吃掉
K44: =SUM(SUM(B44:F44)*360,SUM(G44:J44)*90) -> 0 | N44: =K44+L44-M44 -> 0 | R44: 抹茶 | S44: 1 | T44: 吃掉
K45: =SUM(SUM(B45:F45)*360,SUM(G45:J45)*90) -> 0 | N45: =K45+L45-M45 -> 0 | R45: 原味 | S45: 16 | T45: 人為 | U45: 拍攝用
K46: =SUM(SUM(B46:F46)*360,SUM(G46:J46)*90) -> 0 | N46: =K46+L46-M46 -> 0 | R46: 可可 | S46: 10 | T46: 人為 | U46: 拍攝用
K47: =SUM(SUM(B47:F47)*360,SUM(G47:J47)*90) -> 0 | N47: =K47+L47-M47 -> 0 | R47: 伯爵 | S47: 5 | T47: 人為 | U47: 拍攝用
K48: =SUM(SUM(B48:F48)*360,SUM(G48:J48)*90) -> 0 | N48: =K48+L48-M48 -> 0 | R48: 抹茶 | S48: 6 | T48: 人為 | U48: 拍攝用
K49: =SUM(SUM(B49:F49)*360,SUM(G49:J49)*90) -> 0 | N49: =K49+L49-M49 -> 0
K50: =SUM(SUM(B50:F50)*360,SUM(G50:J50)*90) -> 0 | N50: =K50+L50-M50 -> 0
K51: =SUM(SUM(B51:F51)*360,SUM(G51:J51)*90) -> 0 | N51: =K51+L51-M51 -> 0
K52: =SUM(SUM(B52:F52)*360,SUM(G52:J52)*90) -> 0 | N52: =K52+L52-M52 -> 0
K53: =SUM(SUM(B53:F53)*360,SUM(G53:J53)*90) -> 0 | N53: =K53+L53-M53 -> 0
K54: =SUM(SUM(B54:F54)*360,SUM(G54:J54)*90) -> 0 | N54: =K54+L54-M54 -> 0
K55: =SUM(SUM(B55:F55)*360,SUM(G55:J55)*90) -> 0 | N55: =K55+L55-M55 -> 0
K56: =SUM(SUM(B56:F56)*360,SUM(G56:J56)*90) -> 0 | N56: =K56+L56-M56 -> 0
K57: =SUM(SUM(B57:F57)*360,SUM(G57:J57)*90) -> 0 | N57: =K57+L57-M57 -> 0 | R57: 備註
K58: =SUM(SUM(B58:F58)*360,SUM(G58:J58)*90) -> 0 | N58: =K58+L58-M58 -> 0
K59: =SUM(SUM(B59:F59)*360,SUM(G59:J59)*90) -> 0 | N59: =K59+L59-M59 -> 0
K60: =SUM(SUM(B60:F60)*360,SUM(G60:J60)*90) -> 0 | N60: =K60+L60-M60 -> 0
K61: =SUM(SUM(B61:F61)*360,SUM(G61:J61)*90) -> 0 | N61: =K61+L61-M61 -> 0
K62: =SUM(SUM(B62:F62)*360,SUM(G62:J62)*90) -> 0 | N62: =K62+L62-M62 -> 0
K63: =SUM(SUM(B63:F63)*360,SUM(G63:J63)*90) -> 0 | N63: =K63+L63-M63 -> 0
K64: =SUM(SUM(B64:F64)*360,SUM(G64:J64)*90) -> 0 | N64: =K64+L64-M64 -> 0
K65: =SUM(SUM(B65:F65)*360,SUM(G65:J65)*90) -> 0 | N65: =K65+L65-M65 -> 0
K66: =SUM(SUM(B66:F66)*360,SUM(G66:J66)*90) -> 0 | N66: =K66+L66-M66 -> 0
K67: =SUM(SUM(B67:F67)*360,SUM(G67:J67)*90) -> 0 | N67: =K67+L67-M67 -> 0
K68: =SUM(SUM(B68:F68)*360,SUM(G68:J68)*90) -> 0 | N68: =K68+L68-M68 -> 0
K69: =SUM(SUM(B69:F69)*360,SUM(G69:J69)*90) -> 0 | N69: =K69+L69-M69 -> 0
... K101: =SUM(SUM(B101:F101)*360,SUM(G101:J101)*90) -> 0 | N101: =K101+L101-M101 -> 0

Sheet 11
A1: 日報表
A5: 銷售明細 | R5: 總結
A6: 類別 | B6: 禮盒 | G6: 單顆 | K6: 金額
A7: 購買人 | B7: 綜合 | C7: 原味 | D7: 可可 | E7: 伯爵 | F7: 抹茶 | G7: 原味. | H7: 可可. | I7: 伯爵. | J7: 抹茶. | K7: 金額 | L7: 運費 | M7: 折讓金額 | N7: 實收金額 | O7: 欄1 | P7: 備註
K8: =SUM(SUM(B8:F8)*360,SUM(G8:J8)*90) -> 0 | N8: =K8+L8-M8 -> 0 | R8: 金流 | X8: 應收帳款 | AB8: 今日未結帳款清單 | AC8: 今日銷帳清單
K9: =SUM(SUM(B9:F9)*360,SUM(G9:J9)*90) -> 0 | N9: =K9+L9-M9 -> 0 | R9: 營業總額 | T9: 運費 | U9: =SUMIF(表格1_3345152535455565758[欄1],"<>公關品",表格1_3345152535455565758[運費]) -> 0 | X9: 累積未結 | Y9: =INDEX('10'!Y12:Z13,1,1) -> 31984 | AB9: {=_xlfn.LET(_xlpm.unpaid,_xlfn.UNIQUE(_xlfn._xlws.FILTER(A8:A100,O8:O100="未結帳款","今日無欠款")),IF(_xlpm.unpaid="今日無欠款","今日無欠款",_xlpm.unpaid&"："&SUMIFS(N8:N100,A8:A100,_xlpm.unpaid,O8:O100,"未結帳款")))} -> 今日無欠款 | AC9: {=_xlfn.LET(_xlpm.paid,_xlfn.UNIQUE(_xlfn._xlws.FILTER(A8:A100,P8:P100="銷帳","今日無銷帳")),IF(_xlpm.paid="今日無銷帳","今日無銷帳",_xlpm.paid&"："&SUMIFS(N8:N100,A8:A100,_xlpm.paid,P8:P100,"銷帳")))} -> 今日無銷帳
K10: =SUM(SUM(B10:F10)*360,SUM(G10:J10)*90) -> 0 | N10: =K10+L10-M10 -> 0 | R10: =SUM(K8:K101)-V15 -> 0 | T10: 折讓 | U10: =SUM(M8:M101) -> 0 | X10: 今日未結 | Y10: =U15 -> 0
K11: =SUM(SUM(B11:F11)*360,SUM(G11:J11)*90) -> 0 | N11: =K11+L11-M11 -> 0 | R11: 營業額 | T11: 公關品 | U11: =SUMIF(P8:P100,"公關品",K8:K103) -> 0 | X11: 今日回款 | Y11: =V15 -> 0
K12: =SUM(SUM(B12:F12)*360,SUM(G12:J12)*90) -> 0 | N12: =K12+L12-M12 -> 0 | R12: =R10-U10-U11 -> 0 | T12: 應收 | V12: 實收 | X12: 剩餘未結 | Y12: =Y9+Y10-Y11 -> 31984
K13: =SUM(SUM(B13:F13)*360,SUM(G13:J13)*90) -> 0 | N13: =K13+L13-M13 -> 0 | T13: 匯款 | U13: =SUMIF(O8:O101,"匯款",N8:N101) -> 0
K14: =SUM(SUM(B14:F14)*360,SUM(G14:J14)*90) -> 0 | N14: =K14+L14-M14 -> 0 | T14: 現金 | U14: =SUMIF(O8:O102,"現金",N8:N102) -> 0
K15: =SUM(SUM(B15:F15)*360,SUM(G15:J15)*90) -> 0 | N15: =K15+L15-M15 -> 0 | T15: 未結帳款 | U15: =SUMIF(O8:O102,"未結帳款",N8:N103) -> 0 | V15: =SUMIF(P8:P100,"銷帳",N8:N100) -> 0
K16: =SUM(SUM(B16:F16)*360,SUM(G16:J16)*90) -> 0 | N16: =K16+L16-M16 -> 0 | T16: 銷帳 | X16: 物流
K17: =SUM(SUM(B17:F17)*360,SUM(G17:J17)*90) -> 0 | N17: =K17+L17-M17 -> 0 | R17: 商品銷售量 | X17: 運費實收 | Y17: =U9 -> 0
K18: =SUM(SUM(B18:F18)*360,SUM(G18:J18)*90) -> 0 | N18: =K18+L18-M18 -> 0 | T18: 販售量 | U18: 公關品 | V18: 總盒數 | X18: 運費實支
K19: =SUM(SUM(B19:F19)*360,SUM(G19:J19)*90) -> 0 | N19: =K19+L19-M19 -> 0 | R19: 禮盒 | S19: 綜合 | T19: =SUMIF(P8:P102,"<>公關品",B8:B100) -> 0 | U19: =SUMIF(P8:P102,"公關品",B8:B100) -> 0 | V19: =SUM(T19:T23,U19) -> 0 | X19: 公關運費 | Y19: =SUMIF(P8:P100,"公關品",L8:L100) -> 0
K20: =SUM(SUM(B20:F20)*360,SUM(G20:J20)*90) -> 0 | N20: =K20+L20-M20 -> 0 | S20: 原味 | T20: =SUMIF(P8:P102,"<>公關品",C8:C100) -> 0 | U20: =SUMIF(P8:P102,"公關品",C8:C100) -> 0 | V20: 總顆數 | X20: 物流包材 | Y20: =SUM(Z24:Z27) -> 0
K21: =SUM(SUM(B21:F21)*360,SUM(G21:J21)*90) -> 0 | N21: =K21+L21-M21 -> 0 | S21: 可可 | T21: =SUMIF(P8:P104,"<>公關品",D8:D102) -> 0 | U21: =SUMIF(P8:P102,"公關品",D8:D100) -> 0 | X21: 成本差額 | Y21: =Y17-Y18-Y20+Y19 -> 0
K22: =SUM(SUM(B22:F22)*360,SUM(G22:J22)*90) -> 0 | N22: =K22+L22-M22 -> 0 | S22: 伯爵 | T22: =SUMIF(P8:P102,"<>公關品",E8:E100) -> 0 | U22: =SUMIF(P8:P102,"公關品",E8:E100) -> 0 | X22: 物流包材
K23: =SUM(SUM(B23:F23)*360,SUM(G23:J23)*90) -> 0 | N23: =K23+L23-M23 -> 0 | S23: 抹茶 | T23: =SUMIF(P8:P102,"<>公關品",F8:F100) -> 0 | U23: =SUMIF(P8:P102,"公關品",F8:F100) -> 0 | X23: 種類 | Y23: 數量 | Z23: 總額
K24: =SUM(SUM(B24:F24)*360,SUM(G24:J24)*90) -> 0 | N24: =K24+L24-M24 -> 0 | R24: 單顆 | S24: 原味 | T24: =SUMIF(P9:P103,"<>公關品",G8:G100) -> 0 | U24: =SUMIF(P8:P102,"公關品",G8:G100) -> 0 | V24: =T19+(T20*4)+T24 -> 0 | X24: 2入紙箱
K25: =SUM(SUM(B25:F25)*360,SUM(G25:J25)*90) -> 0 | N25: =K25+L25-M25 -> 0 | S25: 可可 | T25: =SUMIF(P8:P102,"<>公關品",H8:H100) -> 0 | U25: =SUMIF(P8:P102,"公關品",I8:I100) -> 0 | V25: =T19+(T21*4)+T25 -> 0 | X25: 4入紙箱 | Z25: =Y25*5 -> 0
K26: =SUM(SUM(B26:F26)*360,SUM(G26:J26)*90) -> 0 | N26: =K26+L26-M26 -> 0 | S26: 伯爵 | T26: =SUMIF(P9:P103,"<>公關品",I8:I100) -> 0 | U26: =SUMIF(P8:P102,"公關品",I8:I100) -> 0 | V26: =T19+(T22*4)+T26 -> 0 | X26: 10入紙箱
K27: =SUM(SUM(B27:F27)*360,SUM(G27:J27)*90) -> 0 | N27: =K27+L27-M27 -> 0 | S27: 抹茶 | T27: =SUMIF(P8:P102,"<>公關品",J8:J100) -> 0 | U27: =SUMIF(P9:P103,"公關品",J8:J100) -> 0 | V27: =T19+(T23*4)+T27 -> 0 | X27: 膠帶
K28: =SUM(SUM(B28:F28)*360,SUM(G28:J28)*90) -> 0 | N28: =K28+L28-M28 -> 0
K29: =SUM(SUM(B29:F29)*360,SUM(G29:J29)*90) -> 0 | N29: =K29+L29-M29 -> 0
K30: =SUM(SUM(B30:F30)*360,SUM(G30:J30)*90) -> 0 | N30: =K30+L30-M30 -> 0 | R30: 產能及庫存 | AB30: 今日公關品總結
K31: =SUM(SUM(B31:F31)*360,SUM(G31:J31)*90) -> 0 | N31: =K31+L31-M31 -> 0 | AB31: 總禮盒數 | AC31: =SUM(U19:U23) -> 0
K32: =SUM(SUM(B32:F32)*360,SUM(G32:J32)*90) -> 0 | N32: =K32+L32-M32 -> 0 | R32: 品項 | S32: 原庫存 | T32: 預計產量 | U32: 實際產量 | V32: 耗損 | W32: 實際銷售量 | Y32: 今日庫存 | Z32: 總損耗率 | AB32: 總顆數 | AC32: =SUM(AC33:AC36) -> 0
K33: =SUM(SUM(B33:F33)*360,SUM(G33:J33)*90) -> 0 | N33: =K33+L33-M33 -> 0 | R33: 原味 | S33: ='10'!Y33 -> 0 | V33: =SUMIF(R40:R55,"原味",S40:S55) -> 0 | W33: =V24+U24+U19+U20*4 -> 0 | Y33: =S33+U33-V33-W33 -> 0 | Z33: =IFERROR((V33/(U33+S33))," ") | AB33: 原味 | AC33: =U24+U19+U20*4 -> 0
K34: =SUM(SUM(B34:F34)*360,SUM(G34:J34)*90) -> 0 | N34: =K34+L34-M34 -> 0 | R34: 可可 | S34: ='10'!Y34 -> 0 | V34: =SUMIF(R41:R55,"可可",S41:S55) -> 0 | W34: =V25+U25+U19+U21*4 -> 0 | Y34: =S34+U34-V34-W34 -> 0 | Z34: =IFERROR((V34/(U34+S34))," ") | AB34: 可可 | AC34: =U25+U19+U21*4 -> 0
K35: =SUM(SUM(B35:F35)*360,SUM(G35:J35)*90) -> 0 | N35: =K35+L35-M35 -> 0 | R35: 伯爵 | S35: ='10'!Y35 -> 0 | V35: =SUMIF(R41:R55,"伯爵",S41:S55) -> 0 | W35: =V26+U26+U19+U22*4 -> 0 | Y35: =S35+U35-V35-W35 -> 0 | Z35: =IFERROR((V35/(U35+S35))," ") | AB35: 伯爵 | AC35: =U26+U19+U22*4 -> 0
K36: =SUM(SUM(B36:F36)*360,SUM(G36:J36)*90) -> 0 | N36: =K36+L36-M36 -> 0 | R36: 抹茶 | S36: ='10'!Y36 -> 0 | V36: =SUMIF(R41:R55,"抹茶",S41:S55) -> 0 | W36: =V27+U27+U19+U23*4 -> 0 | Y36: =S36+U36-V36-W36 -> 0 | Z36: =IFERROR((V36/(U36+S36))," ") | AB36: 抹茶 | AC36: =U27+U19+U23*4 -> 0
K37: =SUM(SUM(B37:F37)*360,SUM(G37:J37)*90) -> 0 | N37: =K37+L37-M37 -> 0
K38: =SUM(SUM(B38:F38)*360,SUM(G38:J38)*90) -> 0 | N38: =K38+L38-M38 -> 0 | R38: 損耗原因
K39: =SUM(SUM(B39:F39)*360,SUM(G39:J39)*90) -> 0 | N39: =K39+L39-M39 -> 0
K40: =SUM(SUM(B40:F40)*360,SUM(G40:J40)*90) -> 0 | N40: =K40+L40-M40 -> 0 | R40: 品項 | S40: 數量 | T40: 類別 | U40: 原因
K41: =SUM(SUM(B41:F41)*360,SUM(G41:J41)*90) -> 0 | N41: =K41+L41-M41 -> 0
K42: =SUM(SUM(B42:F42)*360,SUM(G42:J42)*90) -> 0 | N42: =K42+L42-M42 -> 0
K43: =SUM(SUM(B43:F43)*360,SUM(G43:J43)*90) -> 0 | N43: =K43+L43-M43 -> 0
K44: =SUM(SUM(B44:F44)*360,SUM(G44:J44)*90) -> 0 | N44: =K44+L44-M44 -> 0
K45: =SUM(SUM(B45:F45)*360,SUM(G45:J45)*90) -> 0 | N45: =K45+L45-M45 -> 0
K46: =SUM(SUM(B46:F46)*360,SUM(G46:J46)*90) -> 0 | N46: =K46+L46-M46 -> 0
K47: =SUM(SUM(B47:F47)*360,SUM(G47:J47)*90) -> 0 | N47: =K47+L47-M47 -> 0
K48: =SUM(SUM(B48:F48)*360,SUM(G48:J48)*90) -> 0 | N48: =K48+L48-M48 -> 0
K49: =SUM(SUM(B49:F49)*360,SUM(G49:J49)*90) -> 0 | N49: =K49+L49-M49 -> 0
K50: =SUM(SUM(B50:F50)*360,SUM(G50:J50)*90) -> 0 | N50: =K50+L50-M50 -> 0
K51: =SUM(SUM(B51:F51)*360,SUM(G51:J51)*90) -> 0 | N51: =K51+L51-M51 -> 0
K52: =SUM(SUM(B52:F52)*360,SUM(G52:J52)*90) -> 0 | N52: =K52+L52-M52 -> 0
... K56: =SUM(SUM(B56:F56)*360,SUM(G56:J56)*90) -> 0 | N56: =K56+L56-M56 -> 0
K57: =SUM(SUM(B57:F57)*360,SUM(G57:J57)*90) -> 0 | N57: =K57+L57-M57 -> 0 | R57: 備註
K58: =SUM(SUM(B58:F58)*360,SUM(G58:J58)*90) -> 0 | N58: =K58+L58-M58 -> 0
K59: =SUM(SUM(B59:F59)*360,SUM(G59:J59)*90) -> 0 | N59: =K59+L59-M59 -> 0
K60: =SUM(SUM(B60:F60)*360,SUM(G60:J60)*90) -> 0 | N60: =K60+L60-M60 -> 0
K61: =SUM(SUM(B61:F61)*360,SUM(G61:J61)*90) -> 0 | N61: =K61+L61-M61 -> 0
K62: =SUM(SUM(B62:F62)*360,SUM(G62:J62)*90) -> 0 | N62: =K62+L62-M62 -> 0
K63: =SUM(SUM(B63:F63)*360,SUM(G63:J63)*90) -> 0 | N63: =K63+L63-M63 -> 0
K64: =SUM(SUM(B64:F64)*360,SUM(G64:J64)*90) -> 0 | N64: =K64+L64-M64 -> 0
K65: =SUM(SUM(B65:F65)*360,SUM(G65:J65)*90) -> 0 | N65: =K65+L65-M65 -> 0
K66: =SUM(SUM(B66:F66)*360,SUM(G66:J66)*90) -> 0 | N66: =K66+L66-M66 -> 0
K67: =SUM(SUM(B67:F67)*360,SUM(G67:J67)*90) -> 0 | N67: =K67+L67-M67 -> 0
K68: =SUM(SUM(B68:F68)*360,SUM(G68:J68)*90) -> 0 | N68: =K68+L68-M68 -> 0
K69: =SUM(SUM(B69:F69)*360,SUM(G69:J69)*90) -> 0 | N69: =K69+L69-M69 -> 0
... K101: =SUM(SUM(B101:F101)*360,SUM(G101:J101)*90) -> 0 | N101: =K101+L101-M101 -> 0

Sheet 12
A1: 日報表
A5: 銷售明細 | R5: 總結
A6: 類別 | B6: 禮盒 | G6: 單顆 | K6: 金額
A7: 購買人 | B7: 綜合 | C7: 原味 | D7: 可可 | E7: 伯爵 | F7: 抹茶 | G7: 原味. | H7: 可可. | I7: 伯爵. | J7: 抹茶. | K7: 金額 | L7: 運費 | M7: 折讓金額 | N7: 實收金額 | O7: 欄1 | P7: 備註
K8: =SUM(SUM(B8:F8)*360,SUM(G8:J8)*90) -> 0 | N8: =K8+L8-M8 -> 0 | R8: 金流 | X8: 應收帳款 | AB8: 今日未結帳款清單 | AC8: 今日銷帳清單
K9: =SUM(SUM(B9:F9)*360,SUM(G9:J9)*90) -> 0 | N9: =K9+L9-M9 -> 0 | R9: 營業總額 | T9: 運費 | U9: =SUMIF(表格1_334515253545556575859[欄1],"<>公關品",表格1_334515253545556575859[運費]) -> 0 | X9: 累積未結 | Y9: =INDEX('11'!Y12:Z13,1,1) -> 31984 | AB9: {=_xlfn.LET(_xlpm.unpaid,_xlfn.UNIQUE(_xlfn._xlws.FILTER(A8:A100,O8:O100="未結帳款","今日無欠款")),IF(_xlpm.unpaid="今日無欠款","今日無欠款",_xlpm.unpaid&"："&SUMIFS(N8:N100,A8:A100,_xlpm.unpaid,O8:O100,"未結帳款")))} -> 今日無欠款 | AC9: {=_xlfn.LET(_xlpm.paid,_xlfn.UNIQUE(_xlfn._xlws.FILTER(A8:A100,P8:P100="銷帳","今日無銷帳")),IF(_xlpm.paid="今日無銷帳","今日無銷帳",_xlpm.paid&"："&SUMIFS(N8:N100,A8:A100,_xlpm.paid,P8:P100,"銷帳")))} -> 今日無銷帳
K10: =SUM(SUM(B10:F10)*360,SUM(G10:J10)*90) -> 0 | N10: =K10+L10-M10 -> 0 | R10: =SUM(K8:K101)-V15 -> 0 | T10: 折讓 | U10: =SUM(M8:M101) -> 0 | X10: 今日未結 | Y10: =U15 -> 0
K11: =SUM(SUM(B11:F11)*360,SUM(G11:J11)*90) -> 0 | N11: =K11+L11-M11 -> 0 | R11: 營業額 | T11: 公關品 | U11: =SUMIF(P8:P100,"公關品",K8:K103) -> 0 | X11: 今日回款 | Y11: =V15 -> 0
K12: =SUM(SUM(B12:F12)*360,SUM(G12:J12)*90) -> 0 | N12: =K12+L12-M12 -> 0 | R12: =R10-U10-U11 -> 0 | T12: 應收 | V12: 實收 | X12: 剩餘未結 | Y12: =Y9+Y10-Y11 -> 31984
K13: =SUM(SUM(B13:F13)*360,SUM(G13:J13)*90) -> 0 | N13: =K13+L13-M13 -> 0 | T13: 匯款 | U13: =SUMIF(O8:O101,"匯款",N8:N101) -> 0
K14: =SUM(SUM(B14:F14)*360,SUM(G14:J14)*90) -> 0 | N14: =K14+L14-M14 -> 0 | T14: 現金 | U14: =SUMIF(O8:O102,"現金",N8:N102) -> 0
K15: =SUM(SUM(B15:F15)*360,SUM(G15:J15)*90) -> 0 | N15: =K15+L15-M15 -> 0 | T15: 未結帳款 | U15: =SUMIF(O8:O102,"未結帳款",N8:N103) -> 0 | V15: =SUMIF(P8:P100,"銷帳",N8:N100) -> 0
K16: =SUM(SUM(B16:F16)*360,SUM(G16:J16)*90) -> 0 | N16: =K16+L16-M16 -> 0 | T16: 銷帳 | X16: 物流
K17: =SUM(SUM(B17:F17)*360,SUM(G17:J17)*90) -> 0 | N17: =K17+L17-M17 -> 0 | R17: 商品銷售量 | X17: 運費實收 | Y17: =U9 -> 0
K18: =SUM(SUM(B18:F18)*360,SUM(G18:J18)*90) -> 0 | N18: =K18+L18-M18 -> 0 | T18: 販售量 | U18: 公關品 | V18: 總盒數 | X18: 運費實支
K19: =SUM(SUM(B19:F19)*360,SUM(G19:J19)*90) -> 0 | N19: =K19+L19-M19 -> 0 | R19: 禮盒 | S19: 綜合 | T19: =SUMIF(P8:P102,"<>公關品",B8:B100) -> 0 | U19: =SUMIF(P8:P102,"公關品",B8:B100) -> 0 | V19: =SUM(T19:T23,U19) -> 0 | X19: 公關運費 | Y19: =SUMIF(P8:P100,"公關品",L8:L100) -> 0
K20: =SUM(SUM(B20:F20)*360,SUM(G20:J20)*90) -> 0 | N20: =K20+L20-M20 -> 0 | S20: 原味 | T20: =SUMIF(P8:P102,"<>公關品",C8:C100) -> 0 | U20: =SUMIF(P8:P102,"公關品",C8:C100) -> 0 | V20: 總顆數 | X20: 物流包材 | Y20: =SUM(Z24:Z27) -> 0
K21: =SUM(SUM(B21:F21)*360,SUM(G21:J21)*90) -> 0 | N21: =K21+L21-M21 -> 0 | S21: 可可 | T21: =SUMIF(P8:P104,"<>公關品",D8:D102) -> 0 | U21: =SUMIF(P8:P102,"公關品",D8:D100) -> 0 | X21: 成本差額 | Y21: =Y17-Y18-Y20+Y19 -> 0
K22: =SUM(SUM(B22:F22)*360,SUM(G22:J22)*90) -> 0 | N22: =K22+L22-M22 -> 0 | S22: 伯爵 | T22: =SUMIF(P8:P102,"<>公關品",E8:E100) -> 0 | U22: =SUMIF(P8:P102,"公關品",E8:E100) -> 0 | X22: 物流包材
K23: =SUM(SUM(B23:F23)*360,SUM(G23:J23)*90) -> 0 | N23: =K23+L23-M23 -> 0 | S23: 抹茶 | T23: =SUMIF(P8:P102,"<>公關品",F8:F100) -> 0 | U23: =SUMIF(P8:P102,"公關品",F8:F100) -> 0 | X23: 種類 | Y23: 數量 | Z23: 總額
K24: =SUM(SUM(B24:F24)*360,SUM(G24:J24)*90) -> 0 | N24: =K24+L24-M24 -> 0 | R24: 單顆 | S24: 原味 | T24: =SUMIF(P9:P103,"<>公關品",G8:G100) -> 0 | U24: =SUMIF(P8:P102,"公關品",G8:G100) -> 0 | V24: =T19+(T20*4)+T24 -> 0 | X24: 2入紙箱
K25: =SUM(SUM(B25:F25)*360,SUM(G25:J25)*90) -> 0 | N25: =K25+L25-M25 -> 0 | S25: 可可 | T25: =SUMIF(P8:P102,"<>公關品",H8:H100) -> 0 | U25: =SUMIF(P8:P102,"公關品",I8:I100) -> 0 | V25: =T19+(T21*4)+T25 -> 0 | X25: 4入紙箱 | Z25: =Y25*5 -> 0
K26: =SUM(SUM(B26:F26)*360,SUM(G26:J26)*90) -> 0 | N26: =K26+L26-M26 -> 0 | S26: 伯爵 | T26: =SUMIF(P9:P103,"<>公關品",I8:I100) -> 0 | U26: =SUMIF(P8:P102,"公關品",I8:I100) -> 0 | V26: =T19+(T22*4)+T26 -> 0 | X26: 10入紙箱
K27: =SUM(SUM(B27:F27)*360,SUM(G27:J27)*90) -> 0 | N27: =K27+L27-M27 -> 0 | S27: 抹茶 | T27: =SUMIF(P8:P102,"<>公關品",J8:J100) -> 0 | U27: =SUMIF(P9:P103,"公關品",J8:J100) -> 0 | V27: =T19+(T23*4)+T27 -> 0 | X27: 膠帶
K28: =SUM(SUM(B28:F28)*360,SUM(G28:J28)*90) -> 0 | N28: =K28+L28-M28 -> 0
K29: =SUM(SUM(B29:F29)*360,SUM(G29:J29)*90) -> 0 | N29: =K29+L29-M29 -> 0
K30: =SUM(SUM(B30:F30)*360,SUM(G30:J30)*90) -> 0 | N30: =K30+L30-M30 -> 0 | R30: 產能及庫存 | AB30: 今日公關品總結
K31: =SUM(SUM(B31:F31)*360,SUM(G31:J31)*90) -> 0 | N31: =K31+L31-M31 -> 0 | AB31: 總禮盒數 | AC31: =SUM(U19:U23) -> 0
K32: =SUM(SUM(B32:F32)*360,SUM(G32:J32)*90) -> 0 | N32: =K32+L32-M32 -> 0 | R32: 品項 | S32: 原庫存 | T32: 預計產量 | U32: 實際產量 | V32: 耗損 | W32: 實際銷售量 | Y32: 今日庫存 | Z32: 總損耗率 | AB32: 總顆數 | AC32: =SUM(AC33:AC36) -> 0
K33: =SUM(SUM(B33:F33)*360,SUM(G33:J33)*90) -> 0 | N33: =K33+L33-M33 -> 0 | R33: 原味 | S33: ='11'!Y33 -> 0 | V33: =SUMIF(R40:R55,"原味",S40:S55) -> 0 | W33: =V24+U24+U19+U20*4 -> 0 | Y33: =S33+U33-V33-W33 -> 0 | Z33: =IFERROR((V33/(U33+S33))," ") | AB33: 原味 | AC33: =U24+U19+U20*4 -> 0
K34: =SUM(SUM(B34:F34)*360,SUM(G34:J34)*90) -> 0 | N34: =K34+L34-M34 -> 0 | R34: 可可 | S34: ='11'!Y34 -> 0 | V34: =SUMIF(R41:R55,"可可",S41:S55) -> 0 | W34: =V25+U25+U19+U21*4 -> 0 | Y34: =S34+U34-V34-W34 -> 0 | Z34: =IFERROR((V34/(U34+S34))," ") | AB34: 可可 | AC34: =U25+U19+U21*4 -> 0
K35: =SUM(SUM(B35:F35)*360,SUM(G35:J35)*90) -> 0 | N35: =K35+L35-M35 -> 0 | R35: 伯爵 | S35: ='11'!Y35 -> 0 | V35: =SUMIF(R41:R55,"伯爵",S41:S55) -> 0 | W35: =V26+U26+U19+U22*4 -> 0 | Y35: =S35+U35-V35-W35 -> 0 | Z35: =IFERROR((V35/(U35+S35))," ") | AB35: 伯爵 | AC35: =U26+U19+U22*4 -> 0
K36: =SUM(SUM(B36:F36)*360,SUM(G36:J36)*90) -> 0 | N36: =K36+L36-M36 -> 0 | R36: 抹茶 | S36: ='11'!Y36 -> 0 | V36: =SUMIF(R41:R55,"抹茶",S41:S55) -> 0 | W36: =V27+U27+U19+U23*4 -> 0 | Y36: =S36+U36-V36-W36 -> 0 | Z36: =IFERROR((V36/(U36+S36))," ") | AB36: 抹茶 | AC36: =U27+U19+U23*4 -> 0
K37: =SUM(SUM(B37:F37)*360,SUM(G37:J37)*90) -> 0 | N37: =K37+L37-M37 -> 0
K38: =SUM(SUM(B38:F38)*360,SUM(G38:J38)*90) -> 0 | N38: =K38+L38-M38 -> 0 | R38: 損耗原因
K39: =SUM(SUM(B39:F39)*360,SUM(G39:J39)*90) -> 0 | N39: =K39+L39-M39 -> 0
K40: =SUM(SUM(B40:F40)*360,SUM(G40:J40)*90) -> 0 | N40: =K40+L40-M40 -> 0 | R40: 品項 | S40: 數量 | T40: 類別 | U40: 原因
K41: =SUM(SUM(B41:F41)*360,SUM(G41:J41)*90) -> 0 | N41: =K41+L41-M41 -> 0
K42: =SUM(SUM(B42:F42)*360,SUM(G42:J42)*90) -> 0 | N42: =K42+L42-M42 -> 0
K43: =SUM(SUM(B43:F43)*360,SUM(G43:J43)*90) -> 0 | N43: =K43+L43-M43 -> 0
K44: =SUM(SUM(B44:F44)*360,SUM(G44:J44)*90) -> 0 | N44: =K44+L44-M44 -> 0
K45: =SUM(SUM(B45:F45)*360,SUM(G45:J45)*90) -> 0 | N45: =K45+L45-M45 -> 0
K46: =SUM(SUM(B46:F46)*360,SUM(G46:J46)*90) -> 0 | N46: =K46+L46-M46 -> 0
K47: =SUM(SUM(B47:F47)*360,SUM(G47:J47)*90) -> 0 | N47: =K47+L47-M47 -> 0
K48: =SUM(SUM(B48:F48)*360,SUM(G48:J48)*90) -> 0 | N48: =K48+L48-M48 -> 0
K49: =SUM(SUM(B49:F49)*360,SUM(G49:J49)*90) -> 0 | N49: =K49+L49-M49 -> 0
K50: =SUM(SUM(B50:F50)*360,SUM(G50:J50)*90) -> 0 | N50: =K50+L50-M50 -> 0
K51: =SUM(SUM(B51:F51)*360,SUM(G51:J51)*90) -> 0 | N51: =K51+L51-M51 -> 0
K52: =SUM(SUM(B52:F52)*360,SUM(G52:J52)*90) -> 0 | N52: =K52+L52-M52 -> 0
... K56: =SUM(SUM(B56:F56)*360,SUM(G56:J56)*90) -> 0 | N56: =K56+L56-M56 -> 0
K57: =SUM(SUM(B57:F57)*360,SUM(G57:J57)*90) -> 0 | N57: =K57+L57-M57 -> 0 | R57: 備註
K58: =SUM(SUM(B58:F58)*360,SUM(G58:J58)*90) -> 0 | N58: =K58+L58-M58 -> 0
K59: =SUM(SUM(B59:F59)*360,SUM(G59:J59)*90) -> 0 | N59: =K59+L59-M59 -> 0
K60: =SUM(SUM(B60:F60)*360,SUM(G60:J60)*90) -> 0 | N60: =K60+L60-M60 -> 0
K61: =SUM(SUM(B61:F61)*360,SUM(G61:J61)*90) -> 0 | N61: =K61+L61-M61 -> 0
K62: =SUM(SUM(B62:F62)*360,SUM(G62:J62)*90) -> 0 | N62: =K62+L62-M62 -> 0
K63: =SUM(SUM(B63:F63)*360,SUM(G63:J63)*90) -> 0 | N63: =K63+L63-M63 -> 0
K64: =SUM(SUM(B64:F64)*360,SUM(G64:J64)*90) -> 0 | N64: =K64+L64-M64 -> 0
K65: =SUM(SUM(B65:F65)*360,SUM(G65:J65)*90) -> 0 | N65: =K65+L65-M65 -> 0
K66: =SUM(SUM(B66:F66)*360,SUM(G66:J66)*90) -> 0 | N66: =K66+L66-M66 -> 0
K67: =SUM(SUM(B67:F67)*360,SUM(G67:J67)*90) -> 0 | N67: =K67+L67-M67 -> 0
K68: =SUM(SUM(B68:F68)*360,SUM(G68:J68)*90) -> 0 | N68: =K68+L68-M68 -> 0
K69: =SUM(SUM(B69:F69)*360,SUM(G69:J69)*90) -> 0 | N69: =K69+L69-M69 -> 0
... K101: =SUM(SUM(B101:F101)*360,SUM(G101:J101)*90) -> 0 | N101: =K101+L101-M101 -> 0

Sheet 13
A1: 日報表
A5: 銷售明細 | R5: 總結
A6: 類別 | B6: 禮盒 | G6: 單顆 | K6: 金額
A7: 購買人 | B7: 綜合 | C7: 原味 | D7: 可可 | E7: 伯爵 | F7: 抹茶 | G7: 原味. | H7: 可可. | I7: 伯爵. | J7: 抹茶. | K7: 金額 | L7: 運費 | M7: 折讓金額 | N7: 實收金額 | O7: 欄1 | P7: 備註
K8: =SUM(SUM(B8:F8)*360,SUM(G8:J8)*90) -> 0 | N8: =K8+L8-M8 -> 0 | R8: 金流 | X8: 應收帳款 | AB8: 今日未結帳款清單 | AC8: 今日銷帳清單
K9: =SUM(SUM(B9:F9)*360,SUM(G9:J9)*90) -> 0 | N9: =K9+L9-M9 -> 0 | R9: 營業總額 | T9: 運費 | U9: =SUMIF(表格1_33451525354555657585960[欄1],"<>公關品",表格1_33451525354555657585960[運費]) -> 0 | X9: 累積未結 | Y9: =INDEX('12'!Y12:Z13,1,1) -> 31984 | AB9: {=_xlfn.LET(_xlpm.unpaid,_xlfn.UNIQUE(_xlfn._xlws.FILTER(A8:A100,O8:O100="未結帳款","今日無欠款")),IF(_xlpm.unpaid="今日無欠款","今日無欠款",_xlpm.unpaid&"："&SUMIFS(N8:N100,A8:A100,_xlpm.unpaid,O8:O100,"未結帳款")))} -> 今日無欠款 | AC9: {=_xlfn.LET(_xlpm.paid,_xlfn.UNIQUE(_xlfn._xlws.FILTER(A8:A100,P8:P100="銷帳","今日無銷帳")),IF(_xlpm.paid="今日無銷帳","今日無銷帳",_xlpm.paid&"："&SUMIFS(N8:N100,A8:A100,_xlpm.paid,P8:P100,"銷帳")))} -> 今日無銷帳
K10: =SUM(SUM(B10:F10)*360,SUM(G10:J10)*90) -> 0 | N10: =K10+L10-M10 -> 0 | R10: =SUM(K8:K101)-V15 -> 0 | T10: 折讓 | U10: =SUM(M8:M101) -> 0 | X10: 今日未結 | Y10: =U15 -> 0
K11: =SUM(SUM(B11:F11)*360,SUM(G11:J11)*90) -> 0 | N11: =K11+L11-M11 -> 0 | R11: 營業額 | T11: 公關品 | U11: =SUMIF(P8:P100,"公關品",K8:K103) -> 0 | X11: 今日回款 | Y11: =V15 -> 0
K12: =SUM(SUM(B12:F12)*360,SUM(G12:J12)*90) -> 0 | N12: =K12+L12-M12 -> 0 | R12: =R10-U10-U11 -> 0 | T12: 應收 | V12: 實收 | X12: 剩餘未結 | Y12: =Y9+Y10-Y11 -> 31984
K13: =SUM(SUM(B13:F13)*360,SUM(G13:J13)*90) -> 0 | N13: =K13+L13-M13 -> 0 | T13: 匯款 | U13: =SUMIF(O8:O101,"匯款",N8:N101) -> 0
K14: =SUM(SUM(B14:F14)*360,SUM(G14:J14)*90) -> 0 | N14: =K14+L14-M14 -> 0 | T14: 現金 | U14: =SUMIF(O8:O102,"現金",N8:N102) -> 0
K15: =SUM(SUM(B15:F15)*360,SUM(G15:J15)*90) -> 0 | N15: =K15+L15-M15 -> 0 | T15: 未結帳款 | U15: =SUMIF(O8:O102,"未結帳款",N8:N103) -> 0 | V15: =SUMIF(P8:P100,"銷帳",N8:N100) -> 0
K16: =SUM(SUM(B16:F16)*360,SUM(G16:J16)*90) -> 0 | N16: =K16+L16-M16 -> 0 | T16: 銷帳 | X16: 物流
K17: =SUM(SUM(B17:F17)*360,SUM(G17:J17)*90) -> 0 | N17: =K17+L17-M17 -> 0 | R17: 商品銷售量 | X17: 運費實收 | Y17: =U9 -> 0
K18: =SUM(SUM(B18:F18)*360,SUM(G18:J18)*90) -> 0 | N18: =K18+L18-M18 -> 0 | T18: 販售量 | U18: 公關品 | V18: 總盒數 | X18: 運費實支
K19: =SUM(SUM(B19:F19)*360,SUM(G19:J19)*90) -> 0 | N19: =K19+L19-M19 -> 0 | R19: 禮盒 | S19: 綜合 | T19: =SUMIF(P8:P102,"<>公關品",B8:B100) -> 0 | U19: =SUMIF(P8:P102,"公關品",B8:B100) -> 0 | V19: =SUM(T19:T23,U19) -> 0 | X19: 公關運費 | Y19: =SUMIF(P8:P100,"公關品",L8:L100) -> 0
K20: =SUM(SUM(B20:F20)*360,SUM(G20:J20)*90) -> 0 | N20: =K20+L20-M20 -> 0 | S20: 原味 | T20: =SUMIF(P8:P102,"<>公關品",C8:C100) -> 0 | U20: =SUMIF(P8:P102,"公關品",C8:C100) -> 0 | V20: 總顆數 | X20: 物流包材 | Y20: =SUM(Z24:Z27) -> 0
K21: =SUM(SUM(B21:F21)*360,SUM(G21:J21)*90) -> 0 | N21: =K21+L21-M21 -> 0 | S21: 可可 | T21: =SUMIF(P8:P104,"<>公關品",D8:D102) -> 0 | U21: =SUMIF(P8:P102,"公關品",D8:D100) -> 0 | X21: 成本差額 | Y21: =Y17-Y18-Y20+Y19 -> 0
K22: =SUM(SUM(B22:F22)*360,SUM(G22:J22)*90) -> 0 | N22: =K22+L22-M22 -> 0 | S22: 伯爵 | T22: =SUMIF(P8:P102,"<>公關品",E8:E100) -> 0 | U22: =SUMIF(P8:P102,"公關品",E8:E100) -> 0 | X22: 物流包材
K23: =SUM(SUM(B23:F23)*360,SUM(G23:J23)*90) -> 0 | N23: =K23+L23-M23 -> 0 | S23: 抹茶 | T23: =SUMIF(P8:P102,"<>公關品",F8:F100) -> 0 | U23: =SUMIF(P8:P102,"公關品",F8:F100) -> 0 | X23: 種類 | Y23: 數量 | Z23: 總額
K24: =SUM(SUM(B24:F24)*360,SUM(G24:J24)*90) -> 0 | N24: =K24+L24-M24 -> 0 | R24: 單顆 | S24: 原味 | T24: =SUMIF(P9:P103,"<>公關品",G8:G100) -> 0 | U24: =SUMIF(P8:P102,"公關品",G8:G100) -> 0 | V24: =T19+(T20*4)+T24 -> 0 | X24: 2入紙箱
K25: =SUM(SUM(B25:F25)*360,SUM(G25:J25)*90) -> 0 | N25: =K25+L25-M25 -> 0 | S25: 可可 | T25: =SUMIF(P8:P102,"<>公關品",H8:H100) -> 0 | U25: =SUMIF(P8:P102,"公關品",I8:I100) -> 0 | V25: =T19+(T21*4)+T25 -> 0 | X25: 4入紙箱 | Z25: =Y25*5 -> 0
K26: =SUM(SUM(B26:F26)*360,SUM(G26:J26)*90) -> 0 | N26: =K26+L26-M26 -> 0 | S26: 伯爵 | T26: =SUMIF(P9:P103,"<>公關品",I8:I100) -> 0 | U26: =SUMIF(P8:P102,"公關品",I8:I100) -> 0 | V26: =T19+(T22*4)+T26 -> 0 | X26: 10入紙箱
K27: =SUM(SUM(B27:F27)*360,SUM(G27:J27)*90) -> 0 | N27: =K27+L27-M27 -> 0 | S27: 抹茶 | T27: =SUMIF(P8:P102,"<>公關品",J8:J100) -> 0 | U27: =SUMIF(P9:P103,"公關品",J8:J100) -> 0 | V27: =T19+(T23*4)+T27 -> 0 | X27: 膠帶
K28: =SUM(SUM(B28:F28)*360,SUM(G28:J28)*90) -> 0 | N28: =K28+L28-M28 -> 0
K29: =SUM(SUM(B29:F29)*360,SUM(G29:J29)*90) -> 0 | N29: =K29+L29-M29 -> 0
K30: =SUM(SUM(B30:F30)*360,SUM(G30:J30)*90) -> 0 | N30: =K30+L30-M30 -> 0 | R30: 產能及庫存 | AB30: 今日公關品總結
K31: =SUM(SUM(B31:F31)*360,SUM(G31:J31)*90) -> 0 | N31: =K31+L31-M31 -> 0 | AB31: 總禮盒數 | AC31: =SUM(U19:U23) -> 0
K32: =SUM(SUM(B32:F32)*360,SUM(G32:J32)*90) -> 0 | N32: =K32+L32-M32 -> 0 | R32: 品項 | S32: 原庫存 | T32: 預計產量 | U32: 實際產量 | V32: 耗損 | W32: 實際銷售量 | Y32: 今日庫存 | Z32: 總損耗率 | AB32: 總顆數 | AC32: =SUM(AC33:AC36) -> 0
K33: =SUM(SUM(B33:F33)*360,SUM(G33:J33)*90) -> 0 | N33: =K33+L33-M33 -> 0 | R33: 原味 | S33: ='12'!Y33 -> 0 | V33: =SUMIF(R40:R55,"原味",S40:S55) -> 0 | W33: =V24+U24+U19+U20*4 -> 0 | Y33: =S33+U33-V33-W33 -> 0 | Z33: =IFERROR((V33/(U33+S33))," ") | AB33: 原味 | AC33: =U24+U19+U20*4 -> 0
K34: =SUM(SUM(B34:F34)*360,SUM(G34:J34)*90) -> 0 | N34: =K34+L34-M34 -> 0 | R34: 可可 | S34: ='12'!Y34 -> 0 | V34: =SUMIF(R41:R55,"可可",S41:S55) -> 0 | W34: =V25+U25+U19+U21*4 -> 0 | Y34: =S34+U34-V34-W34 -> 0 | Z34: =IFERROR((V34/(U34+S34))," ") | AB34: 可可 | AC34: =U25+U19+U21*4 -> 0
K35: =SUM(SUM(B35:F35)*360,SUM(G35:J35)*90) -> 0 | N35: =K35+L35-M35 -> 0 | R35: 伯爵 | S35: ='12'!Y35 -> 0 | V35: =SUMIF(R41:R55,"伯爵",S41:S55) -> 0 | W35: =V26+U26+U19+U22*4 -> 0 | Y35: =S35+U35-V35-W35 -> 0 | Z35: =IFERROR((V35/(U35+S35))," ") | AB35: 伯爵 | AC35: =U26+U19+U22*4 -> 0
K36: =SUM(SUM(B36:F36)*360,SUM(G36:J36)*90) -> 0 | N36: =K36+L36-M36 -> 0 | R36: 抹茶 | S36: ='12'!Y36 -> 0 | V36: =SUMIF(R41:R55,"抹茶",S41:S55) -> 0 | W36: =V27+U27+U19+U23*4 -> 0 | Y36: =S36+U36-V36-W36 -> 0 | Z36: =IFERROR((V36/(U36+S36))," ") | AB36: 抹茶 | AC36: =U27+U19+U23*4 -> 0
K37: =SUM(SUM(B37:F37)*360,SUM(G37:J37)*90) -> 0 | N37: =K37+L37-M37 -> 0
K38: =SUM(SUM(B38:F38)*360,SUM(G38:J38)*90) -> 0 | N38: =K38+L38-M38 -> 0 | R38: 損耗原因
K39: =SUM(SUM(B39:F39)*360,SUM(G39:J39)*90) -> 0 | N39: =K39+L39-M39 -> 0
K40: =SUM(SUM(B40:F40)*360,SUM(G40:J40)*90) -> 0 | N40: =K40+L40-M40 -> 0 | R40: 品項 | S40: 數量 | T40: 類別 | U40: 原因
K41: =SUM(SUM(B41:F41)*360,SUM(G41:J41)*90) -> 0 | N41: =K41+L41-M41 -> 0
K42: =SUM(SUM(B42:F42)*360,SUM(G42:J42)*90) -> 0 | N42: =K42+L42-M42 -> 0
K43: =SUM(SUM(B43:F43)*360,SUM(G43:J43)*90) -> 0 | N43: =K43+L43-M43 -> 0
K44: =SUM(SUM(B44:F44)*360,SUM(G44:J44)*90) -> 0 | N44: =K44+L44-M44 -> 0
K45: =SUM(SUM(B45:F45)*360,SUM(G45:J45)*90) -> 0 | N45: =K45+L45-M45 -> 0
K46: =SUM(SUM(B46:F46)*360,SUM(G46:J46)*90) -> 0 | N46: =K46+L46-M46 -> 0
K47: =SUM(SUM(B47:F47)*360,SUM(G47:J47)*90) -> 0 | N47: =K47+L47-M47 -> 0
K48: =SUM(SUM(B48:F48)*360,SUM(G48:J48)*90) -> 0 | N48: =K48+L48-M48 -> 0
K49: =SUM(SUM(B49:F49)*360,SUM(G49:J49)*90) -> 0 | N49: =K49+L49-M49 -> 0
K50: =SUM(SUM(B50:F50)*360,SUM(G50:J50)*90) -> 0 | N50: =K50+L50-M50 -> 0
K51: =SUM(SUM(B51:F51)*360,SUM(G51:J51)*90) -> 0 | N51: =K51+L51-M51 -> 0
K52: =SUM(SUM(B52:F52)*360,SUM(G52:J52)*90) -> 0 | N52: =K52+L52-M52 -> 0
... K56: =SUM(SUM(B56:F56)*360,SUM(G56:J56)*90) -> 0 | N56: =K56+L56-M56 -> 0
K57: =SUM(SUM(B57:F57)*360,SUM(G57:J57)*90) -> 0 | N57: =K57+L57-M57 -> 0 | R57: 備註
K58: =SUM(SUM(B58:F58)*360,SUM(G58:J58)*90) -> 0 | N58: =K58+L58-M58 -> 0
K59: =SUM(SUM(B59:F59)*360,SUM(G59:J59)*90) -> 0 | N59: =K59+L59-M59 -> 0
K60: =SUM(SUM(B60:F60)*360,SUM(G60:J60)*90) -> 0 | N60: =K60+L60-M60 -> 0
K61: =SUM(SUM(B61:F61)*360,SUM(G61:J61)*90) -> 0 | N61: =K61+L61-M61 -> 0
K62: =SUM(SUM(B62:F62)*360,SUM(G62:J62)*90) -> 0 | N62: =K62+L62-M62 -> 0
K63: =SUM(SUM(B63:F63)*360,SUM(G63:J63)*90) -> 0 | N63: =K63+L63-M63 -> 0
K64: =SUM(SUM(B64:F64)*360,SUM(G64:J64)*90) -> 0 | N64: =K64+L64-M64 -> 0
K65: =SUM(SUM(B65:F65)*360,SUM(G65:J65)*90) -> 0 | N65: =K65+L65-M65 -> 0
K66: =SUM(SUM(B66:F66)*360,SUM(G66:J66)*90) -> 0 | N66: =K66+L66-M66 -> 0
K67: =SUM(SUM(B67:F67)*360,SUM(G67:J67)*90) -> 0 | N67: =K67+L67-M67 -> 0
K68: =SUM(SUM(B68:F68)*360,SUM(G68:J68)*90) -> 0 | N68: =K68+L68-M68 -> 0
K69: =SUM(SUM(B69:F69)*360,SUM(G69:J69)*90) -> 0 | N69: =K69+L69-M69 -> 0
... K101: =SUM(SUM(B101:F101)*360,SUM(G101:J101)*90) -> 0 | N101: =K101+L101-M101 -> 0

Sheet 14
A1: 日報表
A5: 銷售明細 | R5: 總結
A6: 類別 | B6: 禮盒 | G6: 單顆 | K6: 金額
A7: 購買人 | B7: 綜合 | C7: 原味 | D7: 可可 | E7: 伯爵 | F7: 抹茶 | G7: 原味. | H7: 可可. | I7: 伯爵. | J7: 抹茶. | K7: 金額 | L7: 運費 | M7: 折讓金額 | N7: 實收金額 | O7: 欄1 | P7: 備註
K8: =SUM(SUM(B8:F8)*360,SUM(G8:J8)*90) -> 0 | N8: =K8+L8-M8 -> 0 | R8: 金流 | X8: 應收帳款 | AB8: 今日未結帳款清單 | AC8: 今日銷帳清單
K9: =SUM(SUM(B9:F9)*360,SUM(G9:J9)*90) -> 0 | N9: =K9+L9-M9 -> 0 | R9: 營業總額 | T9: 運費 | U9: =SUMIF(表格1_3345152535455565758596061[欄1],"<>公關品",表格1_3345152535455565758596061[運費]) -> 0 | X9: 累積未結 | Y9: =INDEX('13'!Y12:Z13,1,1) -> 31984 | AB9: {=_xlfn.LET(_xlpm.unpaid,_xlfn.UNIQUE(_xlfn._xlws.FILTER(A8:A100,O8:O100="未結帳款","今日無欠款")),IF(_xlpm.unpaid="今日無欠款","今日無欠款",_xlpm.unpaid&"："&SUMIFS(N8:N100,A8:A100,_xlpm.unpaid,O8:O100,"未結帳款")))} -> 今日無欠款 | AC9: {=_xlfn.LET(_xlpm.paid,_xlfn.UNIQUE(_xlfn._xlws.FILTER(A8:A100,P8:P100="銷帳","今日無銷帳")),IF(_xlpm.paid="今日無銷帳","今日無銷帳",_xlpm.paid&"："&SUMIFS(N8:N100,A8:A100,_xlpm.paid,P8:P100,"銷帳")))} -> 今日無銷帳
K10: =SUM(SUM(B10:F10)*360,SUM(G10:J10)*90) -> 0 | N10: =K10+L10-M10 -> 0 | R10: =SUM(K8:K101)-V15 -> 0 | T10: 折讓 | U10: =SUM(M8:M101) -> 0 | X10: 今日未結 | Y10: =U15 -> 0
K11: =SUM(SUM(B11:F11)*360,SUM(G11:J11)*90) -> 0 | N11: =K11+L11-M11 -> 0 | R11: 營業額 | T11: 公關品 | U11: =SUMIF(P8:P100,"公關品",K8:K103) -> 0 | X11: 今日回款 | Y11: =V15 -> 0
K12: =SUM(SUM(B12:F12)*360,SUM(G12:J12)*90) -> 0 | N12: =K12+L12-M12 -> 0 | R12: =R10-U10-U11 -> 0 | T12: 應收 | V12: 實收 | X12: 剩餘未結 | Y12: =Y9+Y10-Y11 -> 31984
K13: =SUM(SUM(B13:F13)*360,SUM(G13:J13)*90) -> 0 | N13: =K13+L13-M13 -> 0 | T13: 匯款 | U13: =SUMIF(O8:O101,"匯款",N8:N101) -> 0
K14: =SUM(SUM(B14:F14)*360,SUM(G14:J14)*90) -> 0 | N14: =K14+L14-M14 -> 0 | T14: 現金 | U14: =SUMIF(O8:O102,"現金",N8:N102) -> 0
K15: =SUM(SUM(B15:F15)*360,SUM(G15:J15)*90) -> 0 | N15: =K15+L15-M15 -> 0 | T15: 未結帳款 | U15: =SUMIF(O8:O102,"未結帳款",N8:N103) -> 0 | V15: =SUMIF(P8:P100,"銷帳",N8:N100) -> 0
K16: =SUM(SUM(B16:F16)*360,SUM(G16:J16)*90) -> 0 | N16: =K16+L16-M16 -> 0 | T16: 銷帳 | X16: 物流
K17: =SUM(SUM(B17:F17)*360,SUM(G17:J17)*90) -> 0 | N17: =K17+L17-M17 -> 0 | R17: 商品銷售量 | X17: 運費實收 | Y17: =U9 -> 0
K18: =SUM(SUM(B18:F18)*360,SUM(G18:J18)*90) -> 0 | N18: =K18+L18-M18 -> 0 | T18: 販售量 | U18: 公關品 | V18: 總盒數 | X18: 運費實支
K19: =SUM(SUM(B19:F19)*360,SUM(G19:J19)*90) -> 0 | N19: =K19+L19-M19 -> 0 | R19: 禮盒 | S19: 綜合 | T19: =SUMIF(P8:P102,"<>公關品",B8:B100) -> 0 | U19: =SUMIF(P8:P102,"公關品",B8:B100) -> 0 | V19: =SUM(T19:T23,U19) -> 0 | X19: 公關運費 | Y19: =SUMIF(P8:P100,"公關品",L8:L100) -> 0
K20: =SUM(SUM(B20:F20)*360,SUM(G20:J20)*90) -> 0 | N20: =K20+L20-M20 -> 0 | S20: 原味 | T20: =SUMIF(P8:P102,"<>公關品",C8:C100) -> 0 | U20: =SUMIF(P8:P102,"公關品",C8:C100) -> 0 | V20: 總顆數 | X20: 物流包材 | Y20: =SUM(Z24:Z27) -> 0
K21: =SUM(SUM(B21:F21)*360,SUM(G21:J21)*90) -> 0 | N21: =K21+L21-M21 -> 0 | S21: 可可 | T21: =SUMIF(P8:P104,"<>公關品",D8:D102) -> 0 | U21: =SUMIF(P8:P102,"公關品",D8:D100) -> 0 | X21: 成本差額 | Y21: =Y17-Y18-Y20+Y19 -> 0
K22: =SUM(SUM(B22:F22)*360,SUM(G22:J22)*90) -> 0 | N22: =K22+L22-M22 -> 0 | S22: 伯爵 | T22: =SUMIF(P8:P102,"<>公關品",E8:E100) -> 0 | U22: =SUMIF(P8:P102,"公關品",E8:E100) -> 0 | X22: 物流包材
K23: =SUM(SUM(B23:F23)*360,SUM(G23:J23)*90) -> 0 | N23: =K23+L23-M23 -> 0 | S23: 抹茶 | T23: =SUMIF(P8:P102,"<>公關品",F8:F100) -> 0 | U23: =SUMIF(P8:P102,"公關品",F8:F100) -> 0 | X23: 種類 | Y23: 數量 | Z23: 總額
K24: =SUM(SUM(B24:F24)*360,SUM(G24:J24)*90) -> 0 | N24: =K24+L24-M24 -> 0 | R24: 單顆 | S24: 原味 | T24: =SUMIF(P9:P103,"<>公關品",G8:G100) -> 0 | U24: =SUMIF(P8:P102,"公關品",G8:G100) -> 0 | V24: =T19+(T20*4)+T24 -> 0 | X24: 2入紙箱
K25: =SUM(SUM(B25:F25)*360,SUM(G25:J25)*90) -> 0 | N25: =K25+L25-M25 -> 0 | S25: 可可 | T25: =SUMIF(P8:P102,"<>公關品",H8:H100) -> 0 | U25: =SUMIF(P8:P102,"公關品",I8:I100) -> 0 | V25: =T19+(T21*4)+T25 -> 0 | X25: 4入紙箱 | Z25: =Y25*5 -> 0
K26: =SUM(SUM(B26:F26)*360,SUM(G26:J26)*90) -> 0 | N26: =K26+L26-M26 -> 0 | S26: 伯爵 | T26: =SUMIF(P9:P103,"<>公關品",I8:I100) -> 0 | U26: =SUMIF(P8:P102,"公關品",I8:I100) -> 0 | V26: =T19+(T22*4)+T26 -> 0 | X26: 10入紙箱
K27: =SUM(SUM(B27:F27)*360,SUM(G27:J27)*90) -> 0 | N27: =K27+L27-M27 -> 0 | S27: 抹茶 | T27: =SUMIF(P8:P102,"<>公關品",J8:J100) -> 0 | U27: =SUMIF(P9:P103,"公關品",J8:J100) -> 0 | V27: =T19+(T23*4)+T27 -> 0 | X27: 膠帶
K28: =SUM(SUM(B28:F28)*360,SUM(G28:J28)*90) -> 0 | N28: =K28+L28-M28 -> 0
K29: =SUM(SUM(B29:F29)*360,SUM(G29:J29)*90) -> 0 | N29: =K29+L29-M29 -> 0
K30: =SUM(SUM(B30:F30)*360,SUM(G30:J30)*90) -> 0 | N30: =K30+L30-M30 -> 0 | R30: 產能及庫存 | AB30: 今日公關品總結
K31: =SUM(SUM(B31:F31)*360,SUM(G31:J31)*90) -> 0 | N31: =K31+L31-M31 -> 0 | AB31: 總禮盒數 | AC31: =SUM(U19:U23) -> 0
K32: =SUM(SUM(B32:F32)*360,SUM(G32:J32)*90) -> 0 | N32: =K32+L32-M32 -> 0 | R32: 品項 | S32: 原庫存 | T32: 預計產量 | U32: 實際產量 | V32: 耗損 | W32: 實際銷售量 | Y32: 今日庫存 | Z32: 總損耗率 | AB32: 總顆數 | AC32: =SUM(AC33:AC36) -> 0
K33: =SUM(SUM(B33:F33)*360,SUM(G33:J33)*90) -> 0 | N33: =K33+L33-M33 -> 0 | R33: 原味 | S33: ='13'!Y33 -> 0 | V33: =SUMIF(R40:R55,"原味",S40:S55) -> 0 | W33: =V24+U24+U19+U20*4 -> 0 | Y33: =S33+U33-V33-W33 -> 0 | Z33: =IFERROR((V33/(U33+S33))," ") | AB33: 原味 | AC33: =U24+U19+U20*4 -> 0
K34: =SUM(SUM(B34:F34)*360,SUM(G34:J34)*90) -> 0 | N34: =K34+L34-M34 -> 0 | R34: 可可 | S34: ='13'!Y34 -> 0 | V34: =SUMIF(R41:R55,"可可",S41:S55) -> 0 | W34: =V25+U25+U19+U21*4 -> 0 | Y34: =S34+U34-V34-W34 -> 0 | Z34: =IFERROR((V34/(U34+S34))," ") | AB34: 可可 | AC34: =U25+U19+U21*4 -> 0
K35: =SUM(SUM(B35:F35)*360,SUM(G35:J35)*90) -> 0 | N35: =K35+L35-M35 -> 0 | R35: 伯爵 | S35: ='13'!Y35 -> 0 | V35: =SUMIF(R41:R55,"伯爵",S41:S55) -> 0 | W35: =V26+U26+U19+U22*4 -> 0 | Y35: =S35+U35-V35-W35 -> 0 | Z35: =IFERROR((V35/(U35+S35))," ") | AB35: 伯爵 | AC35: =U26+U19+U22*4 -> 0
K36: =SUM(SUM(B36:F36)*360,SUM(G36:J36)*90) -> 0 | N36: =K36+L36-M36 -> 0 | R36: 抹茶 | S36: ='13'!Y36 -> 0 | V36: =SUMIF(R41:R55,"抹茶",S41:S55) -> 0 | W36: =V27+U27+U19+U23*4 -> 0 | Y36: =S36+U36-V36-W36 -> 0 | Z36: =IFERROR((V36/(U36+S36))," ") | AB36: 抹茶 | AC36: =U27+U19+U23*4 -> 0
K37: =SUM(SUM(B37:F37)*360,SUM(G37:J37)*90) -> 0 | N37: =K37+L37-M37 -> 0
K38: =SUM(SUM(B38:F38)*360,SUM(G38:J38)*90) -> 0 | N38: =K38+L38-M38 -> 0 | R38: 損耗原因
K39: =SUM(SUM(B39:F39)*360,SUM(G39:J39)*90) -> 0 | N39: =K39+L39-M39 -> 0
K40: =SUM(SUM(B40:F40)*360,SUM(G40:J40)*90) -> 0 | N40: =K40+L40-M40 -> 0 | R40: 品項 | S40: 數量 | T40: 類別 | U40: 原因
K41: =SUM(SUM(B41:F41)*360,SUM(G41:J41)*90) -> 0 | N41: =K41+L41-M41 -> 0
K42: =SUM(SUM(B42:F42)*360,SUM(G42:J42)*90) -> 0 | N42: =K42+L42-M42 -> 0
K43: =SUM(SUM(B43:F43)*360,SUM(G43:J43)*90) -> 0 | N43: =K43+L43-M43 -> 0
K44: =SUM(SUM(B44:F44)*360,SUM(G44:J44)*90) -> 0 | N44: =K44+L44-M44 -> 0
K45: =SUM(SUM(B45:F45)*360,SUM(G45:J45)*90) -> 0 | N45: =K45+L45-M45 -> 0
K46: =SUM(SUM(B46:F46)*360,SUM(G46:J46)*90) -> 0 | N46: =K46+L46-M46 -> 0
K47: =SUM(SUM(B47:F47)*360,SUM(G47:J47)*90) -> 0 | N47: =K47+L47-M47 -> 0
K48: =SUM(SUM(B48:F48)*360,SUM(G48:J48)*90) -> 0 | N48: =K48+L48-M48 -> 0
K49: =SUM(SUM(B49:F49)*360,SUM(G49:J49)*90) -> 0 | N49: =K49+L49-M49 -> 0
K50: =SUM(SUM(B50:F50)*360,SUM(G50:J50)*90) -> 0 | N50: =K50+L50-M50 -> 0
K51: =SUM(SUM(B51:F51)*360,SUM(G51:J51)*90) -> 0 | N51: =K51+L51-M51 -> 0
K52: =SUM(SUM(B52:F52)*360,SUM(G52:J52)*90) -> 0 | N52: =K52+L52-M52 -> 0
... K56: =SUM(SUM(B56:F56)*360,SUM(G56:J56)*90) -> 0 | N56: =K56+L56-M56 -> 0
K57: =SUM(SUM(B57:F57)*360,SUM(G57:J57)*90) -> 0 | N57: =K57+L57-M57 -> 0 | R57: 備註
K58: =SUM(SUM(B58:F58)*360,SUM(G58:J58)*90) -> 0 | N58: =K58+L58-M58 -> 0
K59: =SUM(SUM(B59:F59)*360,SUM(G59:J59)*90) -> 0 | N59: =K59+L59-M59 -> 0
K60: =SUM(SUM(B60:F60)*360,SUM(G60:J60)*90) -> 0 | N60: =K60+L60-M60 -> 0
K61: =SUM(SUM(B61:F61)*360,SUM(G61:J61)*90) -> 0 | N61: =K61+L61-M61 -> 0
K62: =SUM(SUM(B62:F62)*360,SUM(G62:J62)*90) -> 0 | N62: =K62+L62-M62 -> 0
K63: =SUM(SUM(B63:F63)*360,SUM(G63:J63)*90) -> 0 | N63: =K63+L63-M63 -> 0
K64: =SUM(SUM(B64:F64)*360,SUM(G64:J64)*90) -> 0 | N64: =K64+L64-M64 -> 0
K65: =SUM(SUM(B65:F65)*360,SUM(G65:J65)*90) -> 0 | N65: =K65+L65-M65 -> 0
K66: =SUM(SUM(B66:F66)*360,SUM(G66:J66)*90) -> 0 | N66: =K66+L66-M66 -> 0
K67: =SUM(SUM(B67:F67)*360,SUM(G67:J67)*90) -> 0 | N67: =K67+L67-M67 -> 0
K68: =SUM(SUM(B68:F68)*360,SUM(G68:J68)*90) -> 0 | N68: =K68+L68-M68 -> 0
K69: =SUM(SUM(B69:F69)*360,SUM(G69:J69)*90) -> 0 | N69: =K69+L69-M69 -> 0
... K101: =SUM(SUM(B101:F101)*360,SUM(G101:J101)*90) -> 0 | N101: =K101+L101-M101 -> 0

Sheet 15
A1: 日報表
A5: 銷售明細 | R5: 總結
A6: 類別 | B6: 禮盒 | G6: 單顆 | K6: 金額
A7: 購買人 | B7: 綜合 | C7: 原味 | D7: 可可 | E7: 伯爵 | F7: 抹茶 | G7: 原味. | H7: 可可. | I7: 伯爵. | J7: 抹茶. | K7: 金額 | L7: 運費 | M7: 折讓金額 | N7: 實收金額 | O7: 欄1 | P7: 備註
K8: =SUM(SUM(B8:F8)*360,SUM(G8:J8)*90) -> 0 | N8: =K8+L8-M8 -> 0 | R8: 金流 | X8: 應收帳款 | AB8: 今日未結帳款清單 | AC8: 今日銷帳清單
K9: =SUM(SUM(B9:F9)*360,SUM(G9:J9)*90) -> 0 | N9: =K9+L9-M9 -> 0 | R9: 營業總額 | T9: 運費 | U9: =SUMIF(表格1_334515253545556575859606162[欄1],"<>公關品",表格1_334515253545556575859606162[運費]) -> 0 | X9: 累積未結 | Y9: =INDEX('14'!Y12:Z13,1,1) -> 31984 | AB9: {=_xlfn.LET(_xlpm.unpaid,_xlfn.UNIQUE(_xlfn._xlws.FILTER(A8:A100,O8:O100="未結帳款","今日無欠款")),IF(_xlpm.unpaid="今日無欠款","今日無欠款",_xlpm.unpaid&"："&SUMIFS(N8:N100,A8:A100,_xlpm.unpaid,O8:O100,"未結帳款")))} -> 今日無欠款 | AC9: {=_xlfn.LET(_xlpm.paid,_xlfn.UNIQUE(_xlfn._xlws.FILTER(A8:A100,P8:P100="銷帳","今日無銷帳")),IF(_xlpm.paid="今日無銷帳","今日無銷帳",_xlpm.paid&"："&SUMIFS(N8:N100,A8:A100,_xlpm.paid,P8:P100,"銷帳")))} -> 今日無銷帳
K10: =SUM(SUM(B10:F10)*360,SUM(G10:J10)*90) -> 0 | N10: =K10+L10-M10 -> 0 | R10: =SUM(K8:K101)-V15 -> 0 | T10: 折讓 | U10: =SUM(M8:M101) -> 0 | X10: 今日未結 | Y10: =U15 -> 0
K11: =SUM(SUM(B11:F11)*360,SUM(G11:J11)*90) -> 0 | N11: =K11+L11-M11 -> 0 | R11: 營業額 | T11: 公關品 | U11: =SUMIF(P8:P100,"公關品",K8:K103) -> 0 | X11: 今日回款 | Y11: =V15 -> 0
K12: =SUM(SUM(B12:F12)*360,SUM(G12:J12)*90) -> 0 | N12: =K12+L12-M12 -> 0 | R12: =R10-U10-U11 -> 0 | T12: 應收 | V12: 實收 | X12: 剩餘未結 | Y12: =Y9+Y10-Y11 -> 31984
K13: =SUM(SUM(B13:F13)*360,SUM(G13:J13)*90) -> 0 | N13: =K13+L13-M13 -> 0 | T13: 匯款 | U13: =SUMIF(O8:O101,"匯款",N8:N101) -> 0
K14: =SUM(SUM(B14:F14)*360,SUM(G14:J14)*90) -> 0 | N14: =K14+L14-M14 -> 0 | T14: 現金 | U14: =SUMIF(O8:O102,"現金",N8:N102) -> 0
K15: =SUM(SUM(B15:F15)*360,SUM(G15:J15)*90) -> 0 | N15: =K15+L15-M15 -> 0 | T15: 未結帳款 | U15: =SUMIF(O8:O102,"未結帳款",N8:N103) -> 0 | V15: =SUMIF(P8:P100,"銷帳",N8:N100) -> 0
K16: =SUM(SUM(B16:F16)*360,SUM(G16:J16)*90) -> 0 | N16: =K16+L16-M16 -> 0 | T16: 銷帳 | X16: 物流
K17: =SUM(SUM(B17:F17)*360,SUM(G17:J17)*90) -> 0 | N17: =K17+L17-M17 -> 0 | R17: 商品銷售量 | X17: 運費實收 | Y17: =U9 -> 0
K18: =SUM(SUM(B18:F18)*360,SUM(G18:J18)*90) -> 0 | N18: =K18+L18-M18 -> 0 | T18: 販售量 | U18: 公關品 | V18: 總盒數 | X18: 運費實支
K19: =SUM(SUM(B19:F19)*360,SUM(G19:J19)*90) -> 0 | N19: =K19+L19-M19 -> 0 | R19: 禮盒 | S19: 綜合 | T19: =SUMIF(P8:P102,"<>公關品",B8:B100) -> 0 | U19: =SUMIF(P8:P102,"公關品",B8:B100) -> 0 | V19: =SUM(T19:T23,U19) -> 0 | X19: 公關運費 | Y19: =SUMIF(P8:P100,"公關品",L8:L100) -> 0
K20: =SUM(SUM(B20:F20)*360,SUM(G20:J20)*90) -> 0 | N20: =K20+L20-M20 -> 0 | S20: 原味 | T20: =SUMIF(P8:P102,"<>公關品",C8:C100) -> 0 | U20: =SUMIF(P8:P102,"公關品",C8:C100) -> 0 | V20: 總顆數 | X20: 物流包材 | Y20: =SUM(Z24:Z27) -> 0
K21: =SUM(SUM(B21:F21)*360,SUM(G21:J21)*90) -> 0 | N21: =K21+L21-M21 -> 0 | S21: 可可 | T21: =SUMIF(P8:P104,"<>公關品",D8:D102) -> 0 | U21: =SUMIF(P8:P102,"公關品",D8:D100) -> 0 | X21: 成本差額 | Y21: =Y17-Y18-Y20+Y19 -> 0
K22: =SUM(SUM(B22:F22)*360,SUM(G22:J22)*90) -> 0 | N22: =K22+L22-M22 -> 0 | S22: 伯爵 | T22: =SUMIF(P8:P102,"<>公關品",E8:E100) -> 0 | U22: =SUMIF(P8:P102,"公關品",E8:E100) -> 0 | X22: 物流包材
K23: =SUM(SUM(B23:F23)*360,SUM(G23:J23)*90) -> 0 | N23: =K23+L23-M23 -> 0 | S23: 抹茶 | T23: =SUMIF(P8:P102,"<>公關品",F8:F100) -> 0 | U23: =SUMIF(P8:P102,"公關品",F8:F100) -> 0 | X23: 種類 | Y23: 數量 | Z23: 總額
K24: =SUM(SUM(B24:F24)*360,SUM(G24:J24)*90) -> 0 | N24: =K24+L24-M24 -> 0 | R24: 單顆 | S24: 原味 | T24: =SUMIF(P9:P103,"<>公關品",G8:G100) -> 0 | U24: =SUMIF(P8:P102,"公關品",G8:G100) -> 0 | V24: =T19+(T20*4)+T24 -> 0 | X24: 2入紙箱
K25: =SUM(SUM(B25:F25)*360,SUM(G25:J25)*90) -> 0 | N25: =K25+L25-M25 -> 0 | S25: 可可 | T25: =SUMIF(P8:P102,"<>公關品",H8:H100) -> 0 | U25: =SUMIF(P8:P102,"公關品",I8:I100) -> 0 | V25: =T19+(T21*4)+T25 -> 0 | X25: 4入紙箱 | Z25: =Y25*5 -> 0
K26: =SUM(SUM(B26:F26)*360,SUM(G26:J26)*90) -> 0 | N26: =K26+L26-M26 -> 0 | S26: 伯爵 | T26: =SUMIF(P9:P103,"<>公關品",I8:I100) -> 0 | U26: =SUMIF(P8:P102,"公關品",I8:I100) -> 0 | V26: =T19+(T22*4)+T26 -> 0 | X26: 10入紙箱
K27: =SUM(SUM(B27:F27)*360,SUM(G27:J27)*90) -> 0 | N27: =K27+L27-M27 -> 0 | S27: 抹茶 | T27: =SUMIF(P8:P102,"<>公關品",J8:J100) -> 0 | U27: =SUMIF(P9:P103,"公關品",J8:J100) -> 0 | V27: =T19+(T23*4)+T27 -> 0 | X27: 膠帶
K28: =SUM(SUM(B28:F28)*360,SUM(G28:J28)*90) -> 0 | N28: =K28+L28-M28 -> 0
K29: =SUM(SUM(B29:F29)*360,SUM(G29:J29)*90) -> 0 | N29: =K29+L29-M29 -> 0
K30: =SUM(SUM(B30:F30)*360,SUM(G30:J30)*90) -> 0 | N30: =K30+L30-M30 -> 0 | R30: 產能及庫存 | AB30: 今日公關品總結
K31: =SUM(SUM(B31:F31)*360,SUM(G31:J31)*90) -> 0 | N31: =K31+L31-M31 -> 0 | AB31: 總禮盒數 | AC31: =SUM(U19:U23) -> 0
K32: =SUM(SUM(B32:F32)*360,SUM(G32:J32)*90) -> 0 | N32: =K32+L32-M32 -> 0 | R32: 品項 | S32: 原庫存 | T32: 預計產量 | U32: 實際產量 | V32: 耗損 | W32: 實際銷售量 | Y32: 今日庫存 | Z32: 總損耗率 | AB32: 總顆數 | AC32: =SUM(AC33:AC36) -> 0
K33: =SUM(SUM(B33:F33)*360,SUM(G33:J33)*90) -> 0 | N33: =K33+L33-M33 -> 0 | R33: 原味 | S33: ='14'!Y33 -> 0 | V33: =SUMIF(R40:R55,"原味",S40:S55) -> 0 | W33: =V24+U24+U19+U20*4 -> 0 | Y33: =S33+U33-V33-W33 -> 0 | Z33: =IFERROR((V33/(U33+S33))," ") | AB33: 原味 | AC33: =U24+U19+U20*4 -> 0
K34: =SUM(SUM(B34:F34)*360,SUM(G34:J34)*90) -> 0 | N34: =K34+L34-M34 -> 0 | R34: 可可 | S34: ='14'!Y34 -> 0 | V34: =SUMIF(R41:R55,"可可",S41:S55) -> 0 | W34: =V25+U25+U19+U21*4 -> 0 | Y34: =S34+U34-V34-W34 -> 0 | Z34: =IFERROR((V34/(U34+S34))," ") | AB34: 可可 | AC34: =U25+U19+U21*4 -> 0
K35: =SUM(SUM(B35:F35)*360,SUM(G35:J35)*90) -> 0 | N35: =K35+L35-M35 -> 0 | R35: 伯爵 | S35: ='14'!Y35 -> 0 | V35: =SUMIF(R41:R55,"伯爵",S41:S55) -> 0 | W35: =V26+U26+U19+U22*4 -> 0 | Y35: =S35+U35-V35-W35 -> 0 | Z35: =IFERROR((V35/(U35+S35))," ") | AB35: 伯爵 | AC35: =U26+U19+U22*4 -> 0
K36: =SUM(SUM(B36:F36)*360,SUM(G36:J36)*90) -> 0 | N36: =K36+L36-M36 -> 0 | R36: 抹茶 | S36: ='14'!Y36 -> 0 | V36: =SUMIF(R41:R55,"抹茶",S41:S55) -> 0 | W36: =V27+U27+U19+U23*4 -> 0 | Y36: =S36+U36-V36-W36 -> 0 | Z36: =IFERROR((V36/(U36+S36))," ") | AB36: 抹茶 | AC36: =U27+U19+U23*4 -> 0
K37: =SUM(SUM(B37:F37)*360,SUM(G37:J37)*90) -> 0 | N37: =K37+L37-M37 -> 0
K38: =SUM(SUM(B38:F38)*360,SUM(G38:J38)*90) -> 0 | N38: =K38+L38-M38 -> 0 | R38: 損耗原因
K39: =SUM(SUM(B39:F39)*360,SUM(G39:J39)*90) -> 0 | N39: =K39+L39-M39 -> 0
K40: =SUM(SUM(B40:F40)*360,SUM(G40:J40)*90) -> 0 | N40: =K40+L40-M40 -> 0 | R40: 品項 | S40: 數量 | T40: 類別 | U40: 原因
K41: =SUM(SUM(B41:F41)*360,SUM(G41:J41)*90) -> 0 | N41: =K41+L41-M41 -> 0
K42: =SUM(SUM(B42:F42)*360,SUM(G42:J42)*90) -> 0 | N42: =K42+L42-M42 -> 0
K43: =SUM(SUM(B43:F43)*360,SUM(G43:J43)*90) -> 0 | N43: =K43+L43-M43 -> 0
K44: =SUM(SUM(B44:F44)*360,SUM(G44:J44)*90) -> 0 | N44: =K44+L44-M44 -> 0
K45: =SUM(SUM(B45:F45)*360,SUM(G45:J45)*90) -> 0 | N45: =K45+L45-M45 -> 0
K46: =SUM(SUM(B46:F46)*360,SUM(G46:J46)*90) -> 0 | N46: =K46+L46-M46 -> 0
K47: =SUM(SUM(B47:F47)*360,SUM(G47:J47)*90) -> 0 | N47: =K47+L47-M47 -> 0
K48: =SUM(SUM(B48:F48)*360,SUM(G48:J48)*90) -> 0 | N48: =K48+L48-M48 -> 0
K49: =SUM(SUM(B49:F49)*360,SUM(G49:J49)*90) -> 0 | N49: =K49+L49-M49 -> 0
K50: =SUM(SUM(B50:F50)*360,SUM(G50:J50)*90) -> 0 | N50: =K50+L50-M50 -> 0
K51: =SUM(SUM(B51:F51)*360,SUM(G51:J51)*90) -> 0 | N51: =K51+L51-M51 -> 0
K52: =SUM(SUM(B52:F52)*360,SUM(G52:J52)*90) -> 0 | N52: =K52+L52-M52 -> 0
... K56: =SUM(SUM(B56:F56)*360,SUM(G56:J56)*90) -> 0 | N56: =K56+L56-M56 -> 0
K57: =SUM(SUM(B57:F57)*360,SUM(G57:J57)*90) -> 0 | N57: =K57+L57-M57 -> 0 | R57: 備註
K58: =SUM(SUM(B58:F58)*360,SUM(G58:J58)*90) -> 0 | N58: =K58+L58-M58 -> 0
K59: =SUM(SUM(B59:F59)*360,SUM(G59:J59)*90) -> 0 | N59: =K59+L59-M59 -> 0
K60: =SUM(SUM(B60:F60)*360,SUM(G60:J60)*90) -> 0 | N60: =K60+L60-M60 -> 0
K61: =SUM(SUM(B61:F61)*360,SUM(G61:J61)*90) -> 0 | N61: =K61+L61-M61 -> 0
K62: =SUM(SUM(B62:F62)*360,SUM(G62:J62)*90) -> 0 | N62: =K62+L62-M62 -> 0
K63: =SUM(SUM(B63:F63)*360,SUM(G63:J63)*90) -> 0 | N63: =K63+L63-M63 -> 0
K64: =SUM(SUM(B64:F64)*360,SUM(G64:J64)*90) -> 0 | N64: =K64+L64-M64 -> 0
K65: =SUM(SUM(B65:F65)*360,SUM(G65:J65)*90) -> 0 | N65: =K65+L65-M65 -> 0
K66: =SUM(SUM(B66:F66)*360,SUM(G66:J66)*90) -> 0 | N66: =K66+L66-M66 -> 0
K67: =SUM(SUM(B67:F67)*360,SUM(G67:J67)*90) -> 0 | N67: =K67+L67-M67 -> 0
K68: =SUM(SUM(B68:F68)*360,SUM(G68:J68)*90) -> 0 | N68: =K68+L68-M68 -> 0
K69: =SUM(SUM(B69:F69)*360,SUM(G69:J69)*90) -> 0 | N69: =K69+L69-M69 -> 0
... K101: =SUM(SUM(B101:F101)*360,SUM(G101:J101)*90) -> 0 | N101: =K101+L101-M101 -> 0

Sheet 16
A1: 日報表
A5: 銷售明細 | R5: 總結
A6: 類別 | B6: 禮盒 | G6: 單顆 | K6: 金額
A7: 購買人 | B7: 綜合 | C7: 原味 | D7: 可可 | E7: 伯爵 | F7: 抹茶 | G7: 原味. | H7: 可可. | I7: 伯爵. | J7: 抹茶. | K7: 金額 | L7: 運費 | M7: 折讓金額 | N7: 實收金額 | O7: 欄1 | P7: 備註
K8: =SUM(SUM(B8:F8)*360,SUM(G8:J8)*90) -> 0 | N8: =K8+L8-M8 -> 0 | R8: 金流 | X8: 應收帳款 | AB8: 今日未結帳款清單 | AC8: 今日銷帳清單
K9: =SUM(SUM(B9:F9)*360,SUM(G9:J9)*90) -> 0 | N9: =K9+L9-M9 -> 0 | R9: 營業總額 | T9: 運費 | U9: =SUMIF(表格1_33451525354555657585960616263[欄1],"<>公關品",表格1_33451525354555657585960616263[運費]) -> 0 | X9: 累積未結 | Y9: =INDEX('15'!Y12:Z13,1,1) -> 31984 | AB9: {=_xlfn.LET(_xlpm.unpaid,_xlfn.UNIQUE(_xlfn._xlws.FILTER(A8:A100,O8:O100="未結帳款","今日無欠款")),IF(_xlpm.unpaid="今日無欠款","今日無欠款",_xlpm.unpaid&"："&SUMIFS(N8:N100,A8:A100,_xlpm.unpaid,O8:O100,"未結帳款")))} -> 今日無欠款 | AC9: {=_xlfn.LET(_xlpm.paid,_xlfn.UNIQUE(_xlfn._xlws.FILTER(A8:A100,P8:P100="銷帳","今日無銷帳")),IF(_xlpm.paid="今日無銷帳","今日無銷帳",_xlpm.paid&"："&SUMIFS(N8:N100,A8:A100,_xlpm.paid,P8:P100,"銷帳")))} -> 今日無銷帳
K10: =SUM(SUM(B10:F10)*360,SUM(G10:J10)*90) -> 0 | N10: =K10+L10-M10 -> 0 | R10: =SUM(K8:K101)-V15 -> 0 | T10: 折讓 | U10: =SUM(M8:M101) -> 0 | X10: 今日未結 | Y10: =U15 -> 0
K11: =SUM(SUM(B11:F11)*360,SUM(G11:J11)*90) -> 0 | N11: =K11+L11-M11 -> 0 | R11: 營業額 | T11: 公關品 | U11: =SUMIF(P8:P100,"公關品",K8:K103) -> 0 | X11: 今日回款 | Y11: =V15 -> 0
K12: =SUM(SUM(B12:F12)*360,SUM(G12:J12)*90) -> 0 | N12: =K12+L12-M12 -> 0 | R12: =R10-U10-U11 -> 0 | T12: 應收 | V12: 實收 | X12: 剩餘未結 | Y12: =Y9+Y10-Y11 -> 31984
K13: =SUM(SUM(B13:F13)*360,SUM(G13:J13)*90) -> 0 | N13: =K13+L13-M13 -> 0 | T13: 匯款 | U13: =SUMIF(O8:O101,"匯款",N8:N101) -> 0
K14: =SUM(SUM(B14:F14)*360,SUM(G14:J14)*90) -> 0 | N14: =K14+L14-M14 -> 0 | T14: 現金 | U14: =SUMIF(O8:O102,"現金",N8:N102) -> 0
K15: =SUM(SUM(B15:F15)*360,SUM(G15:J15)*90) -> 0 | N15: =K15+L15-M15 -> 0 | T15: 未結帳款 | U15: =SUMIF(O8:O102,"未結帳款",N8:N103) -> 0 | V15: =SUMIF(P8:P100,"銷帳",N8:N100) -> 0
K16: =SUM(SUM(B16:F16)*360,SUM(G16:J16)*90) -> 0 | N16: =K16+L16-M16 -> 0 | T16: 銷帳 | X16: 物流
K17: =SUM(SUM(B17:F17)*360,SUM(G17:J17)*90) -> 0 | N17: =K17+L17-M17 -> 0 | R17: 商品銷售量 | X17: 運費實收 | Y17: =U9 -> 0
K18: =SUM(SUM(B18:F18)*360,SUM(G18:J18)*90) -> 0 | N18: =K18+L18-M18 -> 0 | T18: 販售量 | U18: 公關品 | V18: 總盒數 | X18: 運費實支
K19: =SUM(SUM(B19:F19)*360,SUM(G19:J19)*90) -> 0 | N19: =K19+L19-M19 -> 0 | R19: 禮盒 | S19: 綜合 | T19: =SUMIF(P8:P102,"<>公關品",B8:B100) -> 0 | U19: =SUMIF(P8:P102,"公關品",B8:B100) -> 0 | V19: =SUM(T19:T23,U19) -> 0 | X19: 公關運費 | Y19: =SUMIF(P8:P100,"公關品",L8:L100) -> 0
K20: =SUM(SUM(B20:F20)*360,SUM(G20:J20)*90) -> 0 | N20: =K20+L20-M20 -> 0 | S20: 原味 | T20: =SUMIF(P8:P102,"<>公關品",C8:C100) -> 0 | U20: =SUMIF(P8:P102,"公關品",C8:C100) -> 0 | V20: 總顆數 | X20: 物流包材 | Y20: =SUM(Z24:Z27) -> 0
K21: =SUM(SUM(B21:F21)*360,SUM(G21:J21)*90) -> 0 | N21: =K21+L21-M21 -> 0 | S21: 可可 | T21: =SUMIF(P8:P104,"<>公關品",D8:D102) -> 0 | U21: =SUMIF(P8:P102,"公關品",D8:D100) -> 0 | X21: 成本差額 | Y21: =Y17-Y18-Y20+Y19 -> 0
K22: =SUM(SUM(B22:F22)*360,SUM(G22:J22)*90) -> 0 | N22: =K22+L22-M22 -> 0 | S22: 伯爵 | T22: =SUMIF(P8:P102,"<>公關品",E8:E100) -> 0 | U22: =SUMIF(P8:P102,"公關品",E8:E100) -> 0 | X22: 物流包材
K23: =SUM(SUM(B23:F23)*360,SUM(G23:J23)*90) -> 0 | N23: =K23+L23-M23 -> 0 | S23: 抹茶 | T23: =SUMIF(P8:P102,"<>公關品",F8:F100) -> 0 | U23: =SUMIF(P8:P102,"公關品",F8:F100) -> 0 | X23: 種類 | Y23: 數量 | Z23: 總額
K24: =SUM(SUM(B24:F24)*360,SUM(G24:J24)*90) -> 0 | N24: =K24+L24-M24 -> 0 | R24: 單顆 | S24: 原味 | T24: =SUMIF(P9:P103,"<>公關品",G8:G100) -> 0 | U24: =SUMIF(P8:P102,"公關品",G8:G100) -> 0 | V24: =T19+(T20*4)+T24 -> 0 | X24: 2入紙箱
K25: =SUM(SUM(B25:F25)*360,SUM(G25:J25)*90) -> 0 | N25: =K25+L25-M25 -> 0 | S25: 可可 | T25: =SUMIF(P8:P102,"<>公關品",H8:H100) -> 0 | U25: =SUMIF(P8:P102,"公關品",I8:I100) -> 0 | V25: =T19+(T21*4)+T25 -> 0 | X25: 4入紙箱 | Z25: =Y25*5 -> 0
K26: =SUM(SUM(B26:F26)*360,SUM(G26:J26)*90) -> 0 | N26: =K26+L26-M26 -> 0 | S26: 伯爵 | T26: =SUMIF(P9:P103,"<>公關品",I8:I100) -> 0 | U26: =SUMIF(P8:P102,"公關品",I8:I100) -> 0 | V26: =T19+(T22*4)+T26 -> 0 | X26: 10入紙箱
K27: =SUM(SUM(B27:F27)*360,SUM(G27:J27)*90) -> 0 | N27: =K27+L27-M27 -> 0 | S27: 抹茶 | T27: =SUMIF(P8:P102,"<>公關品",J8:J100) -> 0 | U27: =SUMIF(P9:P103,"公關品",J8:J100) -> 0 | V27: =T19+(T23*4)+T27 -> 0 | X27: 膠帶
K28: =SUM(SUM(B28:F28)*360,SUM(G28:J28)*90) -> 0 | N28: =K28+L28-M28 -> 0
K29: =SUM(SUM(B29:F29)*360,SUM(G29:J29)*90) -> 0 | N29: =K29+L29-M29 -> 0
K30: =SUM(SUM(B30:F30)*360,SUM(G30:J30)*90) -> 0 | N30: =K30+L30-M30 -> 0 | R30: 產能及庫存 | AB30: 今日公關品總結
K31: =SUM(SUM(B31:F31)*360,SUM(G31:J31)*90) -> 0 | N31: =K31+L31-M31 -> 0 | AB31: 總禮盒數 | AC31: =SUM(U19:U23) -> 0
K32: =SUM(SUM(B32:F32)*360,SUM(G32:J32)*90) -> 0 | N32: =K32+L32-M32 -> 0 | R32: 品項 | S32: 原庫存 | T32: 預計產量 | U32: 實際產量 | V32: 耗損 | W32: 實際銷售量 | Y32: 今日庫存 | Z32: 總損耗率 | AB32: 總顆數 | AC32: =SUM(AC33:AC36) -> 0
K33: =SUM(SUM(B33:F33)*360,SUM(G33:J33)*90) -> 0 | N33: =K33+L33-M33 -> 0 | R33: 原味 | S33: ='15'!Y33 -> 0 | V33: =SUMIF(R40:R55,"原味",S40:S55) -> 0 | W33: =V24+U24+U19+U20*4 -> 0 | Y33: =S33+U33-V33-W33 -> 0 | Z33: =IFERROR((V33/(U33+S33))," ") | AB33: 原味 | AC33: =U24+U19+U20*4 -> 0
K34: =SUM(SUM(B34:F34)*360,SUM(G34:J34)*90) -> 0 | N34: =K34+L34-M34 -> 0 | R34: 可可 | S34: ='15'!Y34 -> 0 | V34: =SUMIF(R41:R55,"可可",S41:S55) -> 0 | W34: =V25+U25+U19+U21*4 -> 0 | Y34: =S34+U34-V34-W34 -> 0 | Z34: =IFERROR((V34/(U34+S34))," ") | AB34: 可可 | AC34: =U25+U19+U21*4 -> 0
K35: =SUM(SUM(B35:F35)*360,SUM(G35:J35)*90) -> 0 | N35: =K35+L35-M35 -> 0 | R35: 伯爵 | S35: ='15'!Y35 -> 0 | V35: =SUMIF(R41:R55,"伯爵",S41:S55) -> 0 | W35: =V26+U26+U19+U22*4 -> 0 | Y35: =S35+U35-V35-W35 -> 0 | Z35: =IFERROR((V35/(U35+S35))," ") | AB35: 伯爵 | AC35: =U26+U19+U22*4 -> 0
K36: =SUM(SUM(B36:F36)*360,SUM(G36:J36)*90) -> 0 | N36: =K36+L36-M36 -> 0 | R36: 抹茶 | S36: ='15'!Y36 -> 0 | V36: =SUMIF(R41:R55,"抹茶",S41:S55) -> 0 | W36: =V27+U27+U19+U23*4 -> 0 | Y36: =S36+U36-V36-W36 -> 0 | Z36: =IFERROR((V36/(U36+S36))," ") | AB36: 抹茶 | AC36: =U27+U19+U23*4 -> 0
K37: =SUM(SUM(B37:F37)*360,SUM(G37:J37)*90) -> 0 | N37: =K37+L37-M37 -> 0
K38: =SUM(SUM(B38:F38)*360,SUM(G38:J38)*90) -> 0 | N38: =K38+L38-M38 -> 0 | R38: 損耗原因
K39: =SUM(SUM(B39:F39)*360,SUM(G39:J39)*90) -> 0 | N39: =K39+L39-M39 -> 0
K40: =SUM(SUM(B40:F40)*360,SUM(G40:J40)*90) -> 0 | N40: =K40+L40-M40 -> 0 | R40: 品項 | S40: 數量 | T40: 類別 | U40: 原因
K41: =SUM(SUM(B41:F41)*360,SUM(G41:J41)*90) -> 0 | N41: =K41+L41-M41 -> 0
K42: =SUM(SUM(B42:F42)*360,SUM(G42:J42)*90) -> 0 | N42: =K42+L42-M42 -> 0
K43: =SUM(SUM(B43:F43)*360,SUM(G43:J43)*90) -> 0 | N43: =K43+L43-M43 -> 0
K44: =SUM(SUM(B44:F44)*360,SUM(G44:J44)*90) -> 0 | N44: =K44+L44-M44 -> 0
K45: =SUM(SUM(B45:F45)*360,SUM(G45:J45)*90) -> 0 | N45: =K45+L45-M45 -> 0
K46: =SUM(SUM(B46:F46)*360,SUM(G46:J46)*90) -> 0 | N46: =K46+L46-M46 -> 0
K47: =SUM(SUM(B47:F47)*360,SUM(G47:J47)*90) -> 0 | N47: =K47+L47-M47 -> 0
K48: =SUM(SUM(B48:F48)*360,SUM(G48:J48)*90) -> 0 | N48: =K48+L48-M48 -> 0
K49: =SUM(SUM(B49:F49)*360,SUM(G49:J49)*90) -> 0 | N49: =K49+L49-M49 -> 0
K50: =SUM(SUM(B50:F50)*360,SUM(G50:J50)*90) -> 0 | N50: =K50+L50-M50 -> 0
K51: =SUM(SUM(B51:F51)*360,SUM(G51:J51)*90) -> 0 | N51: =K51+L51-M51 -> 0
K52: =SUM(SUM(B52:F52)*360,SUM(G52:J52)*90) -> 0 | N52: =K52+L52-M52 -> 0
... K56: =SUM(SUM(B56:F56)*360,SUM(G56:J56)*90) -> 0 | N56: =K56+L56-M56 -> 0
K57: =SUM(SUM(B57:F57)*360,SUM(G57:J57)*90) -> 0 | N57: =K57+L57-M57 -> 0 | R57: 備註
K58: =SUM(SUM(B58:F58)*360,SUM(G58:J58)*90) -> 0 | N58: =K58+L58-M58 -> 0
K59: =SUM(SUM(B59:F59)*360,SUM(G59:J59)*90) -> 0 | N59: =K59+L59-M59 -> 0
K60: =SUM(SUM(B60:F60)*360,SUM(G60:J60)*90) -> 0 | N60: =K60+L60-M60 -> 0
K61: =SUM(SUM(B61:F61)*360,SUM(G61:J61)*90) -> 0 | N61: =K61+L61-M61 -> 0
K62: =SUM(SUM(B62:F62)*360,SUM(G62:J62)*90) -> 0 | N62: =K62+L62-M62 -> 0
K63: =SUM(SUM(B63:F63)*360,SUM(G63:J63)*90) -> 0 | N63: =K63+L63-M63 -> 0
K64: =SUM(SUM(B64:F64)*360,SUM(G64:J64)*90) -> 0 | N64: =K64+L64-M64 -> 0
K65: =SUM(SUM(B65:F65)*360,SUM(G65:J65)*90) -> 0 | N65: =K65+L65-M65 -> 0
K66: =SUM(SUM(B66:F66)*360,SUM(G66:J66)*90) -> 0 | N66: =K66+L66-M66 -> 0
K67: =SUM(SUM(B67:F67)*360,SUM(G67:J67)*90) -> 0 | N67: =K67+L67-M67 -> 0
K68: =SUM(SUM(B68:F68)*360,SUM(G68:J68)*90) -> 0 | N68: =K68+L68-M68 -> 0
K69: =SUM(SUM(B69:F69)*360,SUM(G69:J69)*90) -> 0 | N69: =K69+L69-M69 -> 0
... K101: =SUM(SUM(B101:F101)*360,SUM(G101:J101)*90) -> 0 | N101: =K101+L101-M101 -> 0

Sheet 17
A1: 日報表
A5: 銷售明細 | R5: 總結
A6: 類別 | B6: 禮盒 | G6: 單顆 | K6: 金額
A7: 購買人 | B7: 綜合 | C7: 原味 | D7: 可可 | E7: 伯爵 | F7: 抹茶 | G7: 原味. | H7: 可可. | I7: 伯爵. | J7: 抹茶. | K7: 金額 | L7: 運費 | M7: 折讓金額 | N7: 實收金額 | O7: 欄1 | P7: 備註
K8: =SUM(SUM(B8:F8)*360,SUM(G8:J8)*90) -> 0 | N8: =K8+L8-M8 -> 0 | R8: 金流 | X8: 應收帳款 | AB8: 今日未結帳款清單 | AC8: 今日銷帳清單
K9: =SUM(SUM(B9:F9)*360,SUM(G9:J9)*90) -> 0 | N9: =K9+L9-M9 -> 0 | R9: 營業總額 | T9: 運費 | U9: =SUMIF(表格1_3345152535455565758596061626364[欄1],"<>公關品",表格1_3345152535455565758596061626364[運費]) -> 0 | X9: 累積未結 | Y9: =INDEX('16'!Y12:Z13,1,1) -> 31984 | AB9: {=_xlfn.LET(_xlpm.unpaid,_xlfn.UNIQUE(_xlfn._xlws.FILTER(A8:A100,O8:O100="未結帳款","今日無欠款")),IF(_xlpm.unpaid="今日無欠款","今日無欠款",_xlpm.unpaid&"："&SUMIFS(N8:N100,A8:A100,_xlpm.unpaid,O8:O100,"未結帳款")))} -> 今日無欠款 | AC9: {=_xlfn.LET(_xlpm.paid,_xlfn.UNIQUE(_xlfn._xlws.FILTER(A8:A100,P8:P100="銷帳","今日無銷帳")),IF(_xlpm.paid="今日無銷帳","今日無銷帳",_xlpm.paid&"："&SUMIFS(N8:N100,A8:A100,_xlpm.paid,P8:P100,"銷帳")))} -> 今日無銷帳
K10: =SUM(SUM(B10:F10)*360,SUM(G10:J10)*90) -> 0 | N10: =K10+L10-M10 -> 0 | R10: =SUM(K8:K101)-V15 -> 0 | T10: 折讓 | U10: =SUM(M8:M101) -> 0 | X10: 今日未結 | Y10: =U15 -> 0
K11: =SUM(SUM(B11:F11)*360,SUM(G11:J11)*90) -> 0 | N11: =K11+L11-M11 -> 0 | R11: 營業額 | T11: 公關品 | U11: =SUMIF(P8:P100,"公關品",K8:K103) -> 0 | X11: 今日回款 | Y11: =V15 -> 0
K12: =SUM(SUM(B12:F12)*360,SUM(G12:J12)*90) -> 0 | N12: =K12+L12-M12 -> 0 | R12: =R10-U10-U11 -> 0 | T12: 應收 | V12: 實收 | X12: 剩餘未結 | Y12: =Y9+Y10-Y11 -> 31984
K13: =SUM(SUM(B13:F13)*360,SUM(G13:J13)*90) -> 0 | N13: =K13+L13-M13 -> 0 | T13: 匯款 | U13: =SUMIF(O8:O101,"匯款",N8:N101) -> 0
K14: =SUM(SUM(B14:F14)*360,SUM(G14:J14)*90) -> 0 | N14: =K14+L14-M14 -> 0 | T14: 現金 | U14: =SUMIF(O8:O102,"現金",N8:N102) -> 0
K15: =SUM(SUM(B15:F15)*360,SUM(G15:J15)*90) -> 0 | N15: =K15+L15-M15 -> 0 | T15: 未結帳款 | U15: =SUMIF(O8:O102,"未結帳款",N8:N103) -> 0 | V15: =SUMIF(P8:P100,"銷帳",N8:N100) -> 0
K16: =SUM(SUM(B16:F16)*360,SUM(G16:J16)*90) -> 0 | N16: =K16+L16-M16 -> 0 | T16: 銷帳 | X16: 物流
K17: =SUM(SUM(B17:F17)*360,SUM(G17:J17)*90) -> 0 | N17: =K17+L17-M17 -> 0 | R17: 商品銷售量 | X17: 運費實收 | Y17: =U9 -> 0
K18: =SUM(SUM(B18:F18)*360,SUM(G18:J18)*90) -> 0 | N18: =K18+L18-M18 -> 0 | T18: 販售量 | U18: 公關品 | V18: 總盒數 | X18: 運費實支
K19: =SUM(SUM(B19:F19)*360,SUM(G19:J19)*90) -> 0 | N19: =K19+L19-M19 -> 0 | R19: 禮盒 | S19: 綜合 | T19: =SUMIF(P8:P102,"<>公關品",B8:B100) -> 0 | U19: =SUMIF(P8:P102,"公關品",B8:B100) -> 0 | V19: =SUM(T19:T23,U19) -> 0 | X19: 公關運費 | Y19: =SUMIF(P8:P100,"公關品",L8:L100) -> 0
K20: =SUM(SUM(B20:F20)*360,SUM(G20:J20)*90) -> 0 | N20: =K20+L20-M20 -> 0 | S20: 原味 | T20: =SUMIF(P8:P102,"<>公關品",C8:C100) -> 0 | U20: =SUMIF(P8:P102,"公關品",C8:C100) -> 0 | V20: 總顆數 | X20: 物流包材 | Y20: =SUM(Z24:Z27) -> 0
K21: =SUM(SUM(B21:F21)*360,SUM(G21:J21)*90) -> 0 | N21: =K21+L21-M21 -> 0 | S21: 可可 | T21: =SUMIF(P8:P104,"<>公關品",D8:D102) -> 0 | U21: =SUMIF(P8:P102,"公關品",D8:D100) -> 0 | X21: 成本差額 | Y21: =Y17-Y18-Y20+Y19 -> 0
K22: =SUM(SUM(B22:F22)*360,SUM(G22:J22)*90) -> 0 | N22: =K22+L22-M22 -> 0 | S22: 伯爵 | T22: =SUMIF(P8:P102,"<>公關品",E8:E100) -> 0 | U22: =SUMIF(P8:P102,"公關品",E8:E100) -> 0 | X22: 物流包材
K23: =SUM(SUM(B23:F23)*360,SUM(G23:J23)*90) -> 0 | N23: =K23+L23-M23 -> 0 | S23: 抹茶 | T23: =SUMIF(P8:P102,"<>公關品",F8:F100) -> 0 | U23: =SUMIF(P8:P102,"公關品",F8:F100) -> 0 | X23: 種類 | Y23: 數量 | Z23: 總額
K24: =SUM(SUM(B24:F24)*360,SUM(G24:J24)*90) -> 0 | N24: =K24+L24-M24 -> 0 | R24: 單顆 | S24: 原味 | T24: =SUMIF(P9:P103,"<>公關品",G8:G100) -> 0 | U24: =SUMIF(P8:P102,"公關品",G8:G100) -> 0 | V24: =T19+(T20*4)+T24 -> 0 | X24: 2入紙箱
K25: =SUM(SUM(B25:F25)*360,SUM(G25:J25)*90) -> 0 | N25: =K25+L25-M25 -> 0 | S25: 可可 | T25: =SUMIF(P8:P102,"<>公關品",H8:H100) -> 0 | U25: =SUMIF(P8:P102,"公關品",I8:I100) -> 0 | V25: =T19+(T21*4)+T25 -> 0 | X25: 4入紙箱 | Z25: =Y25*5 -> 0
K26: =SUM(SUM(B26:F26)*360,SUM(G26:J26)*90) -> 0 | N26: =K26+L26-M26 -> 0 | S26: 伯爵 | T26: =SUMIF(P9:P103,"<>公關品",I8:I100) -> 0 | U26: =SUMIF(P8:P102,"公關品",I8:I100) -> 0 | V26: =T19+(T22*4)+T26 -> 0 | X26: 10入紙箱
K27: =SUM(SUM(B27:F27)*360,SUM(G27:J27)*90) -> 0 | N27: =K27+L27-M27 -> 0 | S27: 抹茶 | T27: =SUMIF(P8:P102,"<>公關品",J8:J100) -> 0 | U27: =SUMIF(P9:P103,"公關品",J8:J100) -> 0 | V27: =T19+(T23*4)+T27 -> 0 | X27: 膠帶
K28: =SUM(SUM(B28:F28)*360,SUM(G28:J28)*90) -> 0 | N28: =K28+L28-M28 -> 0
K29: =SUM(SUM(B29:F29)*360,SUM(G29:J29)*90) -> 0 | N29: =K29+L29-M29 -> 0
K30: =SUM(SUM(B30:F30)*360,SUM(G30:J30)*90) -> 0 | N30: =K30+L30-M30 -> 0 | R30: 產能及庫存 | AB30: 今日公關品總結
K31: =SUM(SUM(B31:F31)*360,SUM(G31:J31)*90) -> 0 | N31: =K31+L31-M31 -> 0 | AB31: 總禮盒數 | AC31: =SUM(U19:U23) -> 0
K32: =SUM(SUM(B32:F32)*360,SUM(G32:J32)*90) -> 0 | N32: =K32+L32-M32 -> 0 | R32: 品項 | S32: 原庫存 | T32: 預計產量 | U32: 實際產量 | V32: 耗損 | W32: 實際銷售量 | Y32: 今日庫存 | Z32: 總損耗率 | AB32: 總顆數 | AC32: =SUM(AC33:AC36) -> 0
K33: =SUM(SUM(B33:F33)*360,SUM(G33:J33)*90) -> 0 | N33: =K33+L33-M33 -> 0 | R33: 原味 | S33: ='16'!Y33 -> 0 | V33: =SUMIF(R40:R55,"原味",S40:S55) -> 0 | W33: =V24+U24+U19+U20*4 -> 0 | Y33: =S33+U33-V33-W33 -> 0 | Z33: =IFERROR((V33/(U33+S33))," ") | AB33: 原味 | AC33: =U24+U19+U20*4 -> 0
K34: =SUM(SUM(B34:F34)*360,SUM(G34:J34)*90) -> 0 | N34: =K34+L34-M34 -> 0 | R34: 可可 | S34: ='16'!Y34 -> 0 | V34: =SUMIF(R41:R55,"可可",S41:S55) -> 0 | W34: =V25+U25+U19+U21*4 -> 0 | Y34: =S34+U34-V34-W34 -> 0 | Z34: =IFERROR((V34/(U34+S34))," ") | AB34: 可可 | AC34: =U25+U19+U21*4 -> 0
K35: =SUM(SUM(B35:F35)*360,SUM(G35:J35)*90) -> 0 | N35: =K35+L35-M35 -> 0 | R35: 伯爵 | S35: ='16'!Y35 -> 0 | V35: =SUMIF(R41:R55,"伯爵",S41:S55) -> 0 | W35: =V26+U26+U19+U22*4 -> 0 | Y35: =S35+U35-V35-W35 -> 0 | Z35: =IFERROR((V35/(U35+S35))," ") | AB35: 伯爵 | AC35: =U26+U19+U22*4 -> 0
K36: =SUM(SUM(B36:F36)*360,SUM(G36:J36)*90) -> 0 | N36: =K36+L36-M36 -> 0 | R36: 抹茶 | S36: ='16'!Y36 -> 0 | V36: =SUMIF(R41:R55,"抹茶",S41:S55) -> 0 | W36: =V27+U27+U19+U23*4 -> 0 | Y36: =S36+U36-V36-W36 -> 0 | Z36: =IFERROR((V36/(U36+S36))," ") | AB36: 抹茶 | AC36: =U27+U19+U23*4 -> 0
K37: =SUM(SUM(B37:F37)*360,SUM(G37:J37)*90) -> 0 | N37: =K37+L37-M37 -> 0
K38: =SUM(SUM(B38:F38)*360,SUM(G38:J38)*90) -> 0 | N38: =K38+L38-M38 -> 0 | R38: 損耗原因
K39: =SUM(SUM(B39:F39)*360,SUM(G39:J39)*90) -> 0 | N39: =K39+L39-M39 -> 0
K40: =SUM(SUM(B40:F40)*360,SUM(G40:J40)*90) -> 0 | N40: =K40+L40-M40 -> 0 | R40: 品項 | S40: 數量 | T40: 類別 | U40: 原因
K41: =SUM(SUM(B41:F41)*360,SUM(G41:J41)*90) -> 0 | N41: =K41+L41-M41 -> 0
K42: =SUM(SUM(B42:F42)*360,SUM(G42:J42)*90) -> 0 | N42: =K42+L42-M42 -> 0
K43: =SUM(SUM(B43:F43)*360,SUM(G43:J43)*90) -> 0 | N43: =K43+L43-M43 -> 0
K44: =SUM(SUM(B44:F44)*360,SUM(G44:J44)*90) -> 0 | N44: =K44+L44-M44 -> 0
K45: =SUM(SUM(B45:F45)*360,SUM(G45:J45)*90) -> 0 | N45: =K45+L45-M45 -> 0
K46: =SUM(SUM(B46:F46)*360,SUM(G46:J46)*90) -> 0 | N46: =K46+L46-M46 -> 0
K47: =SUM(SUM(B47:F47)*360,SUM(G47:J47)*90) -> 0 | N47: =K47+L47-M47 -> 0
K48: =SUM(SUM(B48:F48)*360,SUM(G48:J48)*90) -> 0 | N48: =K48+L48-M48 -> 0
K49: =SUM(SUM(B49:F49)*360,SUM(G49:J49)*90) -> 0 | N49: =K49+L49-M49 -> 0
K50: =SUM(SUM(B50:F50)*360,SUM(G50:J50)*90) -> 0 | N50: =K50+L50-M50 -> 0
K51: =SUM(SUM(B51:F51)*360,SUM(G51:J51)*90) -> 0 | N51: =K51+L51-M51 -> 0
K52: =SUM(SUM(B52:F52)*360,SUM(G52:J52)*90) -> 0 | N52: =K52+L52-M52 -> 0
... K56: =SUM(SUM(B56:F56)*360,SUM(G56:J56)*90) -> 0 | N56: =K56+L56-M56 -> 0
K57: =SUM(SUM(B57:F57)*360,SUM(G57:J57)*90) -> 0 | N57: =K57+L57-M57 -> 0 | R57: 備註
K58: =SUM(SUM(B58:F58)*360,SUM(G58:J58)*90) -> 0 | N58: =K58+L58-M58 -> 0
K59: =SUM(SUM(B59:F59)*360,SUM(G59:J59)*90) -> 0 | N59: =K59+L59-M59 -> 0
K60: =SUM(SUM(B60:F60)*360,SUM(G60:J60)*90) -> 0 | N60: =K60+L60-M60 -> 0
K61: =SUM(SUM(B61:F61)*360,SUM(G61:J61)*90) -> 0 | N61: =K61+L61-M61 -> 0
K62: =SUM(SUM(B62:F62)*360,SUM(G62:J62)*90) -> 0 | N62: =K62+L62-M62 -> 0
K63: =SUM(SUM(B63:F63)*360,SUM(G63:J63)*90) -> 0 | N63: =K63+L63-M63 -> 0
K64: =SUM(SUM(B64:F64)*360,SUM(G64:J64)*90) -> 0 | N64: =K64+L64-M64 -> 0
K65: =SUM(SUM(B65:F65)*360,SUM(G65:J65)*90) -> 0 | N65: =K65+L65-M65 -> 0
K66: =SUM(SUM(B66:F66)*360,SUM(G66:J66)*90) -> 0 | N66: =K66+L66-M66 -> 0
K67: =SUM(SUM(B67:F67)*360,SUM(G67:J67)*90) -> 0 | N67: =K67+L67-M67 -> 0
K68: =SUM(SUM(B68:F68)*360,SUM(G68:J68)*90) -> 0 | N68: =K68+L68-M68 -> 0
K69: =SUM(SUM(B69:F69)*360,SUM(G69:J69)*90) -> 0 | N69: =K69+L69-M69 -> 0
... K101: =SUM(SUM(B101:F101)*360,SUM(G101:J101)*90) -> 0 | N101: =K101+L101-M101 -> 0

Sheet 18
A1: 日報表
A5: 銷售明細 | R5: 總結
A6: 類別 | B6: 禮盒 | G6: 單顆 | K6: 金額
A7: 購買人 | B7: 綜合 | C7: 原味 | D7: 可可 | E7: 伯爵 | F7: 抹茶 | G7: 原味. | H7: 可可. | I7: 伯爵. | J7: 抹茶. | K7: 金額 | L7: 運費 | M7: 折讓金額 | N7: 實收金額 | O7: 欄1 | P7: 備註
K8: =SUM(SUM(B8:F8)*360,SUM(G8:J8)*90) -> 0 | N8: =K8+L8-M8 -> 0 | R8: 金流 | X8: 應收帳款 | AB8: 今日未結帳款清單 | AC8: 今日銷帳清單
K9: =SUM(SUM(B9:F9)*360,SUM(G9:J9)*90) -> 0 | N9: =K9+L9-M9 -> 0 | R9: 營業總額 | T9: 運費 | U9: =SUMIF(表格1_334515253545556575859606162636465[欄1],"<>公關品",表格1_334515253545556575859606162636465[運費]) -> 0 | X9: 累積未結 | Y9: =INDEX('17'!Y12:Z13,1,1) -> 31984 | AB9: {=_xlfn.LET(_xlpm.unpaid,_xlfn.UNIQUE(_xlfn._xlws.FILTER(A8:A100,O8:O100="未結帳款","今日無欠款")),IF(_xlpm.unpaid="今日無欠款","今日無欠款",_xlpm.unpaid&"："&SUMIFS(N8:N100,A8:A100,_xlpm.unpaid,O8:O100,"未結帳款")))} -> 今日無欠款 | AC9: {=_xlfn.LET(_xlpm.paid,_xlfn.UNIQUE(_xlfn._xlws.FILTER(A8:A100,P8:P100="銷帳","今日無銷帳")),IF(_xlpm.paid="今日無銷帳","今日無銷帳",_xlpm.paid&"："&SUMIFS(N8:N100,A8:A100,_xlpm.paid,P8:P100,"銷帳")))} -> 今日無銷帳
K10: =SUM(SUM(B10:F10)*360,SUM(G10:J10)*90) -> 0 | N10: =K10+L10-M10 -> 0 | R10: =SUM(K8:K101)-V15 -> 0 | T10: 折讓 | U10: =SUM(M8:M101) -> 0 | X10: 今日未結 | Y10: =U15 -> 0
K11: =SUM(SUM(B11:F11)*360,SUM(G11:J11)*90) -> 0 | N11: =K11+L11-M11 -> 0 | R11: 營業額 | T11: 公關品 | U11: =SUMIF(P8:P100,"公關品",K8:K103) -> 0 | X11: 今日回款 | Y11: =V15 -> 0
K12: =SUM(SUM(B12:F12)*360,SUM(G12:J12)*90) -> 0 | N12: =K12+L12-M12 -> 0 | R12: =R10-U10-U11 -> 0 | T12: 應收 | V12: 實收 | X12: 剩餘未結 | Y12: =Y9+Y10-Y11 -> 31984
K13: =SUM(SUM(B13:F13)*360,SUM(G13:J13)*90) -> 0 | N13: =K13+L13-M13 -> 0 | T13: 匯款 | U13: =SUMIF(O8:O101,"匯款",N8:N101) -> 0
K14: =SUM(SUM(B14:F14)*360,SUM(G14:J14)*90) -> 0 | N14: =K14+L14-M14 -> 0 | T14: 現金 | U14: =SUMIF(O8:O102,"現金",N8:N102) -> 0
K15: =SUM(SUM(B15:F15)*360,SUM(G15:J15)*90) -> 0 | N15: =K15+L15-M15 -> 0 | T15: 未結帳款 | U15: =SUMIF(O8:O102,"未結帳款",N8:N103) -> 0 | V15: =SUMIF(P8:P100,"銷帳",N8:N100) -> 0
K16: =SUM(SUM(B16:F16)*360,SUM(G16:J16)*90) -> 0 | N16: =K16+L16-M16 -> 0 | T16: 銷帳 | X16: 物流
K17: =SUM(SUM(B17:F17)*360,SUM(G17:J17)*90) -> 0 | N17: =K17+L17-M17 -> 0 | R17: 商品銷售量 | X17: 運費實收 | Y17: =U9 -> 0
K18: =SUM(SUM(B18:F18)*360,SUM(G18:J18)*90) -> 0 | N18: =K18+L18-M18 -> 0 | T18: 販售量 | U18: 公關品 | V18: 總盒數 | X18: 運費實支
K19: =SUM(SUM(B19:F19)*360,SUM(G19:J19)*90) -> 0 | N19: =K19+L19-M19 -> 0 | R19: 禮盒 | S19: 綜合 | T19: =SUMIF(P8:P102,"<>公關品",B8:B100) -> 0 | U19: =SUMIF(P8:P102,"公關品",B8:B100) -> 0 | V19: =SUM(T19:T23,U19) -> 0 | X19: 公關運費 | Y19: =SUMIF(P8:P100,"公關品",L8:L100) -> 0
K20: =SUM(SUM(B20:F20)*360,SUM(G20:J20)*90) -> 0 | N20: =K20+L20-M20 -> 0 | S20: 原味 | T20: =SUMIF(P8:P102,"<>公關品",C8:C100) -> 0 | U20: =SUMIF(P8:P102,"公關品",C8:C100) -> 0 | V20: 總顆數 | X20: 物流包材 | Y20: =SUM(Z24:Z27) -> 0
K21: =SUM(SUM(B21:F21)*360,SUM(G21:J21)*90) -> 0 | N21: =K21+L21-M21 -> 0 | S21: 可可 | T21: =SUMIF(P8:P104,"<>公關品",D8:D102) -> 0 | U21: =SUMIF(P8:P102,"公關品",D8:D100) -> 0 | X21: 成本差額 | Y21: =Y17-Y18-Y20+Y19 -> 0
K22: =SUM(SUM(B22:F22)*360,SUM(G22:J22)*90) -> 0 | N22: =K22+L22-M22 -> 0 | S22: 伯爵 | T22: =SUMIF(P8:P102,"<>公關品",E8:E100) -> 0 | U22: =SUMIF(P8:P102,"公關品",E8:E100) -> 0 | X22: 物流包材
K23: =SUM(SUM(B23:F23)*360,SUM(G23:J23)*90) -> 0 | N23: =K23+L23-M23 -> 0 | S23: 抹茶 | T23: =SUMIF(P8:P102,"<>公關品",F8:F100) -> 0 | U23: =SUMIF(P8:P102,"公關品",F8:F100) -> 0 | X23: 種類 | Y23: 數量 | Z23: 總額
K24: =SUM(SUM(B24:F24)*360,SUM(G24:J24)*90) -> 0 | N24: =K24+L24-M24 -> 0 | R24: 單顆 | S24: 原味 | T24: =SUMIF(P9:P103,"<>公關品",G8:G100) -> 0 | U24: =SUMIF(P8:P102,"公關品",G8:G100) -> 0 | V24: =T19+(T20*4)+T24 -> 0 | X24: 2入紙箱
K25: =SUM(SUM(B25:F25)*360,SUM(G25:J25)*90) -> 0 | N25: =K25+L25-M25 -> 0 | S25: 可可 | T25: =SUMIF(P8:P102,"<>公關品",H8:H100) -> 0 | U25: =SUMIF(P8:P102,"公關品",I8:I100) -> 0 | V25: =T19+(T21*4)+T25 -> 0 | X25: 4入紙箱 | Z25: =Y25*5 -> 0
K26: =SUM(SUM(B26:F26)*360,SUM(G26:J26)*90) -> 0 | N26: =K26+L26-M26 -> 0 | S26: 伯爵 | T26: =SUMIF(P9:P103,"<>公關品",I8:I100) -> 0 | U26: =SUMIF(P8:P102,"公關品",I8:I100) -> 0 | V26: =T19+(T22*4)+T26 -> 0 | X26: 10入紙箱
K27: =SUM(SUM(B27:F27)*360,SUM(G27:J27)*90) -> 0 | N27: =K27+L27-M27 -> 0 | S27: 抹茶 | T27: =SUMIF(P8:P102,"<>公關品",J8:J100) -> 0 | U27: =SUMIF(P9:P103,"公關品",J8:J100) -> 0 | V27: =T19+(T23*4)+T27 -> 0 | X27: 膠帶
K28: =SUM(SUM(B28:F28)*360,SUM(G28:J28)*90) -> 0 | N28: =K28+L28-M28 -> 0
K29: =SUM(SUM(B29:F29)*360,SUM(G29:J29)*90) -> 0 | N29: =K29+L29-M29 -> 0
K30: =SUM(SUM(B30:F30)*360,SUM(G30:J30)*90) -> 0 | N30: =K30+L30-M30 -> 0 | R30: 產能及庫存 | AB30: 今日公關品總結
K31: =SUM(SUM(B31:F31)*360,SUM(G31:J31)*90) -> 0 | N31: =K31+L31-M31 -> 0 | AB31: 總禮盒數 | AC31: =SUM(U19:U23) -> 0
K32: =SUM(SUM(B32:F32)*360,SUM(G32:J32)*90) -> 0 | N32: =K32+L32-M32 -> 0 | R32: 品項 | S32: 原庫存 | T32: 預計產量 | U32: 實際產量 | V32: 耗損 | W32: 實際銷售量 | Y32: 今日庫存 | Z32: 總損耗率 | AB32: 總顆數 | AC32: =SUM(AC33:AC36) -> 0
K33: =SUM(SUM(B33:F33)*360,SUM(G33:J33)*90) -> 0 | N33: =K33+L33-M33 -> 0 | R33: 原味 | S33: ='17'!Y33 -> 0 | V33: =SUMIF(R40:R55,"原味",S40:S55) -> 0 | W33: =V24+U24+U19+U20*4 -> 0 | Y33: =S33+U33-V33-W33 -> 0 | Z33: =IFERROR((V33/(U33+S33))," ") | AB33: 原味 | AC33: =U24+U19+U20*4 -> 0
K34: =SUM(SUM(B34:F34)*360,SUM(G34:J34)*90) -> 0 | N34: =K34+L34-M34 -> 0 | R34: 可可 | S34: ='17'!Y34 -> 0 | V34: =SUMIF(R41:R55,"可可",S41:S55) -> 0 | W34: =V25+U25+U19+U21*4 -> 0 | Y34: =S34+U34-V34-W34 -> 0 | Z34: =IFERROR((V34/(U34+S34))," ") | AB34: 可可 | AC34: =U25+U19+U21*4 -> 0
K35: =SUM(SUM(B35:F35)*360,SUM(G35:J35)*90) -> 0 | N35: =K35+L35-M35 -> 0 | R35: 伯爵 | S35: ='17'!Y35 -> 0 | V35: =SUMIF(R41:R55,"伯爵",S41:S55) -> 0 | W35: =V26+U26+U19+U22*4 -> 0 | Y35: =S35+U35-V35-W35 -> 0 | Z35: =IFERROR((V35/(U35+S35))," ") | AB35: 伯爵 | AC35: =U26+U19+U22*4 -> 0
K36: =SUM(SUM(B36:F36)*360,SUM(G36:J36)*90) -> 0 | N36: =K36+L36-M36 -> 0 | R36: 抹茶 | S36: ='17'!Y36 -> 0 | V36: =SUMIF(R41:R55,"抹茶",S41:S55) -> 0 | W36: =V27+U27+U19+U23*4 -> 0 | Y36: =S36+U36-V36-W36 -> 0 | Z36: =IFERROR((V36/(U36+S36))," ") | AB36: 抹茶 | AC36: =U27+U19+U23*4 -> 0
K37: =SUM(SUM(B37:F37)*360,SUM(G37:J37)*90) -> 0 | N37: =K37+L37-M37 -> 0
K38: =SUM(SUM(B38:F38)*360,SUM(G38:J38)*90) -> 0 | N38: =K38+L38-M38 -> 0 | R38: 損耗原因
K39: =SUM(SUM(B39:F39)*360,SUM(G39:J39)*90) -> 0 | N39: =K39+L39-M39 -> 0
K40: =SUM(SUM(B40:F40)*360,SUM(G40:J40)*90) -> 0 | N40: =K40+L40-M40 -> 0 | R40: 品項 | S40: 數量 | T40: 類別 | U40: 原因
K41: =SUM(SUM(B41:F41)*360,SUM(G41:J41)*90) -> 0 | N41: =K41+L41-M41 -> 0
K42: =SUM(SUM(B42:F42)*360,SUM(G42:J42)*90) -> 0 | N42: =K42+L42-M42 -> 0
K43: =SUM(SUM(B43:F43)*360,SUM(G43:J43)*90) -> 0 | N43: =K43+L43-M43 -> 0
K44: =SUM(SUM(B44:F44)*360,SUM(G44:J44)*90) -> 0 | N44: =K44+L44-M44 -> 0
K45: =SUM(SUM(B45:F45)*360,SUM(G45:J45)*90) -> 0 | N45: =K45+L45-M45 -> 0
K46: =SUM(SUM(B46:F46)*360,SUM(G46:J46)*90) -> 0 | N46: =K46+L46-M46 -> 0
K47: =SUM(SUM(B47:F47)*360,SUM(G47:J47)*90) -> 0 | N47: =K47+L47-M47 -> 0
K48: =SUM(SUM(B48:F48)*360,SUM(G48:J48)*90) -> 0 | N48: =K48+L48-M48 -> 0
K49: =SUM(SUM(B49:F49)*360,SUM(G49:J49)*90) -> 0 | N49: =K49+L49-M49 -> 0
K50: =SUM(SUM(B50:F50)*360,SUM(G50:J50)*90) -> 0 | N50: =K50+L50-M50 -> 0
K51: =SUM(SUM(B51:F51)*360,SUM(G51:J51)*90) -> 0 | N51: =K51+L51-M51 -> 0
K52: =SUM(SUM(B52:F52)*360,SUM(G52:J52)*90) -> 0 | N52: =K52+L52-M52 -> 0
... K56: =SUM(SUM(B56:F56)*360,SUM(G56:J56)*90) -> 0 | N56: =K56+L56-M56 -> 0
K57: =SUM(SUM(B57:F57)*360,SUM(G57:J57)*90) -> 0 | N57: =K57+L57-M57 -> 0 | R57: 備註
K58: =SUM(SUM(B58:F58)*360,SUM(G58:J58)*90) -> 0 | N58: =K58+L58-M58 -> 0
K59: =SUM(SUM(B59:F59)*360,SUM(G59:J59)*90) -> 0 | N59: =K59+L59-M59 -> 0
K60: =SUM(SUM(B60:F60)*360,SUM(G60:J60)*90) -> 0 | N60: =K60+L60-M60 -> 0
K61: =SUM(SUM(B61:F61)*360,SUM(G61:J61)*90) -> 0 | N61: =K61+L61-M61 -> 0
K62: =SUM(SUM(B62:F62)*360,SUM(G62:J62)*90) -> 0 | N62: =K62+L62-M62 -> 0
K63: =SUM(SUM(B63:F63)*360,SUM(G63:J63)*90) -> 0 | N63: =K63+L63-M63 -> 0
K64: =SUM(SUM(B64:F64)*360,SUM(G64:J64)*90) -> 0 | N64: =K64+L64-M64 -> 0
K65: =SUM(SUM(B65:F65)*360,SUM(G65:J65)*90) -> 0 | N65: =K65+L65-M65 -> 0
K66: =SUM(SUM(B66:F66)*360,SUM(G66:J66)*90) -> 0 | N66: =K66+L66-M66 -> 0
K67: =SUM(SUM(B67:F67)*360,SUM(G67:J67)*90) -> 0 | N67: =K67+L67-M67 -> 0
K68: =SUM(SUM(B68:F68)*360,SUM(G68:J68)*90) -> 0 | N68: =K68+L68-M68 -> 0
K69: =SUM(SUM(B69:F69)*360,SUM(G69:J69)*90) -> 0 | N69: =K69+L69-M69 -> 0
... K101: =SUM(SUM(B101:F101)*360,SUM(G101:J101)*90) -> 0 | N101: =K101+L101-M101 -> 0

Sheet 19
A1: 日報表
A5: 銷售明細 | R5: 總結
A6: 類別 | B6: 禮盒 | G6: 單顆 | K6: 金額
A7: 購買人 | B7: 綜合 | C7: 原味 | D7: 可可 | E7: 伯爵 | F7: 抹茶 | G7: 原味. | H7: 可可. | I7: 伯爵. | J7: 抹茶. | K7: 金額 | L7: 運費 | M7: 折讓金額 | N7: 實收金額 | O7: 欄1 | P7: 備註
K8: =SUM(SUM(B8:F8)*360,SUM(G8:J8)*90) -> 0 | N8: =K8+L8-M8 -> 0 | R8: 金流 | X8: 應收帳款 | AB8: 今日未結帳款清單 | AC8: 今日銷帳清單
K9: =SUM(SUM(B9:F9)*360,SUM(G9:J9)*90) -> 0 | N9: =K9+L9-M9 -> 0 | R9: 營業總額 | T9: 運費 | U9: =SUMIF(表格1_33451525354555657585960616263646566[欄1],"<>公關品",表格1_33451525354555657585960616263646566[運費]) -> 0 | X9: 累積未結 | Y9: =INDEX('18'!Y12:Z13,1,1) -> 31984 | AB9: {=_xlfn.LET(_xlpm.unpaid,_xlfn.UNIQUE(_xlfn._xlws.FILTER(A8:A100,O8:O100="未結帳款","今日無欠款")),IF(_xlpm.unpaid="今日無欠款","今日無欠款",_xlpm.unpaid&"："&SUMIFS(N8:N100,A8:A100,_xlpm.unpaid,O8:O100,"未結帳款")))} -> 今日無欠款 | AC9: {=_xlfn.LET(_xlpm.paid,_xlfn.UNIQUE(_xlfn._xlws.FILTER(A8:A100,P8:P100="銷帳","今日無銷帳")),IF(_xlpm.paid="今日無銷帳","今日無銷帳",_xlpm.paid&"："&SUMIFS(N8:N100,A8:A100,_xlpm.paid,P8:P100,"銷帳")))} -> 今日無銷帳
K10: =SUM(SUM(B10:F10)*360,SUM(G10:J10)*90) -> 0 | N10: =K10+L10-M10 -> 0 | R10: =SUM(K8:K101)-V15 -> 0 | T10: 折讓 | U10: =SUM(M8:M101) -> 0 | X10: 今日未結 | Y10: =U15 -> 0
K11: =SUM(SUM(B11:F11)*360,SUM(G11:J11)*90) -> 0 | N11: =K11+L11-M11 -> 0 | R11: 營業額 | T11: 公關品 | U11: =SUMIF(P8:P100,"公關品",K8:K103) -> 0 | X11: 今日回款 | Y11: =V15 -> 0
K12: =SUM(SUM(B12:F12)*360,SUM(G12:J12)*90) -> 0 | N12: =K12+L12-M12 -> 0 | R12: =R10-U10-U11 -> 0 | T12: 應收 | V12: 實收 | X12: 剩餘未結 | Y12: =Y9+Y10-Y11 -> 31984
K13: =SUM(SUM(B13:F13)*360,SUM(G13:J13)*90) -> 0 | N13: =K13+L13-M13 -> 0 | T13: 匯款 | U13: =SUMIF(O8:O101,"匯款",N8:N101) -> 0
K14: =SUM(SUM(B14:F14)*360,SUM(G14:J14)*90) -> 0 | N14: =K14+L14-M14 -> 0 | T14: 現金 | U14: =SUMIF(O8:O102,"現金",N8:N102) -> 0
K15: =SUM(SUM(B15:F15)*360,SUM(G15:J15)*90) -> 0 | N15: =K15+L15-M15 -> 0 | T15: 未結帳款 | U15: =SUMIF(O8:O102,"未結帳款",N8:N103) -> 0 | V15: =SUMIF(P8:P100,"銷帳",N8:N100) -> 0
K16: =SUM(SUM(B16:F16)*360,SUM(G16:J16)*90) -> 0 | N16: =K16+L16-M16 -> 0 | T16: 銷帳 | X16: 物流
K17: =SUM(SUM(B17:F17)*360,SUM(G17:J17)*90) -> 0 | N17: =K17+L17-M17 -> 0 | R17: 商品銷售量 | X17: 運費實收 | Y17: =U9 -> 0
K18: =SUM(SUM(B18:F18)*360,SUM(G18:J18)*90) -> 0 | N18: =K18+L18-M18 -> 0 | T18: 販售量 | U18: 公關品 | V18: 總盒數 | X18: 運費實支
K19: =SUM(SUM(B19:F19)*360,SUM(G19:J19)*90) -> 0 | N19: =K19+L19-M19 -> 0 | R19: 禮盒 | S19: 綜合 | T19: =SUMIF(P8:P102,"<>公關品",B8:B100) -> 0 | U19: =SUMIF(P8:P102,"公關品",B8:B100) -> 0 | V19: =SUM(T19:T23,U19) -> 0 | X19: 公關運費 | Y19: =SUMIF(P8:P100,"公關品",L8:L100) -> 0
K20: =SUM(SUM(B20:F20)*360,SUM(G20:J20)*90) -> 0 | N20: =K20+L20-M20 -> 0 | S20: 原味 | T20: =SUMIF(P8:P102,"<>公關品",C8:C100) -> 0 | U20: =SUMIF(P8:P102,"公關品",C8:C100) -> 0 | V20: 總顆數 | X20: 物流包材 | Y20: =SUM(Z24:Z27) -> 0
K21: =SUM(SUM(B21:F21)*360,SUM(G21:J21)*90) -> 0 | N21: =K21+L21-M21 -> 0 | S21: 可可 | T21: =SUMIF(P8:P104,"<>公關品",D8:D102) -> 0 | U21: =SUMIF(P8:P102,"公關品",D8:D100) -> 0 | X21: 成本差額 | Y21: =Y17-Y18-Y20+Y19 -> 0
K22: =SUM(SUM(B22:F22)*360,SUM(G22:J22)*90) -> 0 | N22: =K22+L22-M22 -> 0 | S22: 伯爵 | T22: =SUMIF(P8:P102,"<>公關品",E8:E100) -> 0 | U22: =SUMIF(P8:P102,"公關品",E8:E100) -> 0 | X22: 物流包材
K23: =SUM(SUM(B23:F23)*360,SUM(G23:J23)*90) -> 0 | N23: =K23+L23-M23 -> 0 | S23: 抹茶 | T23: =SUMIF(P8:P102,"<>公關品",F8:F100) -> 0 | U23: =SUMIF(P8:P102,"公關品",F8:F100) -> 0 | X23: 種類 | Y23: 數量 | Z23: 總額
K24: =SUM(SUM(B24:F24)*360,SUM(G24:J24)*90) -> 0 | N24: =K24+L24-M24 -> 0 | R24: 單顆 | S24: 原味 | T24: =SUMIF(P9:P103,"<>公關品",G8:G100) -> 0 | U24: =SUMIF(P8:P102,"公關品",G8:G100) -> 0 | V24: =T19+(T20*4)+T24 -> 0 | X24: 2入紙箱
K25: =SUM(SUM(B25:F25)*360,SUM(G25:J25)*90) -> 0 | N25: =K25+L25-M25 -> 0 | S25: 可可 | T25: =SUMIF(P8:P102,"<>公關品",H8:H100) -> 0 | U25: =SUMIF(P8:P102,"公關品",I8:I100) -> 0 | V25: =T19+(T21*4)+T25 -> 0 | X25: 4入紙箱 | Z25: =Y25*5 -> 0
K26: =SUM(SUM(B26:F26)*360,SUM(G26:J26)*90) -> 0 | N26: =K26+L26-M26 -> 0 | S26: 伯爵 | T26: =SUMIF(P9:P103,"<>公關品",I8:I100) -> 0 | U26: =SUMIF(P8:P102,"公關品",I8:I100) -> 0 | V26: =T19+(T22*4)+T26 -> 0 | X26: 10入紙箱
K27: =SUM(SUM(B27:F27)*360,SUM(G27:J27)*90) -> 0 | N27: =K27+L27-M27 -> 0 | S27: 抹茶 | T27: =SUMIF(P8:P102,"<>公關品",J8:J100) -> 0 | U27: =SUMIF(P9:P103,"公關品",J8:J100) -> 0 | V27: =T19+(T23*4)+T27 -> 0 | X27: 膠帶
K28: =SUM(SUM(B28:F28)*360,SUM(G28:J28)*90) -> 0 | N28: =K28+L28-M28 -> 0
K29: =SUM(SUM(B29:F29)*360,SUM(G29:J29)*90) -> 0 | N29: =K29+L29-M29 -> 0
K30: =SUM(SUM(B30:F30)*360,SUM(G30:J30)*90) -> 0 | N30: =K30+L30-M30 -> 0 | R30: 產能及庫存 | AB30: 今日公關品總結
K31: =SUM(SUM(B31:F31)*360,SUM(G31:J31)*90) -> 0 | N31: =K31+L31-M31 -> 0 | AB31: 總禮盒數 | AC31: =SUM(U19:U23) -> 0
K32: =SUM(SUM(B32:F32)*360,SUM(G32:J32)*90) -> 0 | N32: =K32+L32-M32 -> 0 | R32: 品項 | S32: 原庫存 | T32: 預計產量 | U32: 實際產量 | V32: 耗損 | W32: 實際銷售量 | Y32: 今日庫存 | Z32: 總損耗率 | AB32: 總顆數 | AC32: =SUM(AC33:AC36) -> 0
K33: =SUM(SUM(B33:F33)*360,SUM(G33:J33)*90) -> 0 | N33: =K33+L33-M33 -> 0 | R33: 原味 | S33: ='18'!Y33 -> 0 | V33: =SUMIF(R40:R55,"原味",S40:S55) -> 0 | W33: =V24+U24+U19+U20*4 -> 0 | Y33: =S33+U33-V33-W33 -> 0 | Z33: =IFERROR((V33/(U33+S33))," ") | AB33: 原味 | AC33: =U24+U19+U20*4 -> 0
K34: =SUM(SUM(B34:F34)*360,SUM(G34:J34)*90) -> 0 | N34: =K34+L34-M34 -> 0 | R34: 可可 | S34: ='18'!Y34 -> 0 | V34: =SUMIF(R41:R55,"可可",S41:S55) -> 0 | W34: =V25+U25+U19+U21*4 -> 0 | Y34: =S34+U34-V34-W34 -> 0 | Z34: =IFERROR((V34/(U34+S34))," ") | AB34: 可可 | AC34: =U25+U19+U21*4 -> 0
K35: =SUM(SUM(B35:F35)*360,SUM(G35:J35)*90) -> 0 | N35: =K35+L35-M35 -> 0 | R35: 伯爵 | S35: ='18'!Y35 -> 0 | V35: =SUMIF(R41:R55,"伯爵",S41:S55) -> 0 | W35: =V26+U26+U19+U22*4 -> 0 | Y35: =S35+U35-V35-W35 -> 0 | Z35: =IFERROR((V35/(U35+S35))," ") | AB35: 伯爵 | AC35: =U26+U19+U22*4 -> 0
K36: =SUM(SUM(B36:F36)*360,SUM(G36:J36)*90) -> 0 | N36: =K36+L36-M36 -> 0 | R36: 抹茶 | S36: ='18'!Y36 -> 0 | V36: =SUMIF(R41:R55,"抹茶",S41:S55) -> 0 | W36: =V27+U27+U19+U23*4 -> 0 | Y36: =S36+U36-V36-W36 -> 0 | Z36: =IFERROR((V36/(U36+S36))," ") | AB36: 抹茶 | AC36: =U27+U19+U23*4 -> 0
K37: =SUM(SUM(B37:F37)*360,SUM(G37:J37)*90) -> 0 | N37: =K37+L37-M37 -> 0
K38: =SUM(SUM(B38:F38)*360,SUM(G38:J38)*90) -> 0 | N38: =K38+L38-M38 -> 0 | R38: 損耗原因
K39: =SUM(SUM(B39:F39)*360,SUM(G39:J39)*90) -> 0 | N39: =K39+L39-M39 -> 0
K40: =SUM(SUM(B40:F40)*360,SUM(G40:J40)*90) -> 0 | N40: =K40+L40-M40 -> 0 | R40: 品項 | S40: 數量 | T40: 類別 | U40: 原因
K41: =SUM(SUM(B41:F41)*360,SUM(G41:J41)*90) -> 0 | N41: =K41+L41-M41 -> 0
K42: =SUM(SUM(B42:F42)*360,SUM(G42:J42)*90) -> 0 | N42: =K42+L42-M42 -> 0
K43: =SUM(SUM(B43:F43)*360,SUM(G43:J43)*90) -> 0 | N43: =K43+L43-M43 -> 0
K44: =SUM(SUM(B44:F44)*360,SUM(G44:J44)*90) -> 0 | N44: =K44+L44-M44 -> 0
K45: =SUM(SUM(B45:F45)*360,SUM(G45:J45)*90) -> 0 | N45: =K45+L45-M45 -> 0
K46: =SUM(SUM(B46:F46)*360,SUM(G46:J46)*90) -> 0 | N46: =K46+L46-M46 -> 0
K47: =SUM(SUM(B47:F47)*360,SUM(G47:J47)*90) -> 0 | N47: =K47+L47-M47 -> 0
K48: =SUM(SUM(B48:F48)*360,SUM(G48:J48)*90) -> 0 | N48: =K48+L48-M48 -> 0
K49: =SUM(SUM(B49:F49)*360,SUM(G49:J49)*90) -> 0 | N49: =K49+L49-M49 -> 0
K50: =SUM(SUM(B50:F50)*360,SUM(G50:J50)*90) -> 0 | N50: =K50+L50-M50 -> 0
K51: =SUM(SUM(B51:F51)*360,SUM(G51:J51)*90) -> 0 | N51: =K51+L51-M51 -> 0
K52: =SUM(SUM(B52:F52)*360,SUM(G52:J52)*90) -> 0 | N52: =K52+L52-M52 -> 0
... K56: =SUM(SUM(B56:F56)*360,SUM(G56:J56)*90) -> 0 | N56: =K56+L56-M56 -> 0
K57: =SUM(SUM(B57:F57)*360,SUM(G57:J57)*90) -> 0 | N57: =K57+L57-M57 -> 0 | R57: 備註
K58: =SUM(SUM(B58:F58)*360,SUM(G58:J58)*90) -> 0 | N58: =K58+L58-M58 -> 0
K59: =SUM(SUM(B59:F59)*360,SUM(G59:J59)*90) -> 0 | N59: =K59+L59-M59 -> 0
K60: =SUM(SUM(B60:F60)*360,SUM(G60:J60)*90) -> 0 | N60: =K60+L60-M60 -> 0
K61: =SUM(SUM(B61:F61)*360,SUM(G61:J61)*90) -> 0 | N61: =K61+L61-M61 -> 0
K62: =SUM(SUM(B62:F62)*360,SUM(G62:J62)*90) -> 0 | N62: =K62+L62-M62 -> 0
K63: =SUM(SUM(B63:F63)*360,SUM(G63:J63)*90) -> 0 | N63: =K63+L63-M63 -> 0
K64: =SUM(SUM(B64:F64)*360,SUM(G64:J64)*90) -> 0 | N64: =K64+L64-M64 -> 0
K65: =SUM(SUM(B65:F65)*360,SUM(G65:J65)*90) -> 0 | N65: =K65+L65-M65 -> 0
K66: =SUM(SUM(B66:F66)*360,SUM(G66:J66)*90) -> 0 | N66: =K66+L66-M66 -> 0
K67: =SUM(SUM(B67:F67)*360,SUM(G67:J67)*90) -> 0 | N67: =K67+L67-M67 -> 0
K68: =SUM(SUM(B68:F68)*360,SUM(G68:J68)*90) -> 0 | N68: =K68+L68-M68 -> 0
K69: =SUM(SUM(B69:F69)*360,SUM(G69:J69)*90) -> 0 | N69: =K69+L69-M69 -> 0
... K101: =SUM(SUM(B101:F101)*360,SUM(G101:J101)*90) -> 0 | N101: =K101+L101-M101 -> 0

Sheet 20
A1: 日報表
A5: 銷售明細 | R5: 總結
A6: 類別 | B6: 禮盒 | G6: 單顆 | K6: 金額
A7: 購買人 | B7: 綜合 | C7: 原味 | D7: 可可 | E7: 伯爵 | F7: 抹茶 | G7: 原味. | H7: 可可. | I7: 伯爵. | J7: 抹茶. | K7: 金額 | L7: 運費 | M7: 折讓金額 | N7: 實收金額 | O7: 欄1 | P7: 備註
K8: =SUM(SUM(B8:F8)*360,SUM(G8:J8)*90) -> 0 | N8: =K8+L8-M8 -> 0 | R8: 金流 | X8: 應收帳款 | AB8: 今日未結帳款清單 | AC8: 今日銷帳清單
K9: =SUM(SUM(B9:F9)*360,SUM(G9:J9)*90) -> 0 | N9: =K9+L9-M9 -> 0 | R9: 營業總額 | T9: 運費 | U9: =SUMIF(表格1_3345152535455565758596061626364656667[欄1],"<>公關品",表格1_3345152535455565758596061626364656667[運費]) -> 0 | X9: 累積未結 | Y9: =INDEX('19'!Y12:Z13,1,1) -> 31984 | AB9: {=_xlfn.LET(_xlpm.unpaid,_xlfn.UNIQUE(_xlfn._xlws.FILTER(A8:A100,O8:O100="未結帳款","今日無欠款")),IF(_xlpm.unpaid="今日無欠款","今日無欠款",_xlpm.unpaid&"："&SUMIFS(N8:N100,A8:A100,_xlpm.unpaid,O8:O100,"未結帳款")))} -> 今日無欠款 | AC9: {=_xlfn.LET(_xlpm.paid,_xlfn.UNIQUE(_xlfn._xlws.FILTER(A8:A100,P8:P100="銷帳","今日無銷帳")),IF(_xlpm.paid="今日無銷帳","今日無銷帳",_xlpm.paid&"："&SUMIFS(N8:N100,A8:A100,_xlpm.paid,P8:P100,"銷帳")))} -> 今日無銷帳
K10: =SUM(SUM(B10:F10)*360,SUM(G10:J10)*90) -> 0 | N10: =K10+L10-M10 -> 0 | R10: =SUM(K8:K101)-V15 -> 0 | T10: 折讓 | U10: =SUM(M8:M101) -> 0 | X10: 今日未結 | Y10: =U15 -> 0
K11: =SUM(SUM(B11:F11)*360,SUM(G11:J11)*90) -> 0 | N11: =K11+L11-M11 -> 0 | R11: 營業額 | T11: 公關品 | U11: =SUMIF(P8:P100,"公關品",K8:K103) -> 0 | X11: 今日回款 | Y11: =V15 -> 0
K12: =SUM(SUM(B12:F12)*360,SUM(G12:J12)*90) -> 0 | N12: =K12+L12-M12 -> 0 | R12: =R10-U10-U11 -> 0 | T12: 應收 | V12: 實收 | X12: 剩餘未結 | Y12: =Y9+Y10-Y11 -> 31984
K13: =SUM(SUM(B13:F13)*360,SUM(G13:J13)*90) -> 0 | N13: =K13+L13-M13 -> 0 | T13: 匯款 | U13: =SUMIF(O8:O101,"匯款",N8:N101) -> 0
K14: =SUM(SUM(B14:F14)*360,SUM(G14:J14)*90) -> 0 | N14: =K14+L14-M14 -> 0 | T14: 現金 | U14: =SUMIF(O8:O102,"現金",N8:N102) -> 0
K15: =SUM(SUM(B15:F15)*360,SUM(G15:J15)*90) -> 0 | N15: =K15+L15-M15 -> 0 | T15: 未結帳款 | U15: =SUMIF(O8:O102,"未結帳款",N8:N103) -> 0 | V15: =SUMIF(P8:P100,"銷帳",N8:N100) -> 0
K16: =SUM(SUM(B16:F16)*360,SUM(G16:J16)*90) -> 0 | N16: =K16+L16-M16 -> 0 | T16: 銷帳 | X16: 物流
K17: =SUM(SUM(B17:F17)*360,SUM(G17:J17)*90) -> 0 | N17: =K17+L17-M17 -> 0 | R17: 商品銷售量 | X17: 運費實收 | Y17: =U9 -> 0
K18: =SUM(SUM(B18:F18)*360,SUM(G18:J18)*90) -> 0 | N18: =K18+L18-M18 -> 0 | T18: 販售量 | U18: 公關品 | V18: 總盒數 | X18: 運費實支
K19: =SUM(SUM(B19:F19)*360,SUM(G19:J19)*90) -> 0 | N19: =K19+L19-M19 -> 0 | R19: 禮盒 | S19: 綜合 | T19: =SUMIF(P8:P102,"<>公關品",B8:B100) -> 0 | U19: =SUMIF(P8:P102,"公關品",B8:B100) -> 0 | V19: =SUM(T19:T23,U19) -> 0 | X19: 公關運費 | Y19: =SUMIF(P8:P100,"公關品",L8:L100) -> 0
K20: =SUM(SUM(B20:F20)*360,SUM(G20:J20)*90) -> 0 | N20: =K20+L20-M20 -> 0 | S20: 原味 | T20: =SUMIF(P8:P102,"<>公關品",C8:C100) -> 0 | U20: =SUMIF(P8:P102,"公關品",C8:C100) -> 0 | V20: 總顆數 | X20: 物流包材 | Y20: =SUM(Z24:Z27) -> 0
K21: =SUM(SUM(B21:F21)*360,SUM(G21:J21)*90) -> 0 | N21: =K21+L21-M21 -> 0 | S21: 可可 | T21: =SUMIF(P8:P104,"<>公關品",D8:D102) -> 0 | U21: =SUMIF(P8:P102,"公關品",D8:D100) -> 0 | X21: 成本差額 | Y21: =Y17-Y18-Y20+Y19 -> 0
K22: =SUM(SUM(B22:F22)*360,SUM(G22:J22)*90) -> 0 | N22: =K22+L22-M22 -> 0 | S22: 伯爵 | T22: =SUMIF(P8:P102,"<>公關品",E8:E100) -> 0 | U22: =SUMIF(P8:P102,"公關品",E8:E100) -> 0 | X22: 物流包材
K23: =SUM(SUM(B23:F23)*360,SUM(G23:J23)*90) -> 0 | N23: =K23+L23-M23 -> 0 | S23: 抹茶 | T23: =SUMIF(P8:P102,"<>公關品",F8:F100) -> 0 | U23: =SUMIF(P8:P102,"公關品",F8:F100) -> 0 | X23: 種類 | Y23: 數量 | Z23: 總額
K24: =SUM(SUM(B24:F24)*360,SUM(G24:J24)*90) -> 0 | N24: =K24+L24-M24 -> 0 | R24: 單顆 | S24: 原味 | T24: =SUMIF(P9:P103,"<>公關品",G8:G100) -> 0 | U24: =SUMIF(P8:P102,"公關品",G8:G100) -> 0 | V24: =T19+(T20*4)+T24 -> 0 | X24: 2入紙箱
K25: =SUM(SUM(B25:F25)*360,SUM(G25:J25)*90) -> 0 | N25: =K25+L25-M25 -> 0 | S25: 可可 | T25: =SUMIF(P8:P102,"<>公關品",H8:H100) -> 0 | U25: =SUMIF(P8:P102,"公關品",I8:I100) -> 0 | V25: =T19+(T21*4)+T25 -> 0 | X25: 4入紙箱 | Z25: =Y25*5 -> 0
K26: =SUM(SUM(B26:F26)*360,SUM(G26:J26)*90) -> 0 | N26: =K26+L26-M26 -> 0 | S26: 伯爵 | T26: =SUMIF(P9:P103,"<>公關品",I8:I100) -> 0 | U26: =SUMIF(P8:P102,"公關品",I8:I100) -> 0 | V26: =T19+(T22*4)+T26 -> 0 | X26: 10入紙箱
K27: =SUM(SUM(B27:F27)*360,SUM(G27:J27)*90) -> 0 | N27: =K27+L27-M27 -> 0 | S27: 抹茶 | T27: =SUMIF(P8:P102,"<>公關品",J8:J100) -> 0 | U27: =SUMIF(P9:P103,"公關品",J8:J100) -> 0 | V27: =T19+(T23*4)+T27 -> 0 | X27: 膠帶
K28: =SUM(SUM(B28:F28)*360,SUM(G28:J28)*90) -> 0 | N28: =K28+L28-M28 -> 0
K29: =SUM(SUM(B29:F29)*360,SUM(G29:J29)*90) -> 0 | N29: =K29+L29-M29 -> 0
K30: =SUM(SUM(B30:F30)*360,SUM(G30:J30)*90) -> 0 | N30: =K30+L30-M30 -> 0 | R30: 產能及庫存 | AB30: 今日公關品總結
K31: =SUM(SUM(B31:F31)*360,SUM(G31:J31)*90) -> 0 | N31: =K31+L31-M31 -> 0 | AB31: 總禮盒數 | AC31: =SUM(U19:U23) -> 0
K32: =SUM(SUM(B32:F32)*360,SUM(G32:J32)*90) -> 0 | N32: =K32+L32-M32 -> 0 | R32: 品項 | S32: 原庫存 | T32: 預計產量 | U32: 實際產量 | V32: 耗損 | W32: 實際銷售量 | Y32: 今日庫存 | Z32: 總損耗率 | AB32: 總顆數 | AC32: =SUM(AC33:AC36) -> 0
K33: =SUM(SUM(B33:F33)*360,SUM(G33:J33)*90) -> 0 | N33: =K33+L33-M33 -> 0 | R33: 原味 | S33: ='19'!Y33 -> 0 | V33: =SUMIF(R40:R55,"原味",S40:S55) -> 0 | W33: =V24+U24+U19+U20*4 -> 0 | Y33: =S33+U33-V33-W33 -> 0 | Z33: =IFERROR((V33/(U33+S33))," ") | AB33: 原味 | AC33: =U24+U19+U20*4 -> 0
K34: =SUM(SUM(B34:F34)*360,SUM(G34:J34)*90) -> 0 | N34: =K34+L34-M34 -> 0 | R34: 可可 | S34: ='19'!Y34 -> 0 | V34: =SUMIF(R41:R55,"可可",S41:S55) -> 0 | W34: =V25+U25+U19+U21*4 -> 0 | Y34: =S34+U34-V34-W34 -> 0 | Z34: =IFERROR((V34/(U34+S34))," ") | AB34: 可可 | AC34: =U25+U19+U21*4 -> 0
K35: =SUM(SUM(B35:F35)*360,SUM(G35:J35)*90) -> 0 | N35: =K35+L35-M35 -> 0 | R35: 伯爵 | S35: ='19'!Y35 -> 0 | V35: =SUMIF(R41:R55,"伯爵",S41:S55) -> 0 | W35: =V26+U26+U19+U22*4 -> 0 | Y35: =S35+U35-V35-W35 -> 0 | Z35: =IFERROR((V35/(U35+S35))," ") | AB35: 伯爵 | AC35: =U26+U19+U22*4 -> 0
K36: =SUM(SUM(B36:F36)*360,SUM(G36:J36)*90) -> 0 | N36: =K36+L36-M36 -> 0 | R36: 抹茶 | S36: ='19'!Y36 -> 0 | V36: =SUMIF(R41:R55,"抹茶",S41:S55) -> 0 | W36: =V27+U27+U19+U23*4 -> 0 | Y36: =S36+U36-V36-W36 -> 0 | Z36: =IFERROR((V36/(U36+S36))," ") | AB36: 抹茶 | AC36: =U27+U19+U23*4 -> 0
K37: =SUM(SUM(B37:F37)*360,SUM(G37:J37)*90) -> 0 | N37: =K37+L37-M37 -> 0
K38: =SUM(SUM(B38:F38)*360,SUM(G38:J38)*90) -> 0 | N38: =K38+L38-M38 -> 0 | R38: 損耗原因
K39: =SUM(SUM(B39:F39)*360,SUM(G39:J39)*90) -> 0 | N39: =K39+L39-M39 -> 0
K40: =SUM(SUM(B40:F40)*360,SUM(G40:J40)*90) -> 0 | N40: =K40+L40-M40 -> 0 | R40: 品項 | S40: 數量 | T40: 類別 | U40: 原因
K41: =SUM(SUM(B41:F41)*360,SUM(G41:J41)*90) -> 0 | N41: =K41+L41-M41 -> 0
K42: =SUM(SUM(B42:F42)*360,SUM(G42:J42)*90) -> 0 | N42: =K42+L42-M42 -> 0
K43: =SUM(SUM(B43:F43)*360,SUM(G43:J43)*90) -> 0 | N43: =K43+L43-M43 -> 0
K44: =SUM(SUM(B44:F44)*360,SUM(G44:J44)*90) -> 0 | N44: =K44+L44-M44 -> 0
K45: =SUM(SUM(B45:F45)*360,SUM(G45:J45)*90) -> 0 | N45: =K45+L45-M45 -> 0
K46: =SUM(SUM(B46:F46)*360,SUM(G46:J46)*90) -> 0 | N46: =K46+L46-M46 -> 0
K47: =SUM(SUM(B47:F47)*360,SUM(G47:J47)*90) -> 0 | N47: =K47+L47-M47 -> 0
K48: =SUM(SUM(B48:F48)*360,SUM(G48:J48)*90) -> 0 | N48: =K48+L48-M48 -> 0
K49: =SUM(SUM(B49:F49)*360,SUM(G49:J49)*90) -> 0 | N49: =K49+L49-M49 -> 0
K50: =SUM(SUM(B50:F50)*360,SUM(G50:J50)*90) -> 0 | N50: =K50+L50-M50 -> 0
K51: =SUM(SUM(B51:F51)*360,SUM(G51:J51)*90) -> 0 | N51: =K51+L51-M51 -> 0
K52: =SUM(SUM(B52:F52)*360,SUM(G52:J52)*90) -> 0 | N52: =K52+L52-M52 -> 0
... K56: =SUM(SUM(B56:F56)*360,SUM(G56:J56)*90) -> 0 | N56: =K56+L56-M56 -> 0
K57: =SUM(SUM(B57:F57)*360,SUM(G57:J57)*90) -> 0 | N57: =K57+L57-M57 -> 0 | R57: 備註
K58: =SUM(SUM(B58:F58)*360,SUM(G58:J58)*90) -> 0 | N58: =K58+L58-M58 -> 0
K59: =SUM(SUM(B59:F59)*360,SUM(G59:J59)*90) -> 0 | N59: =K59+L59-M59 -> 0
K60: =SUM(SUM(B60:F60)*360,SUM(G60:J60)*90) -> 0 | N60: =K60+L60-M60 -> 0
K61: =SUM(SUM(B61:F61)*360,SUM(G61:J61)*90) -> 0 | N61: =K61+L61-M61 -> 0
K62: =SUM(SUM(B62:F62)*360,SUM(G62:J62)*90) -> 0 | N62: =K62+L62-M62 -> 0
K63: =SUM(SUM(B63:F63)*360,SUM(G63:J63)*90) -> 0 | N63: =K63+L63-M63 -> 0
K64: =SUM(SUM(B64:F64)*360,SUM(G64:J64)*90) -> 0 | N64: =K64+L64-M64 -> 0
K65: =SUM(SUM(B65:F65)*360,SUM(G65:J65)*90) -> 0 | N65: =K65+L65-M65 -> 0
K66: =SUM(SUM(B66:F66)*360,SUM(G66:J66)*90) -> 0 | N66: =K66+L66-M66 -> 0
K67: =SUM(SUM(B67:F67)*360,SUM(G67:J67)*90) -> 0 | N67: =K67+L67-M67 -> 0
K68: =SUM(SUM(B68:F68)*360,SUM(G68:J68)*90) -> 0 | N68: =K68+L68-M68 -> 0
K69: =SUM(SUM(B69:F69)*360,SUM(G69:J69)*90) -> 0 | N69: =K69+L69-M69 -> 0
... K101: =SUM(SUM(B101:F101)*360,SUM(G101:J101)*90) -> 0 | N101: =K101+L101-M101 -> 0

Sheet 21
A1: 日報表
A5: 銷售明細 | R5: 總結
A6: 類別 | B6: 禮盒 | G6: 單顆 | K6: 金額
A7: 購買人 | B7: 綜合 | C7: 原味 | D7: 可可 | E7: 伯爵 | F7: 抹茶 | G7: 原味. | H7: 可可. | I7: 伯爵. | J7: 抹茶. | K7: 金額 | L7: 運費 | M7: 折讓金額 | N7: 實收金額 | O7: 欄1 | P7: 備註
K8: =SUM(SUM(B8:F8)*360,SUM(G8:J8)*90) -> 0 | N8: =K8+L8-M8 -> 0 | R8: 金流 | X8: 應收帳款 | AB8: 今日未結帳款清單 | AC8: 今日銷帳清單
K9: =SUM(SUM(B9:F9)*360,SUM(G9:J9)*90) -> 0 | N9: =K9+L9-M9 -> 0 | R9: 營業總額 | T9: 運費 | U9: =SUMIF(表格1_334515253545556575859606162636465666768[欄1],"<>公關品",表格1_334515253545556575859606162636465666768[運費]) -> 0 | X9: 累積未結 | Y9: =INDEX('20'!Y12:Z13,1,1) -> 31984 | AB9: {=_xlfn.LET(_xlpm.unpaid,_xlfn.UNIQUE(_xlfn._xlws.FILTER(A8:A100,O8:O100="未結帳款","今日無欠款")),IF(_xlpm.unpaid="今日無欠款","今日無欠款",_xlpm.unpaid&"："&SUMIFS(N8:N100,A8:A100,_xlpm.unpaid,O8:O100,"未結帳款")))} -> 今日無欠款 | AC9: {=_xlfn.LET(_xlpm.paid,_xlfn.UNIQUE(_xlfn._xlws.FILTER(A8:A100,P8:P100="銷帳","今日無銷帳")),IF(_xlpm.paid="今日無銷帳","今日無銷帳",_xlpm.paid&"："&SUMIFS(N8:N100,A8:A100,_xlpm.paid,P8:P100,"銷帳")))} -> 今日無銷帳
K10: =SUM(SUM(B10:F10)*360,SUM(G10:J10)*90) -> 0 | N10: =K10+L10-M10 -> 0 | R10: =SUM(K8:K101)-V15 -> 0 | T10: 折讓 | U10: =SUM(M8:M101) -> 0 | X10: 今日未結 | Y10: =U15 -> 0
K11: =SUM(SUM(B11:F11)*360,SUM(G11:J11)*90) -> 0 | N11: =K11+L11-M11 -> 0 | R11: 營業額 | T11: 公關品 | U11: =SUMIF(P8:P100,"公關品",K8:K103) -> 0 | X11: 今日回款 | Y11: =V15 -> 0
K12: =SUM(SUM(B12:F12)*360,SUM(G12:J12)*90) -> 0 | N12: =K12+L12-M12 -> 0 | R12: =R10-U10-U11 -> 0 | T12: 應收 | V12: 實收 | X12: 剩餘未結 | Y12: =Y9+Y10-Y11 -> 31984
K13: =SUM(SUM(B13:F13)*360,SUM(G13:J13)*90) -> 0 | N13: =K13+L13-M13 -> 0 | T13: 匯款 | U13: =SUMIF(O8:O101,"匯款",N8:N101) -> 0
K14: =SUM(SUM(B14:F14)*360,SUM(G14:J14)*90) -> 0 | N14: =K14+L14-M14 -> 0 | T14: 現金 | U14: =SUMIF(O8:O102,"現金",N8:N102) -> 0
K15: =SUM(SUM(B15:F15)*360,SUM(G15:J15)*90) -> 0 | N15: =K15+L15-M15 -> 0 | T15: 未結帳款 | U15: =SUMIF(O8:O102,"未結帳款",N8:N103) -> 0 | V15: =SUMIF(P8:P100,"銷帳",N8:N100) -> 0
K16: =SUM(SUM(B16:F16)*360,SUM(G16:J16)*90) -> 0 | N16: =K16+L16-M16 -> 0 | T16: 銷帳 | X16: 物流
K17: =SUM(SUM(B17:F17)*360,SUM(G17:J17)*90) -> 0 | N17: =K17+L17-M17 -> 0 | R17: 商品銷售量 | X17: 運費實收 | Y17: =U9 -> 0
K18: =SUM(SUM(B18:F18)*360,SUM(G18:J18)*90) -> 0 | N18: =K18+L18-M18 -> 0 | T18: 販售量 | U18: 公關品 | V18: 總盒數 | X18: 運費實支
K19: =SUM(SUM(B19:F19)*360,SUM(G19:J19)*90) -> 0 | N19: =K19+L19-M19 -> 0 | R19: 禮盒 | S19: 綜合 | T19: =SUMIF(P8:P102,"<>公關品",B8:B100) -> 0 | U19: =SUMIF(P8:P102,"公關品",B8:B100) -> 0 | V19: =SUM(T19:T23,U19) -> 0 | X19: 公關運費 | Y19: =SUMIF(P8:P100,"公關品",L8:L100) -> 0
K20: =SUM(SUM(B20:F20)*360,SUM(G20:J20)*90) -> 0 | N20: =K20+L20-M20 -> 0 | S20: 原味 | T20: =SUMIF(P8:P102,"<>公關品",C8:C100) -> 0 | U20: =SUMIF(P8:P102,"公關品",C8:C100) -> 0 | V20: 總顆數 | X20: 物流包材 | Y20: =SUM(Z24:Z27) -> 0
K21: =SUM(SUM(B21:F21)*360,SUM(G21:J21)*90) -> 0 | N21: =K21+L21-M21 -> 0 | S21: 可可 | T21: =SUMIF(P8:P104,"<>公關品",D8:D102) -> 0 | U21: =SUMIF(P8:P102,"公關品",D8:D100) -> 0 | X21: 成本差額 | Y21: =Y17-Y18-Y20+Y19 -> 0
K22: =SUM(SUM(B22:F22)*360,SUM(G22:J22)*90) -> 0 | N22: =K22+L22-M22 -> 0 | S22: 伯爵 | T22: =SUMIF(P8:P102,"<>公關品",E8:E100) -> 0 | U22: =SUMIF(P8:P102,"公關品",E8:E100) -> 0 | X22: 物流包材
K23: =SUM(SUM(B23:F23)*360,SUM(G23:J23)*90) -> 0 | N23: =K23+L23-M23 -> 0 | S23: 抹茶 | T23: =SUMIF(P8:P102,"<>公關品",F8:F100) -> 0 | U23: =SUMIF(P8:P102,"公關品",F8:F100) -> 0 | X23: 種類 | Y23: 數量 | Z23: 總額
K24: =SUM(SUM(B24:F24)*360,SUM(G24:J24)*90) -> 0 | N24: =K24+L24-M24 -> 0 | R24: 單顆 | S24: 原味 | T24: =SUMIF(P9:P103,"<>公關品",G8:G100) -> 0 | U24: =SUMIF(P8:P102,"公關品",G8:G100) -> 0 | V24: =T19+(T20*4)+T24 -> 0 | X24: 2入紙箱
K25: =SUM(SUM(B25:F25)*360,SUM(G25:J25)*90) -> 0 | N25: =K25+L25-M25 -> 0 | S25: 可可 | T25: =SUMIF(P8:P102,"<>公關品",H8:H100) -> 0 | U25: =SUMIF(P8:P102,"公關品",I8:I100) -> 0 | V25: =T19+(T21*4)+T25 -> 0 | X25: 4入紙箱 | Z25: =Y25*5 -> 0
K26: =SUM(SUM(B26:F26)*360,SUM(G26:J26)*90) -> 0 | N26: =K26+L26-M26 -> 0 | S26: 伯爵 | T26: =SUMIF(P9:P103,"<>公關品",I8:I100) -> 0 | U26: =SUMIF(P8:P102,"公關品",I8:I100) -> 0 | V26: =T19+(T22*4)+T26 -> 0 | X26: 10入紙箱
K27: =SUM(SUM(B27:F27)*360,SUM(G27:J27)*90) -> 0 | N27: =K27+L27-M27 -> 0 | S27: 抹茶 | T27: =SUMIF(P8:P102,"<>公關品",J8:J100) -> 0 | U27: =SUMIF(P9:P103,"公關品",J8:J100) -> 0 | V27: =T19+(T23*4)+T27 -> 0 | X27: 膠帶
K28: =SUM(SUM(B28:F28)*360,SUM(G28:J28)*90) -> 0 | N28: =K28+L28-M28 -> 0
K29: =SUM(SUM(B29:F29)*360,SUM(G29:J29)*90) -> 0 | N29: =K29+L29-M29 -> 0
K30: =SUM(SUM(B30:F30)*360,SUM(G30:J30)*90) -> 0 | N30: =K30+L30-M30 -> 0 | R30: 產能及庫存 | AB30: 今日公關品總結
K31: =SUM(SUM(B31:F31)*360,SUM(G31:J31)*90) -> 0 | N31: =K31+L31-M31 -> 0 | AB31: 總禮盒數 | AC31: =SUM(U19:U23) -> 0
K32: =SUM(SUM(B32:F32)*360,SUM(G32:J32)*90) -> 0 | N32: =K32+L32-M32 -> 0 | R32: 品項 | S32: 原庫存 | T32: 預計產量 | U32: 實際產量 | V32: 耗損 | W32: 實際銷售量 | Y32: 今日庫存 | Z32: 總損耗率 | AB32: 總顆數 | AC32: =SUM(AC33:AC36) -> 0
K33: =SUM(SUM(B33:F33)*360,SUM(G33:J33)*90) -> 0 | N33: =K33+L33-M33 -> 0 | R33: 原味 | S33: ='20'!Y33 -> 0 | V33: =SUMIF(R40:R55,"原味",S40:S55) -> 0 | W33: =V24+U24+U19+U20*4 -> 0 | Y33: =S33+U33-V33-W33 -> 0 | Z33: =IFERROR((V33/(U33+S33))," ") | AB33: 原味 | AC33: =U24+U19+U20*4 -> 0
K34: =SUM(SUM(B34:F34)*360,SUM(G34:J34)*90) -> 0 | N34: =K34+L34-M34 -> 0 | R34: 可可 | S34: ='20'!Y34 -> 0 | V34: =SUMIF(R41:R55,"可可",S41:S55) -> 0 | W34: =V25+U25+U19+U21*4 -> 0 | Y34: =S34+U34-V34-W34 -> 0 | Z34: =IFERROR((V34/(U34+S34))," ") | AB34: 可可 | AC34: =U25+U19+U21*4 -> 0
K35: =SUM(SUM(B35:F35)*360,SUM(G35:J35)*90) -> 0 | N35: =K35+L35-M35 -> 0 | R35: 伯爵 | S35: ='20'!Y35 -> 0 | V35: =SUMIF(R41:R55,"伯爵",S41:S55) -> 0 | W35: =V26+U26+U19+U22*4 -> 0 | Y35: =S35+U35-V35-W35 -> 0 | Z35: =IFERROR((V35/(U35+S35))," ") | AB35: 伯爵 | AC35: =U26+U19+U22*4 -> 0
K36: =SUM(SUM(B36:F36)*360,SUM(G36:J36)*90) -> 0 | N36: =K36+L36-M36 -> 0 | R36: 抹茶 | S36: ='20'!Y36 -> 0 | V36: =SUMIF(R41:R55,"抹茶",S41:S55) -> 0 | W36: =V27+U27+U19+U23*4 -> 0 | Y36: =S36+U36-V36-W36 -> 0 | Z36: =IFERROR((V36/(U36+S36))," ") | AB36: 抹茶 | AC36: =U27+U19+U23*4 -> 0
K37: =SUM(SUM(B37:F37)*360,SUM(G37:J37)*90) -> 0 | N37: =K37+L37-M37 -> 0
K38: =SUM(SUM(B38:F38)*360,SUM(G38:J38)*90) -> 0 | N38: =K38+L38-M38 -> 0 | R38: 損耗原因
K39: =SUM(SUM(B39:F39)*360,SUM(G39:J39)*90) -> 0 | N39: =K39+L39-M39 -> 0
K40: =SUM(SUM(B40:F40)*360,SUM(G40:J40)*90) -> 0 | N40: =K40+L40-M40 -> 0 | R40: 品項 | S40: 數量 | T40: 類別 | U40: 原因
K41: =SUM(SUM(B41:F41)*360,SUM(G41:J41)*90) -> 0 | N41: =K41+L41-M41 -> 0
K42: =SUM(SUM(B42:F42)*360,SUM(G42:J42)*90) -> 0 | N42: =K42+L42-M42 -> 0
K43: =SUM(SUM(B43:F43)*360,SUM(G43:J43)*90) -> 0 | N43: =K43+L43-M43 -> 0
K44: =SUM(SUM(B44:F44)*360,SUM(G44:J44)*90) -> 0 | N44: =K44+L44-M44 -> 0
K45: =SUM(SUM(B45:F45)*360,SUM(G45:J45)*90) -> 0 | N45: =K45+L45-M45 -> 0
K46: =SUM(SUM(B46:F46)*360,SUM(G46:J46)*90) -> 0 | N46: =K46+L46-M46 -> 0
K47: =SUM(SUM(B47:F47)*360,SUM(G47:J47)*90) -> 0 | N47: =K47+L47-M47 -> 0
K48: =SUM(SUM(B48:F48)*360,SUM(G48:J48)*90) -> 0 | N48: =K48+L48-M48 -> 0
K49: =SUM(SUM(B49:F49)*360,SUM(G49:J49)*90) -> 0 | N49: =K49+L49-M49 -> 0
K50: =SUM(SUM(B50:F50)*360,SUM(G50:J50)*90) -> 0 | N50: =K50+L50-M50 -> 0
K51: =SUM(SUM(B51:F51)*360,SUM(G51:J51)*90) -> 0 | N51: =K51+L51-M51 -> 0
K52: =SUM(SUM(B52:F52)*360,SUM(G52:J52)*90) -> 0 | N52: =K52+L52-M52 -> 0
... K56: =SUM(SUM(B56:F56)*360,SUM(G56:J56)*90) -> 0 | N56: =K56+L56-M56 -> 0
K57: =SUM(SUM(B57:F57)*360,SUM(G57:J57)*90) -> 0 | N57: =K57+L57-M57 -> 0 | R57: 備註
K58: =SUM(SUM(B58:F58)*360,SUM(G58:J58)*90) -> 0 | N58: =K58+L58-M58 -> 0
K59: =SUM(SUM(B59:F59)*360,SUM(G59:J59)*90) -> 0 | N59: =K59+L59-M59 -> 0
K60: =SUM(SUM(B60:F60)*360,SUM(G60:J60)*90) -> 0 | N60: =K60+L60-M60 -> 0
K61: =SUM(SUM(B61:F61)*360,SUM(G61:J61)*90) -> 0 | N61: =K61+L61-M61 -> 0
K62: =SUM(SUM(B62:F62)*360,SUM(G62:J62)*90) -> 0 | N62: =K62+L62-M62 -> 0
K63: =SUM(SUM(B63:F63)*360,SUM(G63:J63)*90) -> 0 | N63: =K63+L63-M63 -> 0
K64: =SUM(SUM(B64:F64)*360,SUM(G64:J64)*90) -> 0 | N64: =K64+L64-M64 -> 0
K65: =SUM(SUM(B65:F65)*360,SUM(G65:J65)*90) -> 0 | N65: =K65+L65-M65 -> 0
K66: =SUM(SUM(B66:F66)*360,SUM(G66:J66)*90) -> 0 | N66: =K66+L66-M66 -> 0
K67: =SUM(SUM(B67:F67)*360,SUM(G67:J67)*90) -> 0 | N67: =K67+L67-M67 -> 0
K68: =SUM(SUM(B68:F68)*360,SUM(G68:J68)*90) -> 0 | N68: =K68+L68-M68 -> 0
K69: =SUM(SUM(B69:F69)*360,SUM(G69:J69)*90) -> 0 | N69: =K69+L69-M69 -> 0
... K101: =SUM(SUM(B101:F101)*360,SUM(G101:J101)*90) -> 0 | N101: =K101+L101-M101 -> 0

Sheet 22
A1: 日報表
A5: 銷售明細 | R5: 總結
A6: 類別 | B6: 禮盒 | G6: 單顆 | K6: 金額
A7: 購買人 | B7: 綜合 | C7: 原味 | D7: 可可 | E7: 伯爵 | F7: 抹茶 | G7: 原味. | H7: 可可. | I7: 伯爵. | J7: 抹茶. | K7: 金額 | L7: 運費 | M7: 折讓金額 | N7: 實收金額 | O7: 欄1 | P7: 備註
K8: =SUM(SUM(B8:F8)*360,SUM(G8:J8)*90) -> 0 | N8: =K8+L8-M8 -> 0 | R8: 金流 | X8: 應收帳款 | AB8: 今日未結帳款清單 | AC8: 今日銷帳清單
K9: =SUM(SUM(B9:F9)*360,SUM(G9:J9)*90) -> 0 | N9: =K9+L9-M9 -> 0 | R9: 營業總額 | T9: 運費 | U9: =SUMIF(表格1_33451525354555657585960616263646566676869[欄1],"<>公關品",表格1_33451525354555657585960616263646566676869[運費]) -> 0 | X9: 累積未結 | Y9: =INDEX('21'!Y12:Z13,1,1) -> 31984 | AB9: {=_xlfn.LET(_xlpm.unpaid,_xlfn.UNIQUE(_xlfn._xlws.FILTER(A8:A100,O8:O100="未結帳款","今日無欠款")),IF(_xlpm.unpaid="今日無欠款","今日無欠款",_xlpm.unpaid&"："&SUMIFS(N8:N100,A8:A100,_xlpm.unpaid,O8:O100,"未結帳款")))} -> 今日無欠款 | AC9: {=_xlfn.LET(_xlpm.paid,_xlfn.UNIQUE(_xlfn._xlws.FILTER(A8:A100,P8:P100="銷帳","今日無銷帳")),IF(_xlpm.paid="今日無銷帳","今日無銷帳",_xlpm.paid&"："&SUMIFS(N8:N100,A8:A100,_xlpm.paid,P8:P100,"銷帳")))} -> 今日無銷帳
K10: =SUM(SUM(B10:F10)*360,SUM(G10:J10)*90) -> 0 | N10: =K10+L10-M10 -> 0 | R10: =SUM(K8:K101)-V15 -> 0 | T10: 折讓 | U10: =SUM(M8:M101) -> 0 | X10: 今日未結 | Y10: =U15 -> 0
K11: =SUM(SUM(B11:F11)*360,SUM(G11:J11)*90) -> 0 | N11: =K11+L11-M11 -> 0 | R11: 營業額 | T11: 公關品 | U11: =SUMIF(P8:P100,"公關品",K8:K103) -> 0 | X11: 今日回款 | Y11: =V15 -> 0
K12: =SUM(SUM(B12:F12)*360,SUM(G12:J12)*90) -> 0 | N12: =K12+L12-M12 -> 0 | R12: =R10-U10-U11 -> 0 | T12: 應收 | V12: 實收 | X12: 剩餘未結 | Y12: =Y9+Y10-Y11 -> 31984
K13: =SUM(SUM(B13:F13)*360,SUM(G13:J13)*90) -> 0 | N13: =K13+L13-M13 -> 0 | T13: 匯款 | U13: =SUMIF(O8:O101,"匯款",N8:N101) -> 0
K14: =SUM(SUM(B14:F14)*360,SUM(G14:J14)*90) -> 0 | N14: =K14+L14-M14 -> 0 | T14: 現金 | U14: =SUMIF(O8:O102,"現金",N8:N102) -> 0
K15: =SUM(SUM(B15:F15)*360,SUM(G15:J15)*90) -> 0 | N15: =K15+L15-M15 -> 0 | T15: 未結帳款 | U15: =SUMIF(O8:O102,"未結帳款",N8:N103) -> 0 | V15: =SUMIF(P8:P100,"銷帳",N8:N100) -> 0
K16: =SUM(SUM(B16:F16)*360,SUM(G16:J16)*90) -> 0 | N16: =K16+L16-M16 -> 0 | T16: 銷帳 | X16: 物流
K17: =SUM(SUM(B17:F17)*360,SUM(G17:J17)*90) -> 0 | N17: =K17+L17-M17 -> 0 | R17: 商品銷售量 | X17: 運費實收 | Y17: =U9 -> 0
K18: =SUM(SUM(B18:F18)*360,SUM(G18:J18)*90) -> 0 | N18: =K18+L18-M18 -> 0 | T18: 販售量 | U18: 公關品 | V18: 總盒數 | X18: 運費實支
K19: =SUM(SUM(B19:F19)*360,SUM(G19:J19)*90) -> 0 | N19: =K19+L19-M19 -> 0 | R19: 禮盒 | S19: 綜合 | T19: =SUMIF(P8:P102,"<>公關品",B8:B100) -> 0 | U19: =SUMIF(P8:P102,"公關品",B8:B100) -> 0 | V19: =SUM(T19:T23,U19) -> 0 | X19: 公關運費 | Y19: =SUMIF(P8:P100,"公關品",L8:L100) -> 0
K20: =SUM(SUM(B20:F20)*360,SUM(G20:J20)*90) -> 0 | N20: =K20+L20-M20 -> 0 | S20: 原味 | T20: =SUMIF(P8:P102,"<>公關品",C8:C100) -> 0 | U20: =SUMIF(P8:P102,"公關品",C8:C100) -> 0 | V20: 總顆數 | X20: 物流包材 | Y20: =SUM(Z24:Z27) -> 0
K21: =SUM(SUM(B21:F21)*360,SUM(G21:J21)*90) -> 0 | N21: =K21+L21-M21 -> 0 | S21: 可可 | T21: =SUMIF(P8:P104,"<>公關品",D8:D102) -> 0 | U21: =SUMIF(P8:P102,"公關品",D8:D100) -> 0 | X21: 成本差額 | Y21: =Y17-Y18-Y20+Y19 -> 0
K22: =SUM(SUM(B22:F22)*360,SUM(G22:J22)*90) -> 0 | N22: =K22+L22-M22 -> 0 | S22: 伯爵 | T22: =SUMIF(P8:P102,"<>公關品",E8:E100) -> 0 | U22: =SUMIF(P8:P102,"公關品",E8:E100) -> 0 | X22: 物流包材
K23: =SUM(SUM(B23:F23)*360,SUM(G23:J23)*90) -> 0 | N23: =K23+L23-M23 -> 0 | S23: 抹茶 | T23: =SUMIF(P8:P102,"<>公關品",F8:F100) -> 0 | U23: =SUMIF(P8:P102,"公關品",F8:F100) -> 0 | X23: 種類 | Y23: 數量 | Z23: 總額
K24: =SUM(SUM(B24:F24)*360,SUM(G24:J24)*90) -> 0 | N24: =K24+L24-M24 -> 0 | R24: 單顆 | S24: 原味 | T24: =SUMIF(P9:P103,"<>公關品",G8:G100) -> 0 | U24: =SUMIF(P8:P102,"公關品",G8:G100) -> 0 | V24: =T19+(T20*4)+T24 -> 0 | X24: 2入紙箱
K25: =SUM(SUM(B25:F25)*360,SUM(G25:J25)*90) -> 0 | N25: =K25+L25-M25 -> 0 | S25: 可可 | T25: =SUMIF(P8:P102,"<>公關品",H8:H100) -> 0 | U25: =SUMIF(P8:P102,"公關品",I8:I100) -> 0 | V25: =T19+(T21*4)+T25 -> 0 | X25: 4入紙箱 | Z25: =Y25*5 -> 0
K26: =SUM(SUM(B26:F26)*360,SUM(G26:J26)*90) -> 0 | N26: =K26+L26-M26 -> 0 | S26: 伯爵 | T26: =SUMIF(P9:P103,"<>公關品",I8:I100) -> 0 | U26: =SUMIF(P8:P102,"公關品",I8:I100) -> 0 | V26: =T19+(T22*4)+T26 -> 0 | X26: 10入紙箱
K27: =SUM(SUM(B27:F27)*360,SUM(G27:J27)*90) -> 0 | N27: =K27+L27-M27 -> 0 | S27: 抹茶 | T27: =SUMIF(P8:P102,"<>公關品",J8:J100) -> 0 | U27: =SUMIF(P9:P103,"公關品",J8:J100) -> 0 | V27: =T19+(T23*4)+T27 -> 0 | X27: 膠帶
K28: =SUM(SUM(B28:F28)*360,SUM(G28:J28)*90) -> 0 | N28: =K28+L28-M28 -> 0
K29: =SUM(SUM(B29:F29)*360,SUM(G29:J29)*90) -> 0 | N29: =K29+L29-M29 -> 0
K30: =SUM(SUM(B30:F30)*360,SUM(G30:J30)*90) -> 0 | N30: =K30+L30-M30 -> 0 | R30: 產能及庫存 | AB30: 今日公關品總結
K31: =SUM(SUM(B31:F31)*360,SUM(G31:J31)*90) -> 0 | N31: =K31+L31-M31 -> 0 | AB31: 總禮盒數 | AC31: =SUM(U19:U23) -> 0
K32: =SUM(SUM(B32:F32)*360,SUM(G32:J32)*90) -> 0 | N32: =K32+L32-M32 -> 0 | R32: 品項 | S32: 原庫存 | T32: 預計產量 | U32: 實際產量 | V32: 耗損 | W32: 實際銷售量 | Y32: 今日庫存 | Z32: 總損耗率 | AB32: 總顆數 | AC32: =SUM(AC33:AC36) -> 0
K33: =SUM(SUM(B33:F33)*360,SUM(G33:J33)*90) -> 0 | N33: =K33+L33-M33 -> 0 | R33: 原味 | S33: ='21'!Y33 -> 0 | V33: =SUMIF(R40:R55,"原味",S40:S55) -> 0 | W33: =V24+U24+U19+U20*4 -> 0 | Y33: =S33+U33-V33-W33 -> 0 | Z33: =IFERROR((V33/(U33+S33))," ") | AB33: 原味 | AC33: =U24+U19+U20*4 -> 0
K34: =SUM(SUM(B34:F34)*360,SUM(G34:J34)*90) -> 0 | N34: =K34+L34-M34 -> 0 | R34: 可可 | S34: ='21'!Y34 -> 0 | V34: =SUMIF(R41:R55,"可可",S41:S55) -> 0 | W34: =V25+U25+U19+U21*4 -> 0 | Y34: =S34+U34-V34-W34 -> 0 | Z34: =IFERROR((V34/(U34+S34))," ") | AB34: 可可 | AC34: =U25+U19+U21*4 -> 0
K35: =SUM(SUM(B35:F35)*360,SUM(G35:J35)*90) -> 0 | N35: =K35+L35-M35 -> 0 | R35: 伯爵 | S35: ='21'!Y35 -> 0 | V35: =SUMIF(R41:R55,"伯爵",S41:S55) -> 0 | W35: =V26+U26+U19+U22*4 -> 0 | Y35: =S35+U35-V35-W35 -> 0 | Z35: =IFERROR((V35/(U35+S35))," ") | AB35: 伯爵 | AC35: =U26+U19+U22*4 -> 0
K36: =SUM(SUM(B36:F36)*360,SUM(G36:J36)*90) -> 0 | N36: =K36+L36-M36 -> 0 | R36: 抹茶 | S36: ='21'!Y36 -> 0 | V36: =SUMIF(R41:R55,"抹茶",S41:S55) -> 0 | W36: =V27+U27+U19+U23*4 -> 0 | Y36: =S36+U36-V36-W36 -> 0 | Z36: =IFERROR((V36/(U36+S36))," ") | AB36: 抹茶 | AC36: =U27+U19+U23*4 -> 0
K37: =SUM(SUM(B37:F37)*360,SUM(G37:J37)*90) -> 0 | N37: =K37+L37-M37 -> 0
K38: =SUM(SUM(B38:F38)*360,SUM(G38:J38)*90) -> 0 | N38: =K38+L38-M38 -> 0 | R38: 損耗原因
K39: =SUM(SUM(B39:F39)*360,SUM(G39:J39)*90) -> 0 | N39: =K39+L39-M39 -> 0
K40: =SUM(SUM(B40:F40)*360,SUM(G40:J40)*90) -> 0 | N40: =K40+L40-M40 -> 0 | R40: 品項 | S40: 數量 | T40: 類別 | U40: 原因
K41: =SUM(SUM(B41:F41)*360,SUM(G41:J41)*90) -> 0 | N41: =K41+L41-M41 -> 0
K42: =SUM(SUM(B42:F42)*360,SUM(G42:J42)*90) -> 0 | N42: =K42+L42-M42 -> 0
K43: =SUM(SUM(B43:F43)*360,SUM(G43:J43)*90) -> 0 | N43: =K43+L43-M43 -> 0
K44: =SUM(SUM(B44:F44)*360,SUM(G44:J44)*90) -> 0 | N44: =K44+L44-M44 -> 0
K45: =SUM(SUM(B45:F45)*360,SUM(G45:J45)*90) -> 0 | N45: =K45+L45-M45 -> 0
K46: =SUM(SUM(B46:F46)*360,SUM(G46:J46)*90) -> 0 | N46: =K46+L46-M46 -> 0
K47: =SUM(SUM(B47:F47)*360,SUM(G47:J47)*90) -> 0 | N47: =K47+L47-M47 -> 0
K48: =SUM(SUM(B48:F48)*360,SUM(G48:J48)*90) -> 0 | N48: =K48+L48-M48 -> 0
K49: =SUM(SUM(B49:F49)*360,SUM(G49:J49)*90) -> 0 | N49: =K49+L49-M49 -> 0
K50: =SUM(SUM(B50:F50)*360,SUM(G50:J50)*90) -> 0 | N50: =K50+L50-M50 -> 0
K51: =SUM(SUM(B51:F51)*360,SUM(G51:J51)*90) -> 0 | N51: =K51+L51-M51 -> 0
K52: =SUM(SUM(B52:F52)*360,SUM(G52:J52)*90) -> 0 | N52: =K52+L52-M52 -> 0
... K56: =SUM(SUM(B56:F56)*360,SUM(G56:J56)*90) -> 0 | N56: =K56+L56-M56 -> 0
K57: =SUM(SUM(B57:F57)*360,SUM(G57:J57)*90) -> 0 | N57: =K57+L57-M57 -> 0 | R57: 備註
K58: =SUM(SUM(B58:F58)*360,SUM(G58:J58)*90) -> 0 | N58: =K58+L58-M58 -> 0
K59: =SUM(SUM(B59:F59)*360,SUM(G59:J59)*90) -> 0 | N59: =K59+L59-M59 -> 0
K60: =SUM(SUM(B60:F60)*360,SUM(G60:J60)*90) -> 0 | N60: =K60+L60-M60 -> 0
K61: =SUM(SUM(B61:F61)*360,SUM(G61:J61)*90) -> 0 | N61: =K61+L61-M61 -> 0
K62: =SUM(SUM(B62:F62)*360,SUM(G62:J62)*90) -> 0 | N62: =K62+L62-M62 -> 0
K63: =SUM(SUM(B63:F63)*360,SUM(G63:J63)*90) -> 0 | N63: =K63+L63-M63 -> 0
K64: =SUM(SUM(B64:F64)*360,SUM(G64:J64)*90) -> 0 | N64: =K64+L64-M64 -> 0
K65: =SUM(SUM(B65:F65)*360,SUM(G65:J65)*90) -> 0 | N65: =K65+L65-M65 -> 0
K66: =SUM(SUM(B66:F66)*360,SUM(G66:J66)*90) -> 0 | N66: =K66+L66-M66 -> 0
K67: =SUM(SUM(B67:F67)*360,SUM(G67:J67)*90) -> 0 | N67: =K67+L67-M67 -> 0
K68: =SUM(SUM(B68:F68)*360,SUM(G68:J68)*90) -> 0 | N68: =K68+L68-M68 -> 0
K69: =SUM(SUM(B69:F69)*360,SUM(G69:J69)*90) -> 0 | N69: =K69+L69-M69 -> 0
... K101: =SUM(SUM(B101:F101)*360,SUM(G101:J101)*90) -> 0 | N101: =K101+L101-M101 -> 0

Sheet 23
A1: 日報表
A5: 銷售明細 | R5: 總結
A6: 類別 | B6: 禮盒 | G6: 單顆 | K6: 金額
A7: 購買人 | B7: 綜合 | C7: 原味 | D7: 可可 | E7: 伯爵 | F7: 抹茶 | G7: 原味. | H7: 可可. | I7: 伯爵. | J7: 抹茶. | K7: 金額 | L7: 運費 | M7: 折讓金額 | N7: 實收金額 | O7: 欄1 | P7: 備註
K8: =SUM(SUM(B8:F8)*360,SUM(G8:J8)*90) -> 0 | N8: =K8+L8-M8 -> 0 | R8: 金流 | X8: 應收帳款 | AB8: 今日未結帳款清單 | AC8: 今日銷帳清單
K9: =SUM(SUM(B9:F9)*360,SUM(G9:J9)*90) -> 0 | N9: =K9+L9-M9 -> 0 | R9: 營業總額 | T9: 運費 | U9: =SUMIF(表格1_3345152535455565758596061626364656667686970[欄1],"<>公關品",表格1_3345152535455565758596061626364656667686970[運費]) -> 0 | X9: 累積未結 | Y9: =INDEX('22'!Y12:Z13,1,1) -> 31984 | AB9: {=_xlfn.LET(_xlpm.unpaid,_xlfn.UNIQUE(_xlfn._xlws.FILTER(A8:A100,O8:O100="未結帳款","今日無欠款")),IF(_xlpm.unpaid="今日無欠款","今日無欠款",_xlpm.unpaid&"："&SUMIFS(N8:N100,A8:A100,_xlpm.unpaid,O8:O100,"未結帳款")))} -> 今日無欠款 | AC9: {=_xlfn.LET(_xlpm.paid,_xlfn.UNIQUE(_xlfn._xlws.FILTER(A8:A100,P8:P100="銷帳","今日無銷帳")),IF(_xlpm.paid="今日無銷帳","今日無銷帳",_xlpm.paid&"："&SUMIFS(N8:N100,A8:A100,_xlpm.paid,P8:P100,"銷帳")))} -> 今日無銷帳
K10: =SUM(SUM(B10:F10)*360,SUM(G10:J10)*90) -> 0 | N10: =K10+L10-M10 -> 0 | R10: =SUM(K8:K101)-V15 -> 0 | T10: 折讓 | U10: =SUM(M8:M101) -> 0 | X10: 今日未結 | Y10: =U15 -> 0
K11: =SUM(SUM(B11:F11)*360,SUM(G11:J11)*90) -> 0 | N11: =K11+L11-M11 -> 0 | R11: 營業額 | T11: 公關品 | U11: =SUMIF(P8:P100,"公關品",K8:K103) -> 0 | X11: 今日回款 | Y11: =V15 -> 0
